[{"zh": ["現在", "被", "綁", "在", "地窖", "的", "是", "你"], "en": "You're the one tied up in a basement."}, {"zh": ["地窖", "是", "最", "安全", "的", "地方"], "en": "Look, the cellar's the safest place."}, {"zh": ["看看", "有", "沒", "有", "地窖"], "en": "(DISTANT MEN CHATTERING) See if there's a larder."}, {"zh": ["但", "我", "不", "準備", "讓", "我", "的", "信念", " ", "屈從", "於", "我", "的", "意願", "或", "我", "的", "需要"], "en": "But I'm not prepared to let my--beliefs be determined by my desires or my--needs."}, {"zh": ["我們", "能", "做", "的", "只有", "屈從", "於", "命運", "。"], "en": "All we can do is try to appeal to fate."}, {"zh": ["你", "不", "該", "在", "我", "這個", "瘋", "老頭子", "身上", "浪費", "時間"], "en": "You shouldn't be wasting your time with a crazy old man."}, {"zh": ["而", "這些", "都", "是", "由", "你", "們", "這些", "老頭子", "引起", "的"], "en": "And it all starts with the elders."}, {"zh": ["我", "只", "知道", "他", "是", "個", "可愛的", "老頭子"], "en": "Anyway, all I know is that he's a darling old man."}, {"zh": ["不", "小心", "把", "它", "的", "手機", "收到", "道具", "組"], "en": "We collected his real phone by accident."}, {"zh": ["希望", "她", "們", "不要", "有", "道具"], "en": "Let's hope there are no props."}, {"zh": ["這是", "我", "弄", "來", "的", "道具"], "en": "I found these at Goodwill."}, {"zh": ["", "", "癸", "и", "", "痷", "", "", "礚", "┮", ""], "en": "You really don't know anything about us."}, {"zh": ["你", "不", "就", "找", "了", "年", "長", "的", "對象", "嗎"], "en": "It's okay for you to take an older lover?"}, {"zh": ["不", "可能", "再", "找到", "這麼", "好", "的", "對象"], "en": "A proposal as opportune as this will not come to us again."}, {"zh": ["你們", "把", "他", "帶", "來", "警局", "很", "好"], "en": "It's good you brought him in."}, {"zh": ["完", "了", "後", "我們", "馬", "上", "就", "去", "警局"], "en": "After that we will go to the police."}, {"zh": ["我", "很快", "就", "會", "在", "警局", "被", "抓", "到", "了"], "en": "I'm about to be found out at work for what I really am."}, {"zh": ["我", "昨天", "把子", "彈", "拿出", "來", "了"], "en": "It was me. I emptied the clip yesterday."}, {"zh": ["如果", "我能", "把子", "彈", "碎片", "拿出", "來"], "en": "If I can get the bullet fragments out..."}, {"zh": ["我們", "把子", "彈", "取出", "來", "了"], "en": "We were able to remove the bullet."}, {"zh": ["她", "送", "了", "頭嗲利狗給", "我"], "en": "She bought me an Airedale terrier, who I love."}, {"zh": ["易", "先生", "啊", "，", "易", "太太", "都", "發", "嗲", "了"], "en": "Mr. Yee. Look how sweet Yee Tai Tai is with you."}, {"zh": ["如果", "我要", "變", "呀", " ", "我", "變個", "又", "索", "又", "嗲"], "en": "I want a much hotter, much sultry BO,"}, {"zh": ["我", "認為", "在", "理查德", "的", "身上", "她", "找到", "了", "她", "要", "找", "的", "東西"], "en": "I think she found what she was looking for in Richard."}, {"zh": ["就", "說", "理查德", "讓", "你", "來", "的"], "en": "Say Richard sent you."}, {"zh": ["你", "知道", "我", "和", "理查德", "沒法", "生活", "下去", "的"], "en": "You know my life with Richard isn't working."}, {"zh": ["既然", "你", "認得", "我", "是", "太子", "炳", "的", "女兒"], "en": "We must move him out before the Police Chief arrives."}, {"zh": ["我們", "派", "真正", "的", "太子", "去"], "en": "We shall send a real prince"}, {"zh": ["太子", "想", "站", "到", "輪胎", "上"], "en": "Cause Taz wants to go on the tire"}, {"zh": ["不", "可能", "有", "白蘭地", "的"], "en": "Yes,butwe don't have any brandy."}, {"zh": ["下次", "我給", "他", "帶", "白蘭地"], "en": "I'll bring him brandy next time."}, {"zh": ["是", "你", "指使", "那", "傢", "伙", "偷", "我", "的", "錢", "是", "吧"], "en": "You had that guy steal my money."}, {"zh": ["但", "他", "找", "你", "要", "錢", "可不是", "我", "指使", "的"], "en": "But I had nothing to do with him coming after your money."}, {"zh": ["是不是", "有人", "讓", "你", "指使", "你", "那麼", "說", "的"], "en": "Did someone incite you to say all these?"}, {"zh": ["他", "回來", "的", "時候", "我", "能", "從", "他", "手上", "聞到"], "en": "When he came to bed, I could smell dirt on his hands, and I think..."}, {"zh": ["不能", "讓", "他", "在", "我", "身上", "聞到", "你", "的", "味道"], "en": "Wouldn't want him to smell you on me."}, {"zh": ["我", "喜歡", "在", "早上", "聞到", "肉", "的", "味道"], "en": "I love the smell of fleshies in the morning."}, {"zh": ["農作", "被", "撿", "光", "了"], "en": "Field's picked clean."}, {"zh": ["暫停", "收成", "農作"], "en": "The harvest must wait."}, {"zh": ["現在", "沒", "了", "，", "農作", "幾乎", "都", "沒", "了"], "en": "No. Not now, with half the crop gone."}, {"zh": ["你", "要", "告訴", "所有人", "小心", "被", "暗算"], "en": "You get word to everybody: eyes in the back of your head,"}, {"zh": ["那些", "流氓", "會", "在", "背", "後", "暗算", "你"], "en": "They plot all kinds of shit behind your back."}, {"zh": ["他", "總", "是", "注視", "著", "我", "想", "著", "我", "的", "事情"], "en": "He always looks out for me and thinks about me."}, {"zh": ["你", "要", "在", "那些", "人", "的", "注視", "中", "上學"], "en": "You have to go to school under their gaze"}, {"zh": ["我", "不會", "再", "注視", "著", "你", "了"], "en": "My eyes don't see you anymore."}, {"zh": ["你", "在", "這", "裏", "能", "找到", "的", "唯一", "工作", " ", "就是", "躺", "在", "松木", "棺材", "裏"], "en": "The only job you're gonna get in here is pushin' up daisies from a pine box."}, {"zh": ["松木"], "en": "Pine."}, {"zh": ["其實", "是", "松木", "和", "楓木"], "en": "No, it's pine and maple."}, {"zh": ["我", "迂回", "著", "走", " ", "挑", "硬地", "走", " ", "就", "為", "了", "別", "留下", "蹤", "跡"], "en": "I went way around, stayed on hard ground which wouldn't show the tracks."}, {"zh": ["又", "走", "開", "了", " ", "看來", "他", "在", "迂回"], "en": "They go way back. He nurtured her or something."}, {"zh": ["你", "得", "做", "一些", "迂回"], "en": "Well, we're gonna retrace your steps a bit."}, {"zh": ["可", "我", "母親", "讓", "我", "好好", "提防", "你", "呢"], "en": "My mother warned me not to trust you."}, {"zh": ["我", "母親", "讓", "我", "好好", "提防", "你", "呢"], "en": "My mother warned me not to trust you."}, {"zh": ["戒嚴", "時間", "馬", "上", "就", "到", "了"], "en": "- The curfew will begin shortly."}, {"zh": ["總統", "宣", "佈", "在", "德州", "實行", "戒嚴"], "en": "The president has declared martial law in Texas."}, {"zh": ["似乎", "那", "是", "個", "存放", "東西", "的", "好", "地方"], "en": "It does seem as safe a place to keep them as any."}, {"zh": ["那", "就是", "我們", "要", "存放", "它", "的", "地方"], "en": "That's where we're gonna put it."}, {"zh": ["她", "要", "找", "的", "是", "他", "存放", "機密", "的", "地方"], "en": "She needs to find where he kept his secrets."}, {"zh": ["你", "是", "說", "你", "不", "知道", "你", "的", "孫女", "住", "哪兒"], "en": "You don't know where your grandchild lives?"}, {"zh": ["我覺", "得", "我", "認識", "自己", "的", "孫女"], "en": "I think I know my own granddaughter."}, {"zh": ["他", "從", "不", "提及", "她", "或者", "他", "弟弟"], "en": "He never talks about her or his brother."}, {"zh": ["所有", "那些", "我", "不想", "提及", "的", "事"], "en": "All these things that I did not want to talk about."}, {"zh": ["是", "非常", "漫不經心", "的", "關心"], "en": "An absentminded attention."}, {"zh": ["不能", "漫不經心", "的", "樣子"], "en": "So, there's nothing cavalier about it."}, {"zh": ["我", "看不出", "你", "是", "在", "故意", "漫不經心", " ", "還是", "真的", "精神", "不", "穩定"], "en": "I can't really tell if you're purposely being contemptuous, of maybe you are unstable."}, {"zh": ["然后", "你", "轉向", "她", "然后", "你們", "倆", "都", "坐下"], "en": "Then you turn toward her, and you both sit down."}, {"zh": ["他", "轉向", "倒", "在", "地上", "的", "那", "傢", "伙"], "en": "He turned to the guy on the floor."}, {"zh": ["你", "和", "你", "的", "村民", "已經", "轉向", "我們", "了"], "en": "You and the villagers have turned against one of your own."}, {"zh": ["她", "整個", "人", "都", "跟", "以前", "相差", "很多"], "en": "Everything about her, not just her home, was less than before."}, {"zh": ["和", "我", "的", "朋友", "相差", "很多"], "en": "Different from all the people I know."}, {"zh": ["我", "的", "行為", "與", "他們", "的", "期望", "相差", "甚遠"], "en": "I wasn't very good at doing things the way they're supposed to be done."}, {"zh": ["她", "所有", "的", "藍寶石", "都", "不如", "這個", "讓", "我", "開心"], "en": "And that makes me happier than all her sapphires."}, {"zh": ["別", "再給", "我", "買", "鑽石", "或者", "藍寶石", "之類", "的", "了"], "en": "Don't buy me any more diamonds or sapphires or any other damn thing."}, {"zh": ["藍寶石", "的", "事情", "我", "很", "抱歉"], "en": "Sorry about the sapphires."}, {"zh": ["看來", "你", "需要", "個", "新", "的", "膠帶"], "en": "Looks like you need a new bandage."}, {"zh": ["把", "膠帶", "拿", "來"], "en": "And get the duct tape"}, {"zh": ["我們", "猜想", "他們", "藏", "在", "這片", "區域", "以及", "向東", "的", "地方"], "en": "We think they're hiding it in homes in this area and towards the east."}, {"zh": ["嫌犯", "車輛", "在", "湖濱", "大道", "向東"], "en": "Suspect vehicle turning east on Lakeshore."}, {"zh": ["我們", "何不", "給", "莉莉", "唱", "催眠曲"], "en": "Hey, why don't we all sing Lily a sleep tight song?"}, {"zh": ["這首", "催眠曲", "效果", "最好"], "en": "Hey, the lullaby worked better than ever."}, {"zh": ["然後貓", "媽媽", "開始", "唱", "催眠曲"], "en": "\"Then their mother sang a lullaby.\""}, {"zh": ["道奇", "隊", "的", "比賽", "開始", "囉"], "en": "It's time for Dodger baseball."}, {"zh": ["足夠", "的", "時間", "離開", "道奇", "車"], "en": "Plenty of time to get the hell out of Dodge."}, {"zh": ["喜歡", "道奇", "隊", "嗎"], "en": "You like the Dodgers?"}, {"zh": ["別", "把", "蛤蜊", "醬", "的", "味道", "吹", "在", "我", "身上"], "en": "Stop breathing that clam sauce on me."}, {"zh": ["這里", "的", "白", "蛤蜊", "醬", "是", "最好", "的"], "en": "White clam sauce. The best."}, {"zh": ["他們", "不會", "吃光", "所有", "的", "蛤蜊"], "en": "The flock never taking all the clams."}, {"zh": ["只", "因為", "你", "收購", "了", "我", "工作", "的", "商店"], "en": "Only because you bought the store that I work at! No, I didn't."}, {"zh": ["他們", "想", "收購", "那", "房子", "的", "所有", "權"], "en": "They're interested in purchasing the property."}, {"zh": ["我們", "要", "被", "收購", "了"], "en": "We're being taken over."}, {"zh": ["日", "復", "一日", "，", "她", "用心", "工作", " ", "用雙", "巧手", "把", "老", "破屋", "變成", "溫馨", "的", "家"], "en": "Day after day she worked away, remaking the old Granville house into a home."}, {"zh": ["用", "你", "這雙大", "巧手", "來個", "足底", "按摩", "怎麼樣", "?"], "en": "Yeah, how about a foot massage with those big, gorgeous hands of yours?"}, {"zh": ["我", "猜", "你", "還有", "奶水"], "en": "I'd say you're fresh."}, {"zh": ["我", "的", "奶水", "不好"], "en": "My milk is not good."}, {"zh": ["我用", "自己", "的", "奶水", "餵養", "他"], "en": "I have fed him my milk."}, {"zh": ["你", "不能", "把", "武器", "帶進", "營房"], "en": "You can't have any weapons in the camp."}, {"zh": ["其他人", "都", "右", "轉進", "了", "營房", "和", "食堂"], "en": "-Everyone else turned right, toward the barracks and the mess."}, {"zh": ["我們", "殺", "了", "它", "媽媽", "是", "不得已", "的"], "en": "We've taken its mammy and it weren't to blame."}, {"zh": ["我們", "是", "不得已", "才", "這樣", "說", "的"], "en": "We had to say we were circus."}, {"zh": ["他", "那", "是", "不得已", "而", "為", "之"], "en": "People do what they have to do."}, {"zh": ["他們", "說", "你", "以前", "是", "打拳", "的"], "en": "The boys tell me you used to box before you came here."}, {"zh": ["但", "我", "不想", "再", "回去", "打拳", "了"], "en": "I don't wanna go back to boxing."}, {"zh": ["我", "不", "相信", "你", "想", "打拳"], "en": "I can't believe you want to box."}, {"zh": ["姐", "蛆"], "en": "My dearest friend..."}, {"zh": ["小姐", "，", "妳", "的", "腳", "已", "經長", "蛆", "了", " ", "就", "得", "犧牲", "妳", "的", "腳換", "妳", "的", "命"], "en": "Young lady, you get gangrene in your foot, you sacrifice your whole leg to save the rest."}, {"zh": ["我", "說", "能", "有", "你", "是", "他們", "的", "福氣"], "en": "I said them they'd be lucky to have you."}, {"zh": ["有", "你", "這樣", "的", "妻子", "真是", "我", "的", "福氣"], "en": "I'm so lucky for having a wife like you."}, {"zh": ["我們", "有", "她", "也", "是", "我們", "的", "福氣"], "en": "She's a blessing to us, too."}, {"zh": ["才能", "做出", "想要", "的", "和弦"], "en": "to reach harmony"}, {"zh": ["多", "美妙", "的", "和弦", "連接", "啊"], "en": "Sweet chord of connectivity."}, {"zh": ["每個", "音符", "都", "在", "尋找", "和弦"], "en": "Notes... all... search... harmony."}, {"zh": ["說", "不定", "你", "到", "時候", "就", "上西天", "了"], "en": "Maybe, by that time, you'll die of old age."}, {"zh": ["它", "只會", "送", "你", "們", "上西天"], "en": "It is the tinder on which you burn."}, {"zh": ["你", "等", "著", "上西天", "吧"], "en": "It is your requiem mass, boy."}, {"zh": ["你", "應該", "陪", "媽媽", "去", "上", "探戈", "課"], "en": "You're supposed to be with mom at tango!"}, {"zh": ["你", "跟", "誰", "學", "的", "探戈"], "en": "- Where did you learn to tango?"}, {"zh": ["簡單", "就是", "探戈", "的", "魅力"], "en": "It's simple. That's what makes the tango so great."}, {"zh": ["我給", "他", "打", "了", "足量", "的", "疫苗"], "en": "I gave him a full dose of the vaccine."}, {"zh": ["足量", "的", "魚子", "醬"], "en": "Plenty of caviar."}, {"zh": ["你", "要", "知道", "肯定", "很", "開心", " ", "我", "拿到", "了", "足量", "的", "貼紙"], "en": "Well, you'll be pleased to know I have the requisite stickers."}, {"zh": ["能", "求援", "的", "家族", "我們", "都", "找過", "了"], "en": "We've pleaded with every house that'll have us."}, {"zh": ["她", "去", "找", "人", "求援"], "en": "She looked for help!"}, {"zh": ["我們", "可以", "向", "酒吧", "招待", "求援"], "en": "We can ask the man to help us."}, {"zh": ["但是", "我", "不想", "讓", "人們", "認為", "我", "是", "左翼", "魔鬼"], "en": "But I don't want people to think I'm some right-wing ogre."}, {"zh": ["而", "我", "的", "左翼", "也", "在", "進", "軍"], "en": "And my left flank moves forward..."}, {"zh": ["我", "正", "從", "你", "左翼", "通過"], "en": "Passing on the Left!"}, {"zh": ["我", "決定", "不", "接受", "這次", "的", "升遷"], "en": "I've decided not to pursue that."}, {"zh": ["別告訴", "我", "他", "又", "要", "放棄", "升遷", "了"], "en": "Don't tell me he's going to pass up another commission!"}, {"zh": ["也", "是", "你", "升遷", "的", "機會"], "en": "And by extension, to you. Yeah, no, sir."}, {"zh": ["她", "讓", "我", "替", "她", "在亞", "克朗", "市", "找個", "醫生"], "en": "Geez, she asked me to refer her to a doctor in akron."}, {"zh": ["克朗", "指揮官"], "en": "Commander Krang."}, {"zh": ["托姆", "斯", "克朗", "打", "的", "很", "好"], "en": "Good play by Thomas Crown. Looks like... it's a goal!"}, {"zh": ["我", "忘", "了", "告訴", "你", "那個", "清潔工", "的", "事"], "en": "The cleaning lady, I forgot to tell you..."}, {"zh": ["我", "不會", "讓", "那些", "清潔工", "失望", "的"], "en": "And I wouldn't let those janitors down."}, {"zh": ["我", "以", "為", "你", "是", "清潔工"], "en": "Oh. I thought you were the porter."}, {"zh": ["是", "我", "想", "出", "的", "構想", "使", "它", "能", "運作"], "en": "I'm the one that came up with the idea that made it work."}, {"zh": ["我", "再也", "沒", "地方", "構想", "你", "的", "模樣", "了"], "en": "I won't know where to picture you anymore."}, {"zh": ["我要", "告訴", "你", "這個", "構想", "如何"], "en": "So I'll tell you what I really think of your campaign."}, {"zh": ["現在", "已經", "是", "第五", "回合", "的", "半場", "了"], "en": "Here we are halfway through the fifth"}, {"zh": ["只", "看", "了", "後", "半場"], "en": "The last half."}, {"zh": ["他們", "說", "你", "是", "個", "自由", "思想家"], "en": "They say you're quite the free-thinker."}, {"zh": ["過去", "偉大", "思想家", "的", "腳步"], "en": "\"of the great imagineers of the past:"}, {"zh": ["你", "告訴", "我", "中情局", "那裡", "有", "你", "想要", "的", "東西"], "en": "You told me the CIA had something you wanted."}, {"zh": ["我", "是", "說", "你", "是", "怎麼", "進", "中情局", "的"], "en": "I mean, how did you get into the CIA?"}, {"zh": ["你", "看", "起來", "不", "像", "中情局", "的", "人"], "en": "You don't look like CIA."}, {"zh": ["我們", "與", "仇恨", "自己", "的", "人", "朝夕", "相處"], "en": "You live on intimate terms with people who hate you."}, {"zh": ["之后", "便", "與", "你", "們", "朝夕", "相處"], "en": "I've seen both your faces almost every day since."}, {"zh": ["我", "是", "說", "我們", "朝夕", "相處"], "en": "I mean, we work together and live together."}, {"zh": ["他", "腦袋", "瓜", "已", "迷迷糊糊"], "en": "His head's full of scars."}, {"zh": ["迷迷糊糊", "的", "樣子"], "en": "You were half asleep."}, {"zh": ["你", "知道", "我", "從", "不", "退回", "你給", "我", "的", "東西"], "en": "You know I never return anything you give me."}, {"zh": ["你", "是", "說", "我們", "該", "退回", "長", "城", "嗎"], "en": "You saying we should fall back to the Wall?"}, {"zh": ["被", "她", "退回", "來", "了"], "en": "She sent it back, man."}, {"zh": ["他們", "居然", "在", "保護", "墻", "而", "不是", "保護人"], "en": "Protecting the Wall instead of people."}, {"zh": ["你", "是", "指", "我", "的", "受", "保護人"], "en": "You mean my protégée?"}, {"zh": ["保鑣", "的", "工作", "就是", "緊", "跟", "著", "被", "保護人"], "en": "Cos, a bodyguard... What does a bodyguard do?"}, {"zh": ["讓", "那些", "庸人", "們", "喝茶", "吧"], "en": "Let the common herd drink tea."}, {"zh": ["謙遜", "的", "庸人"], "en": "Humility zombie philistine."}, {"zh": ["不要", "那麼", "庸人", "自擾"], "en": "Don't fuss so much."}, {"zh": ["只是", "覺得", "自然而然", "就", "該", "這樣", "了"], "en": "It just seemed like the next interesting thing to do."}, {"zh": ["自信", "會", "讓", "人", "自然而然", "的", "漂亮", "起來"], "en": "People become beautiful when you feel their confidence."}, {"zh": ["因為", "這", "就是", "自然而然", "的", "事"], "en": "Because it is natural."}, {"zh": ["歡迎", "來", "到", "我們", "的", "第一次", "爐邊", "談話"], "en": "And welcome to the very first mayor's fireside chat."}, {"zh": ["你", "到", "壁", "爐邊", "去", "取暖", "吧"], "en": "Why don't you go over there by the fireplace and get warm."}, {"zh": ["以及", "和", "您", "在", "爐邊", "共度", "傍晚"], "en": "And evenings by the fireside with your good self."}, {"zh": ["然后", "她", "用", "她", "的", "爪子", "抓住", "他"], "en": "And then she grabbed him with her claws."}, {"zh": ["我", "可", "不想", "把", "它", "的", "爪子", "弄", "濕", "了"], "en": "And I don't want to get his paws all soggy."}, {"zh": ["我", "的", "爪子", "從來", "沒", "這麼", "漂亮", "過"], "en": "My paws have never looked better."}, {"zh": ["我現", "在", "不能", "接聽", "你", "的", "電話", "請", "留言"], "en": "I cannot come to the phone right now, please leave a message."}, {"zh": ["他", "的", "電話", "是", "唯一", "需要", "接聽", "的"], "en": "That's the one phone call I would have taken."}, {"zh": ["我們", "會", "很快", "接聽", "您", "的", "電話"], "en": "We will be with you shortly."}, {"zh": ["又", "是", "何等", "恰如", "事實"], "en": "Isn't it indeed."}, {"zh": ["恰如", "螢火蟲"], "en": "They're like glow-worms."}, {"zh": ["又", "是", "諷刺", "話", " ", "但", "恰如", "其份"], "en": "Ironic again, but it suits you."}, {"zh": ["馬", "拉岡", "小姐", "被", "扣留", "在", "那里", "了"], "en": "Miss Maragon is being held there."}, {"zh": ["朱莉", "·", "馬", "拉岡", "是", "個", "淑女"], "en": "Julie Maragon's a lady."}, {"zh": ["我", "的", "朋友", "朱莉", "·", "馬", "拉岡", " ", "她", "是", "當地", "的", "教師"], "en": "My friend Julie Maragon. She's the local schoolteacher."}, {"zh": ["我要", "讓", "你", "在", "地牢", "流血", "而", "死"], "en": "I'll leave you bleeding in my dungeon"}, {"zh": ["我要", "把", "你", "扔", "進", "地牢"], "en": "I'll throw you in the dungeon!"}, {"zh": ["終于", "可以", "離開", "這個", "地牢", "了"], "en": "I am finally getting out of the dungeon."}, {"zh": ["大家", "都", "不願意", "再", "經歷", "近日", "來", "的", "恐怖", "時光"], "en": "We'll enter that sweet period where everyone agrees not to repeat the recent horrors."}, {"zh": ["我", "近日", "失去", "了", "最", "信任", "的", "顧問"], "en": "I recently lost my most trusted advisor to treachery."}, {"zh": ["洛頓", "兄弟", "公司", "近日", "的", "交易", "活動"], "en": "\"into recent Lawton Brothers trade activity.\""}, {"zh": ["無人", "之", "地", "從", "外側", "趕上"], "en": "No Man's Land moves up on the outside."}, {"zh": ["假設", "他", "沿著", "外側", "腳踝", "翻過", "去", " ", "我們", "差不多", "就", "穩操", "勝券", "了"], "en": "Let's say he does reel over with that outside ankle, that's pretty much game over."}, {"zh": ["左胸", "外側", "靠近", "肋骨", "骨折", "的", "區域", "顯示"], "en": "Oh, uh, areas on the left lateral thorax near the rib fractures show..."}, {"zh": ["就", "在", "威尼斯", "運", "河口", "上", "的", "華盛頓", "大道"], "en": "It's at the mouth of the Venice Canal, on Washington Boulevard."}, {"zh": ["河口", "深處", "還有", "狼", "人"], "en": "There are still wolves deep in the bayou,"}, {"zh": ["帶", "她", "去", "河口"], "en": "You'll take her to the bayou."}, {"zh": ["說", "不定", "是", "用", "那", "把", "小刀", "殉情", "自殺", "的"], "en": "She must have used it in a love suicide."}, {"zh": ["既", "沒", "有用", "來", "活命", "的", "時間", " ", "也", "沒", "有用", "來", "殉情", "的", "時間"], "en": "Neither time enough to live from it, nor time enough to die from it."}, {"zh": ["沒人", "記得", "有", "個", "帶", "著", "麻布", "面罩", "的", "男孩"], "en": "But no one remembered a child wearing a sack mask."}, {"zh": ["他", "的", "口袋", "只有", "刀子", "和", "麻布"], "en": "Nothing in his pockets but knives and lint."}, {"zh": ["咱們", "畢竟", "都", "是", "在", "這兒", "混飯", "吃"], "en": "After all, you work here and I work here."}, {"zh": ["我", "這輩子", "在", "這裡", "混飯", "吃"], "en": "I've made a living here all my life."}, {"zh": ["你", "以", "為", "你", "還能", "靠", "這四個", "字", "混飯", "吃", "嗎", "？"], "en": "Do you think you can still depend on this tattoo?"}, {"zh": ["也", "許他", "並不在", "伊爾庫茨克"], "en": "Maybe he's not in Irkutsk?"}, {"zh": ["我", "打", "聽", "到", "在", "伊爾庫茨克", "的", "賓館", "有", "一個", "美國人"], "en": "I have found a hotel in Irkutsk... that has an American guest."}, {"zh": ["不", " ", "他", "就", "在", "伊爾庫茨克", " ", "所以", "我", "才", "這樣問", "你"], "en": "No, no he is in Irkutsk. That's the whole point."}, {"zh": ["你", "把", "好", "貨色", "都", "藏", "在", "這里", "了", "嗎"], "en": "So this is where you stashed all the good stuff, huh ?"}, {"zh": ["大家", "都", "喜歡", "我們", "賣", "的", "貨色"], "en": "People seem to like what we're selling."}, {"zh": ["我", "就是", "上面", "寫", "的", "這種", "貨色"], "en": "This, me, right now, this is who I am."}, {"zh": ["有話", "好好", "說", "啊呀"], "en": "Take it easy."}, {"zh": ["啊呀", "，", "話", "可", "不能", "亂", "說"], "en": "Whoa, don't just throw words."}, {"zh": ["那", "我", "先", "去", "交", "原稿", "了"], "en": "I'll go deliver the drafts, then."}, {"zh": ["這是", "之前", "說", "好", "的", "原稿"], "en": "As promised, here is the manuscript."}, {"zh": ["在", "我給", "你", "看", "原稿", "之前"], "en": "Before I show you the manuscript,"}, {"zh": ["或許", "我們", "不", "需要", "摒棄"], "en": "Perhaps we need not discard them."}, {"zh": ["你", "要", "摒棄", "這種", "想法"], "en": "You have to banish that kind of thinking."}, {"zh": ["暫時", "摒棄", "你", "的", "震", "驚"], "en": "Edit out your initial shock."}, {"zh": ["我", "不要", "再", "聽", "到", "啥", "廢柴", "想法", "了"], "en": "I don't want any more negativity."}, {"zh": ["因為", "你", "要", "娶", "廢柴"], "en": "For marrying Zippy. Hey!"}, {"zh": ["好", "吧", "　", "可能", "是", "空穴", "來風"], "en": "- Yeah. Probably not even true."}, {"zh": ["這場", "合", "併", "案", "的", "謠傳", "是", "空穴", "來風"], "en": "There is absolutely no truth to the rumor of this merger."}, {"zh": ["去", "相信", "空穴", "來風", "的", "事"], "en": "You can make yourself believe anything."}, {"zh": ["我", "想", "她", "從", "來", "沒錯", "的", "那么", "離譜"], "en": "I don't remember her getting that much wrong before, do you?"}, {"zh": ["她", "的", "夢", "話", "都", "很", "離譜"], "en": "She says the craziest stuff in her sleep."}, {"zh": ["真", "遺憾", "她", "錯", "得", "這么", "離譜"], "en": "I'm sorry she was so wrong."}, {"zh": ["他", "在", "獄", "中", "靠", "販賣", "違", "禁品", "賺", "了", "很多", "錢"], "en": "Apparently, he made a lot of money running contraband in prison."}, {"zh": ["你明", "知道", "在", "這裡", "是", "違", "禁品"], "en": "You know this is not allowed in here. It's contraband."}, {"zh": ["要", "殺", "要剮", "隨", "你", "，", "放", "了", "她", " ", "別", "逞英雄", "了"], "en": "Do what you want with me, let her go. Don't play the hero with me."}, {"zh": ["要", "殺", "要剮", "隨便", "你", "們"], "en": "Bust her up; see if I care."}, {"zh": ["我", "的", "爸爸", "有", "足球", "傷患"], "en": "My father has an old football injury."}, {"zh": ["他", "說", "有", "傷患", "嗎"], "en": "Did he say \"we have casualties\"?"}, {"zh": ["我們", "找到", "個", "腹部", "傷患"], "en": "We got an abdominal wound."}, {"zh": ["她", "對", "我", "拳打", "腳", "踢", "的"], "en": "She punches me, slaps me, kicks me."}, {"zh": ["我", "吞", "你", "時", "你", "可別", "拳打", "腳", "踢"], "en": "Try not to kick going down, boy."}, {"zh": ["太多", "的", "議員", "只", "為", "個", "人", "私利", "行事"], "en": "Too many senators serving their own interests."}, {"zh": ["但並", "不是", "為", "了", "個", "人", "私利", "拿", "性命", "冒險"], "en": "But it's not about risking our lives for personal gain."}, {"zh": ["這", "完全", "是", "出于", "個", "人", "私利"], "en": "It was done for personal profit."}, {"zh": ["他五歲", "的", "時候", " ", "通過", "仔細", "觀察鄰", "居", "的", "房子", " ", "他", "推斷", "出", "小孩", "不是", "鸛", "送", "來", "的", " ", "而是", "從", "接生婆", "的", "提包", "里", "來", "的"], "en": "At the age of five, by carefully observing a neighbor's house, he deduced that babies were brought not by the stork, but by the mid-wife, in her satchel."}, {"zh": ["即使", "當", "接生婆", "告訴", "她", "說", "她", "將要", "死去", "...", " ", "她", "仍", "拒絕", "最", "後", "的", "聖潔", "!"], "en": "Even when the midwife told her she would die... she still refused to keep the Last Holy Sacraments!"}, {"zh": ["我", "簡直", "不能", "告訴", "您", "我", "有", "多", "釋懷"], "en": "I can't tell you how relieved I was."}, {"zh": ["我", "就", "不", "確定", "我", "能", "釋懷"], "en": "And I'm not so sure I'd be so forgiving."}, {"zh": ["我", "不", "確定", "我", "能否", "釋懷"], "en": "I'm not sure I can get past this."}, {"zh": ["有", "任何", "外部", "人員", "知道", "你", "在", "這", "裏", "工作", "的", "真面目", "嗎"], "en": "Does anyone outside of the program know the nature of your work here?"}, {"zh": ["在", "這", "裏", "可以", "逃避", "外部", "世界"], "en": "It's a refuge from the world out there."}, {"zh": ["如果", "我們", "從", "外部", "關閉", "呢"], "en": "What if we shut it down from the outside?"}, {"zh": ["我們", "坦言", "自己", "的", "感受"], "en": "To talk openly about how we feel."}, {"zh": ["將來", "就", "掌握", "在", "像", "他", "這樣", "的", "人手", "裡", " ", "能", "坦言", "事實", "的", "人"], "en": "Future generations depend on men like him, men capable of speaking the truth."}, {"zh": ["等", "你", "打算", "說", "實話", "了", " ", "坦言", "你", "的", "經歷", "和", "感情", " ", "再來", "找", "我"], "en": "When you're ready to be honest with me about yourself and your feelings, then come find me."}, {"zh": ["我", "對", "你", "的", "技倆", "瞭若", "指掌"], "en": "- You forget I know all your tricks."}, {"zh": ["你", "的", "唬人", "技倆", "真", "了", "得", " ", "你", "是", "個", "非常", "聰明", "的", "年", "輕人"], "en": "Well, you're an amazing con artist, or you're a very smart young man,"}, {"zh": ["拉", "他", "彎", "下腰", "來", "然后", "你", "在", "他", "耳邊", " ", "說", "一些", "關于", "主教", "木質", "假腿", "的", "玩笑"], "en": "Pull him down to you, and whisper something naughty about the bishop's wooden leg."}, {"zh": ["假腿", "是", "開", "玩笑", "的", "，", "我", "只", "需要", "這兩樣"], "en": "I was just kidding about the leg. I just need these two things."}, {"zh": ["我", "知道", "一個", "有", "一只", "木頭", "假腿", "的", "人", " ", "名字", "叫", "史密斯"], "en": "\"I know a man with a wooden leg named Smith.\""}, {"zh": ["房間", "會", "排列", "到", "起始", "位置"], "en": "The rooms can realign to zero position."}, {"zh": ["她", "的", "心", "被", "你", "的", "激情", "演講", "打動", "了", " ", "儘", "管", "是", "以", "欺", "騙", "起始"], "en": "And she has seen the good in your message, despite its dishonest beginnings."}, {"zh": ["這是", "美洲", "生物", "種類", "大量", "繁衍", "的", "起始", " ", "這兒", "曾", "是", "生物", "的", "伊甸", "園"], "en": "It was the genesis of a great wave of life that would inhabit the Americas, and this was it's Eden."}, {"zh": ["要是", "我", " ", "早就", "接受", "苦行", "戒律", "永遠", "到", "山洞", "隱居", "了"], "en": "I'd have taken the vows of schema and live in a cave."}, {"zh": ["在", "苦行", "幾個", "星期", "後", " ", "它們", "已經", "精疲力", "盡"], "en": "After weeks of marching they're desperately tired."}, {"zh": ["苦行", "動物", " ", "受到", "危險", "沙塵暴", "的", "阻礙"], "en": "The travellers are hampered by dangerous dust storms."}, {"zh": ["萊", "克斯", "集團", "的", "創始", "人", "和", "所有者"], "en": "Owner and founder of lexcorp industries."}, {"zh": ["布萊恩", "•", "米爾是", "死者", "的", "前夫", "和", "這座", "公寓", "的", "所有者"], "en": "Brian Mill's is the owner of the apartment and the ex-husband of the deceased."}, {"zh": ["讓", "先生", "有", "沒", "有", "跟", "你", "說過", " ", "這座", "建筑", "的", "年邁", "的", "所有者", "的", "事"], "en": "Did Monsieur Jean have a word or two to share with you about the aged proprietor of this establishment?"}, {"zh": ["我", "想", "我", "也", "該", "去", "那里", "瘦", "下身"], "en": "I think I could use some time at that place."}, {"zh": ["丟", "下身", "無", "分文", "的", "她"], "en": "Left her abandoned and penniless."}, {"zh": ["我", "可以", "彎", "下身", "撿", "鉛筆"], "en": "I could bend over and pick up a pencil."}, {"zh": ["他", "滿", "不在乎", "地", "玷污", "了", "宗廟", "祠堂"], "en": "With a grimace he disgraced the holy ancestral places."}, {"zh": ["祠堂", "是", "最近", "新蓋", "的", "吧"], "en": "Must have recently built the ancestor shrine?"}, {"zh": ["談戀", "愛的", "最終", "結果", "你", "當然", "要", "考慮", "得", "周密", "點"], "en": "Isn't that where all relationships should end up?"}, {"zh": ["所以", "他們", "制定", "了", "周密", "的", "計劃"], "en": "And so they cook up a lucrative scheme."}, {"zh": ["那", "怎麼", "說", "我", "也", "該", "回敬", "你", "啊"], "en": "In that case I should return the respect too."}, {"zh": ["我", "也", "該", "回敬", "你", "才", "是"], "en": "You'll lose this time too."}, {"zh": ["這是", "回敬", "你", "破壞", "我", "的", "婚禮"], "en": "That was for ruining my wedding."}, {"zh": ["我", "的", "腎"], "en": "Kidney. Kidney. Kidney."}, {"zh": ["要", "不", "我", "就", "打爆", "她", "的", "腎"], "en": "Don't try anything funny or the whore loses a kidney."}, {"zh": ["把", "你", "的", "肺", "和", "腎", "都", "換掉"], "en": "Or I'll switch your lung and kidney."}, {"zh": ["落幕", "的", "時候", "你", "必須", "站", "在", "舞台", "上"], "en": "You have to be on the stage when the curtain falls."}, {"zh": ["不過", "這", "恐怖", "的", "場景", "即將", "落幕", "了"], "en": "But this season of terror is drawing to a close."}, {"zh": ["追捕", "行動", "可能", "在", "此", "停車場", "落幕"], "en": "And it looks like this parking garage is where it will end."}, {"zh": ["我們", "是", "這個", "街區", "的", "龍頭"], "en": "We're the big boy on the block."}, {"zh": ["連", "那根", "龍頭", "棍", "也", "讓給", "我", "摸摸", "呢"], "en": "I d like to get my hands on the Dragon Head Baton."}, {"zh": ["我們", "可", "不能", "讓", "他們", "流失", "到", "Alicia", "的", "律", "所"], "en": "We don't want to lose them to Alicia's firm."}, {"zh": ["今天", "還", "流失", "了", "其他", "客戶", "嗎"], "en": "You lose any other clients today?"}, {"zh": ["而", "我們", "的", "時間", "正在", "流失"], "en": "And ours is running out."}, {"zh": ["只有", "死亡", "才能", "劃下", "完美", "的", "句點"], "en": "Only a famous death will do."}, {"zh": ["即將", "在", "這個", "案件", "劃下", "句點"], "en": "\"...would come to an end... \"...in this courtroom.\""}, {"zh": ["你", "要", "去", "徹查", "的", "是", "他", "的", "家人"], "en": "It's his family you'd have to tear apart."}, {"zh": ["人人", "都", "樂", "也", "融融"], "en": "People are happy."}, {"zh": ["你們", "家", "看", "起來", "其樂", "融融"], "en": "The family looks beautiful."}, {"zh": ["全家", "和", "樂", "融融"], "en": "The family together."}, {"zh": ["有些", "地方", "會", "向", "移民", "提供", "地皮", "及", "很多", "優惠", "政策"], "en": "Some places offer land to immigrants on very favorable terms."}, {"zh": ["我們", "最好", "把", "房子", "和", "地皮", "賣掉"], "en": "It's best we sell the house and grounds."}, {"zh": ["我", "只", "知道", "那邊", "廠房", "公司", "的", "地皮", "很值", "錢"], "en": "I just know the land of the factory is worth a lot."}, {"zh": ["我", "沒", "惡意", " ", "你", "這麼", "出色", "的", "醫學系", "學生", " ", "我", "還以", "為", "會", "..."], "en": "No offense meant, but for a bright 2nd-year medical student I expected you to be a bit more..."}, {"zh": ["誠如", "你", "所知", "他", "在", "華盛頓", "特區"], "en": "He's in D.C., like you said."}, {"zh": ["這些", "絕妙", "的", "藝術品", "非常", "多元", " ", "誠如", "各位", "所知"], "en": "These are amazing works of art and incredibly diverse, as you already know."}, {"zh": ["此", "事件", "的", "意義在", "於", " ", "誠如", "我", "的", "大學", "教授", "所", "言", " ", "直", "搗", "帝國", "核心"], "en": "What is significant, as my old teachers said, is they struck at the heart of the Empire."}, {"zh": ["西元", "1700", "年末", " ", "全", "巴黎", "的", "居民", "開始", "抱怨", " ", "擁擠", "的", "墓穴", "開始", "傳出", "令人", "感到", "噁", "心", "的", "味道"], "en": "By the end of the 1700s, residents from all over Paris began to complain about the horrible smell of the bodies in the overcrowded cemetery."}, {"zh": ["戰場", "詩人", "就此", "隕落"], "en": "The warrior poet has passed on."}, {"zh": ["獻給", "隕落", "的", "偉人"], "en": "For a great man has fallen."}, {"zh": ["你", "說", "王國要", "隕落", "了"], "en": "The fall of an empire, you told me."}, {"zh": ["反正", "您", "自己", "也", "能", "負擔", "得", "起", "西德", "的", "香煙", "了"], "en": "You can pay with the West German cigarettes from your red case."}, {"zh": ["找到", "你", "不", "容易", "啊", "西德"], "en": "You're a hard girl to find, Syd."}, {"zh": ["那", "姑娘", "想", "去", "西德"], "en": "She wants to go over to the West."}, {"zh": ["謝謝", "你", "不厭", "其煩", "地來", "看", "我"], "en": "Thank you for taking the trouble to see me."}, {"zh": ["我", "認為", "你", "叫", "我", "來", "只是", "想開", "我", "的", "玩笑"], "en": "I think you asked me here to make fun of me."}, {"zh": ["想開", "人妖", "的", "玩笑"], "en": "Want to make jokes about tyranny hookers?"}, {"zh": ["影子", "橫穿", "馬", "路", "了"], "en": "Shadow crossed the road."}, {"zh": ["我會", "橫穿", "的"], "en": "I will cross."}, {"zh": ["如果", "我們", "要", "橫穿", "城區"], "en": "Which means riding cross town is..."}, {"zh": ["和", "克羅地亞", "的", "烏", "斯塔", "夏", "右翼", "分子", "進行", "軍火", "交易"], "en": "- with the right-wing Ustashe in Croatia."}, {"zh": ["我", "在", "克羅地亞", "執行", "保護", "勤務"], "en": "I was on a protection detail in Croatia."}, {"zh": ["我", "在", "克羅地亞"], "en": "I was there in Croatia."}, {"zh": ["整個", "婚禮", "又", "豈止", "是", "漂亮", "呢"], "en": "Oh, this wedding is way more than beautiful."}, {"zh": ["他", "的", "罪", "豈止", "這一點"], "en": "He had worse than that."}, {"zh": ["豈止", "是", "黑", "啊"], "en": "Black is too colorful."}, {"zh": ["人", "把", "下海", "游泳", "作為", "消遣", "之前"], "en": "And that before people started to swim for recreation..."}, {"zh": ["我們", "要", "下海", "游泳", "嗎"], "en": "- We're going in?"}, {"zh": ["他", "可是", "心靈", "手巧", "啊"], "en": "He's the handyman."}, {"zh": ["你", "找", "了", "個", "心靈", "手巧", "的", "姑娘", ",", "這是", "好事"], "en": "You got a handyman woman. That's a good thing."}, {"zh": ["你", "真是", "個", "手巧", "的", "人", " ", "你", "知道", "嗎"], "en": "You're a real chatterbox, you know that?"}, {"zh": ["那", "是", "聽", "到", "你", "對", "著", "她", "的", "照片", "手淫"], "en": "Heard you say you jacked off to her picture, sicko."}, {"zh": ["這個", "女人", "在", "第一次", "手淫", "的", "時候", "被", "父親", "毆", "打"], "en": "This woman was beaten by her father when she first menstruated."}, {"zh": ["還是", "談", "手淫", "的", "事", "吧"], "en": "Let's get back to masturbation."}, {"zh": ["丹尼", "脫去", "她", "的", "襯衫"], "en": "And Dan's got her shirt off..."}, {"zh": ["美好", "的", "事物", " ", "脫去", "遮蔽", "我們", "陰暗", "靈魂", "的", "長", "袍"], "en": "\"Some shape of beauty moves away the pall From our dark spirits\""}, {"zh": ["這么", "說", "那", "是", "真事"], "en": "So it's true, then?"}, {"zh": ["這是", "個", "真事"], "en": "True story."}, {"zh": ["這是", "過激", "的", "反共", "產主義的", "右翼", "分子"], "en": "This is an ultra-right wing group of anti-Communist fanatics."}, {"zh": ["我", "想", "知道", "這是", "怎么", "跑", "到", "收發室", "去", "的"], "en": "But I want to know how it got to the goddamn mail room."}, {"zh": ["讓", "老", "吉米", "待", "在", "收發室"], "en": "Keep old Jimmy down in the mailroom."}, {"zh": ["收發室", "負責任", "要", "和", "你", "談談"], "en": "Deborah: Sir, chuck in the mailroom Needs to talk to you."}, {"zh": ["假使", "當時", "我們", "被", "抓", "到"], "en": "If we were caught at that time, that was it."}, {"zh": ["我", "有", "時候", "也", "對性", "感到", "無聊", " ", "假使", "我", "不", "利用", "它", "的", "話"], "en": "I get bored by sex too, if I don't use it."}, {"zh": ["如果", "你", "沒", "有", "認識", "我", " ", "假使", "我", "沒", "有", "愛上", "你"], "en": "If you hadn't met me, if I hadn't liked you..."}, {"zh": ["你", "的", "話", "就", "能", "讓", "我", "勃起", "呢"], "en": "Listening to you is giving me an erection."}, {"zh": ["我", "是", "泡", "了", "你", "女兒", "但", "沒", "有", "勃起"], "en": "Your daughter and I did make out but there was no erection."}, {"zh": ["我現", "在", "勃起", "都", "有", "問題", "了"], "en": "I have a problem achieving a full erection now."}, {"zh": ["我還", "不", "知道", "有", "首選", "這", "回事", "呢"], "en": "I didn't realize he had a primary law firm."}, {"zh": ["很", "確定", "我", "不是", "你", "的", "首選"], "en": "Pretty sure I wasn't first on your list."}, {"zh": ["我們", "跟", "蹤", "逃犯", "的", "首選", "就是", "這樣"], "en": "That is the number one way we track runners."}, {"zh": ["你", "去", "買", "清潔劑", "我", "就", "打", "掃"], "en": "Buy chemicals and I'll clean it."}, {"zh": ["她", "不能", "把", "廁所", "清潔劑", "塗", "我頭", "髮", "上"], "en": "She is not putting toilet cleaner in my hair."}, {"zh": ["你", "在", "做", "清潔劑", "雞尾酒"], "en": "-You're making a detergent cocktail!"}, {"zh": ["也", "許他", "受", "的", "是", "內傷"], "en": "Maybe he got internal injury."}, {"zh": ["你", "可能", "受", "了", "內傷"], "en": "You may have some internal injuries."}, {"zh": ["Angel", "遭受", "了", "嚴重", "的", "內傷"], "en": "Angel sustained severe internal injuries."}, {"zh": ["父親", "跟", "我們", "說", "你", "要", "興建", "自己", "的", "農場"], "en": "Father tells us you intend setting up on your own."}, {"zh": ["現在", "為", "興建", "賀林", "公寓", "抽", "籤"], "en": "Now, let's begin the draw for the construction of Horim apartment."}, {"zh": ["這是", "巴布", "爾為", "他", "的", "皇后", "興建", "的", "宮殿"], "en": "This is a palace built by Babur for his queen."}, {"zh": ["ぃ", "琌", "", "琌", "哆", "媚", "琵", "и", ""], "en": "No, it's the Oxy, and it's making me..."}, {"zh": ["這位", "是", "克文", "提裡", "烏斯", "·", "瓦魯斯", " ", "我", "夫君", "的", "友人"], "en": "This is Quintilius Varus, an acquaintance of my late husband."}, {"zh": ["他", "正在", "古老", "的", "石板", "旁", "等", "你", "們"], "en": "He's waiting for you at the Ancient Table."}, {"zh": ["小伙子", "的", "石板", "街", "冰淇淋"], "en": "Rocky road for the little man."}, {"zh": ["那", "石板", "就是", "鑰匙"], "en": "The parchment is key."}, {"zh": ["小", "松鼠", "或者", "郊狼", "生病", "的"], "en": "A little squirrelly or a coyote might get sick."}, {"zh": ["在", "往昔", "的", "大", "草原", "上", " ", "郊狼", "在", "那兒", "哀嚎"], "en": "On the old prairie Where the coyotes howl"}, {"zh": ["媽", " ", "郊狼", "又", "來", "了"], "en": "Coyote's come back again, Mom."}, {"zh": ["我們", "會", "讓", "她", "變得", "前所未有", "的", "強盛"], "en": "And you will make it grander than it has ever been."}, {"zh": ["卡斯蒂利", "亞", "由此", "強盛", "了", "起來"], "en": "Castile will be strengthened."}, {"zh": ["我", "扯住", "他的頭", "髮", "把", "他", "的", "頭扭", "了", "過來", "。"], "en": "I grabbed him by the hair and whirled his head around."}, {"zh": ["他", "跑", "去", "拿", "槍", " ", "我則", "扯住", "他", "后腿"], "en": "He rushed off to get his gun with me clutching his leg."}, {"zh": ["我", "是", "八旗", "軍", "的", "武術", "教頭"], "en": "I'm the Army's chief kung fu instructor!"}, {"zh": ["這", "可是", "黃", "四郎", "的", "團練", "教頭"], "en": "He coaches Huang's militia."}, {"zh": ["那", "她", "又", "自殘", "了", "嗎"], "en": "Did she try to hurt herself again? - Hurt herself?"}, {"zh": ["看起", "來", "她", "自殘", "了"], "en": "She seemed to be cutting herself."}, {"zh": ["陽光", "把", "你", "的頭", "髮", "照得", "很", "美"], "en": "- The light is hitting your hair in this great way."}, {"zh": ["你", "把", "我", "照得", "好", "漂亮"], "en": "You made me beautiful."}, {"zh": ["照得", "不錯", "呢"], "en": "The photo turned out nice."}, {"zh": ["他", "建立", "安全", "協定", "來", "消除", "記憶體"], "en": "HE'S ESTABLISHED FAILSAFE PROTOCOLS TO WIPE THE MEMORY"}, {"zh": ["是", "張", "記憶體", "卡"], "en": "It's a micro SD card."}, {"zh": ["控制", "版", "的", "記憶體"], "en": "the console's memory board."}, {"zh": ["我覺", "得", "你", "的", "浮游生物", "圈", "不", "太", "開心", "啊"], "en": "Dude, I think your zoo-plancton is not very happy."}, {"zh": ["這", "意味", "看", "這", "裏", "有", "機會", "這", "裏", "的", "浮游生物", "很多"], "en": "Toni spots a sign they're in the right place to find mantas."}, {"zh": ["我", "的", "版本", "有", "食用", "土", "和", "浮游生物", "泡沫"], "en": "My version of surf and turf, edible soil and plankton foam."}, {"zh": ["大聲", "唱", "這", "首歌", "很", "有", "療效", "呢"], "en": "We've sung it so many times..."}, {"zh": ["我們", "目前", "這種", "治療", "方法", "的", "療效", "前所未有"], "en": "We're getting the most effective treatments we've ever had,"}, {"zh": ["時間", "才能", "見證", "療效"], "en": "To a certain extent, time will tell."}, {"zh": ["Marilyn", " ", "坐電梯", "這會兒", " ", "我", "沒", "干什么", "不道德", "的", "事", "吧"], "en": "Well, Marilyn, I hope I didn't make any ethical infractions on the elevator ride."}, {"zh": ["坐電梯", "就是", "好玩", "嘛", "！"], "en": "Riding in an elevator would be fun"}, {"zh": ["從", "這", "下去", "，", "坐電梯", " ", "到", "二樓", "，", "向", "右", "拐"], "en": "Just go down here and take the elevator to the second floor and make a right."}, {"zh": ["我", "想", "你", "已經", "陷入", "泥潭", "了"], "en": "Yeah, I thought you had lost your damn mind."}, {"zh": ["因為", "你", "就是", "陷在", "這", "泥潭", "裏"], "en": "Because here's where you got stuck."}, {"zh": ["有", "沒", "有", "做過", "超音波"], "en": "Did you do an ultrasound?"}, {"zh": ["你", "跟", "我", "說", "想", "看", "我", "爸爸", "這幅", "遺作"], "en": "As you requested I want to show the last painting of my father"}, {"zh": ["沒人", "對", "你", "的", "這個", "遺作", "感興趣"], "en": "Nobody is interested in this..."}, {"zh": ["我", "的", "遺作"], "en": "And my testament."}, {"zh": ["也", "沒", "按", "任何", "按鍵"], "en": "I never pressed the button."}, {"zh": ["看到", "按鍵", "了", "嗎"], "en": "Do you see it?"}, {"zh": ["按鍵", "沒", "反應"], "en": "The controls aren't responding."}, {"zh": ["那個", "故事", "是", "單一", "的"], "en": "And that story is singular."}, {"zh": ["我們", "不是", "在", "跟", "單一", "的", "心智", "打交道"], "en": "We're not dealing with an individual mind."}, {"zh": ["目前", "是", "以", "單一", "作者", "名義", "出版"], "en": "Published, on this occasion,Nunder sole authorship."}, {"zh": ["現在", "我", "把", "記者", "會", "交給", "破案", "的", "功臣"], "en": "So now, I'll turn things over to the officer who cracked the case."}, {"zh": ["所以", "你", "是", "該", "組織", "蓬勃", "發展", "的", "功臣", "嗎"], "en": "So, are you responsible for their, uh, rise in prominence?"}, {"zh": ["我", "曾", "是", "希伯倫", "最", "重要", "的", "功臣"], "en": "I was the most important men in Hebalon."}, {"zh": ["你", "可以", "到", "斷頭谷", "做", "你", "的", "實驗", " ", "然", "後", "找出", "真兇"], "en": "You will take your experimentations... to Sleepy Hollow, -... and there you will detect the murderer."}, {"zh": ["只要", "我們", "找到", "真兇", " ", "她", "就", "可以", "安息", "了"], "en": "We must catch the culprit so that she can rest in peace."}, {"zh": ["我們", "東方", "航空公司", "也", "決定", "增加", "東南亞", "的", "班次"], "en": "Therefore, we have decided to expand... Eastern Airlines's flights to Southeast Asia."}, {"zh": ["旅行", "班次"], "en": "Tourist class."}, {"zh": ["我要", "趕", "搭六時", "半", "的", "班次", "離開"], "en": "I'm going to have to catch the 6:30 departure."}, {"zh": ["他", "的", "爸爸", "是", "海王", "波士", "頓"], "en": "He was a king of ocean named Poseidon."}, {"zh": ["海王", "抓住", "了", "他們", "把", "我", "的", "叉", " ", "傻瓜"], "en": "The kings have them. Bring me my f... Fools!"}, {"zh": ["看", "那兒", "血跡", "斑斑"], "en": "Look at the bloodstains right there."}, {"zh": ["看來", "我們", "都", "喜歡", "劣跡", "斑斑"], "en": "I suppose we both like getting our hands a little dirty."}, {"zh": ["斑斑"], "en": "Scabbers!"}, {"zh": ["我", "在", "康諾利", "的", "房產", "在", "縮水"], "en": "My money's on Connolly down in Property."}, {"zh": ["讓", "我", "幫", "他", "開", "苞", "吧", "！"], "en": "You should let me try first"}, {"zh": ["她", "已", "被", "開", "苞", "了", "，", "但", "對", "像", "不是", "你"], "en": "She's been plucked since I saw her last, and not by you."}, {"zh": ["立刻", "到", "訓導處", "報到"], "en": "Report to the conduct office at once!"}, {"zh": ["要", "不要", "跟", "我", "去", "訓導處", "談", "？"], "en": "Do you want to continue in my office?"}, {"zh": ["叵", "、", "氙", "、", "汞", "、", "鉭", "和", "硒"], "en": "Promethium, xenon, mercury, tantalum and dialum."}, {"zh": ["是", "叵", "、", "氙", "、", "汞", "、", "鉭", "還是", "硒", "?"], "en": "Promethium, xenon, mercury, tantalum and dialum?"}, {"zh": ["硒", "，", "鈦", "，", "砷"], "en": "Selenium, titanium, arsenic."}, {"zh": ["你", "幹", "嘛", "把", "衣服", "剪成", "這個", "樣子", "？"], "en": "Why did you cut up the shirt like this?"}, {"zh": ["第一次", "把", "你", "的", "小雞", "雞", "剪成", "兩段"], "en": "The first time, she snipped your penis in half."}, {"zh": ["莫莉", " ", "我", "再也", "看不到", "你", "美麗", "的", "面龐", "了", "嗎"], "en": "Molly, I'll never see your beautiful face again?"}, {"zh": ["但", "你", "也", "得", "夸夸", "我", "這么帥氣", "的", "面龐"], "en": "Okay, but you can appreciate a good cheekbone."}, {"zh": ["他們", "要是", "發現", "錢", "沒", "了", "會", "很", "火大"], "en": "They're not gonna be too happy when they find out it's gone."}, {"zh": ["你", "把", "我", "搞", "得", "很", "火大"], "en": "And this upsets me."}, {"zh": ["你", "太", "讓", "我", "火大", "了"], "en": "Too pissed at you."}, {"zh": ["你", "哥哥", "已經", "變節"], "en": "Your brother has turned"}, {"zh": ["變節", "緝毒局", "條子"], "en": "And shot your boss."}, {"zh": ["我覺", "得", "這就", "像", "穆罕默德", "下", "的", "最", "後", "通牒", " ", "普里特", "維", "拉吉", "要不是", "變節", "就是", "戰鬥"], "en": "I would liken it to Muhammad's brazen ultimatum that Prithviraj either apostatize or fight."}, {"zh": ["因為", "房子", "首付", "問題"], "en": "Downpayment for an apartment."}, {"zh": ["沒有", "抓狂", "的", "最低", "首付", " ", "這些", "你", "都", "不", "需要", "考慮"], "en": "No rip-off minimum down payments. That's not your bag."}, {"zh": ["連", "首付", "都", "不夠", " ", "他", "還是", "要", "離開"], "en": "That won't even begin to cover it. He's gonna have to leave."}, {"zh": ["它", "的", "觸角", "就", "像", "香腸"], "en": "Flipping glorious little sausages."}, {"zh": ["他", "像章", "魚", "伸出", "觸角", "糾纏", "我們", "全家"], "en": "That kid is wrapping his tentacles around every member of this family."}, {"zh": ["用細長", "的", "觸角", "殺", "了", "旁邊", "的", "珊瑚"], "en": "It sticks out a thin tentacle and kills the coral next to it."}, {"zh": ["姚飛救", "了", "我", "的", "命"], "en": "Yao Fei saved my life."}, {"zh": ["我們", "按", "你", "吩咐", "的", "追", "蹤", "姚", "大", "師"], "en": "We tracked master yao like you said,"}, {"zh": ["你", "認為", "姚飛現", "在", "也", "會", "在", "那兒", "嗎"], "en": "Do--do you think that's where Yao Fei is now?"}, {"zh": ["真", "繫", "好", "唔", "客", "氣", "喎"], "en": "You are really taking advantage."}, {"zh": ["你", "地", "畀", "錢", "我", "哋", "喎"], "en": "If you give use money,"}, {"zh": ["睇", "你", "地", "啲", "火", "唔", "繫", "好", "靚", "喎"], "en": "I feel the party is a bit quiet here."}, {"zh": ["免禮", "平身"], "en": "Don't get up."}, {"zh": ["嘛", " ", "行", "了", " ", "平身"], "en": "Very well. Raise your heads."}, {"zh": ["我", "只是", "不能", "辨明", "它", "的", "材質"], "en": "I'm having a bit of trouble identifying the material."}, {"zh": ["但", "她", "能夠", "通過", "解讀", "頭頂", "的", "草", "莖", "來", "辨明", "方向", " ", "從", "而", "找到", "回家", "的", "路"], "en": "But she can read the pattern of the stems overhead like a map, and so find her way home."}, {"zh": ["滲水", "問題", "也", "已", "受到", "控制"], "en": "All flooding has been contained."}, {"zh": ["滲水", "安全", "員", "理查德", "·", "布爾", "很", "擔心", "保羅", "的", "安全"], "en": "I can just see it, look. You can just pick her out."}, {"zh": ["這是", "我", "第一次", "在", "印度洋", "的", "島上", "滲水"], "en": "If you just do a little bit of hand fanning..."}, {"zh": ["沃倫", "知道", "要", "往", "哪", "裏", "走"], "en": "Warren knows where she's going."}, {"zh": ["你", "今晚", "看到", "沃倫", "了", "么"], "en": "Did you see Warren tonight?"}, {"zh": ["你", "是", "在", "說", "沃倫"], "en": "You're suggesting that Warren..."}, {"zh": ["展示", "出", "了", "與", "之前", "大相", "徑庭", "的", "工作", "姿態"], "en": "Hanzawa's Peer KONDO NAOSUKE had transformed so much he was hardly recognizable."}, {"zh": ["肯定", "大相", "徑庭", "吧"], "en": "- Quite different things, surely. - Uxoriousness."}, {"zh": ["這和", "我們", "想象", "大相", "徑庭", " ", "我們", "應該", "回到", "我們", "隊里"], "en": "This is not what we imagined. We must return to our flock."}, {"zh": ["你", "知道", "克萊恩", "小姐", "同母", "異父", "的", "妹妹"], "en": "Are you aware that Miss Crain's half-sister,"}, {"zh": ["樸", "荷", "是", "你", "同母", "異父", "的親", "妹妹", "咯"], "en": "Pak Ha has the same mother, so that makes her your real sister now."}, {"zh": ["他們", "會", "設法", "讓", "所有人", "噤若", "寒蟬"], "en": "They'll try to silence anyone who speaks out."}, {"zh": ["人人", "噤若", "寒蟬"], "en": "Everyone silent"}, {"zh": ["你", "真是太", "養眼", "了"], "en": "Aren't you a sight for sore eyes."}, {"zh": ["謝", "了", "，", "改天", "有", "更", "養眼", "的"], "en": "Thanks. Let's do it again sometime."}, {"zh": ["聽起", "來", "好像", "南韓", "總統", "的", "名字"], "en": "Yeah. Hey, that's the name of the South Korean president."}, {"zh": ["我們", "南韓", "也", "要", "踏上", "那樣", "的", "路"], "en": "\"South Korea must follow in suit.\""}, {"zh": ["也", "是", "南韓", "最", "接近", "北韓", "的", "島嶼", "之一"], "en": "This is one of Korea island closest to the North."}, {"zh": ["點擊", " ", "成本", "和", "換算", "數據"], "en": "Click, cost and conversion data.\""}, {"zh": ["и", "程", "", "", "Ω", "ǎ", "", "", "琌", "", "", "紂"], "en": "The last time I saw him, he was in the temple."}, {"zh": ["", "絋", "﹚", "", "", "", "紂", ""], "en": "Are you sure that they are in the holy temple?"}, {"zh": ["我們", "的", "工作站", "全", "被", "他們", "毀了"], "en": "They smashed up everything. The workshop, all of it."}, {"zh": ["這是", "加密", "鈷", "的", "工作站"], "en": "That is a cobalt encrypted workstation."}, {"zh": ["你", "的", "工作站", "很", "干", "凈", "嘛", " ", "杰隆"], "en": "You keep your workstation so clean, Jerome."}, {"zh": ["媽媽", "說", "離子", "風暴", "變得", "越來", "越", "嚴重", "了"], "en": "Mother saying the ion storm is getting worse."}, {"zh": ["現在", "共和", "國", "知道", "我們", "的", "離子", "炮", "了"], "en": "Now the Republic will learn of our ion cannon."}, {"zh": ["鉚釘", "可", "減低", "風阻"], "en": "Flat head rivets would reduce wind drag."}, {"zh": ["他們", "敲擊", "的", "每顆", "鉚釘", " ", "都", "可能", "是", "一顆", "子彈"], "en": "Every rivet that they strike could have been a bullet."}, {"zh": ["他", "知道", "在", "她", "的", "每", "一個", "鉚釘", "。"], "en": "He knows every rivet in her."}, {"zh": ["我", "的", "意思", "是", "人人", "都", "似乎", "在", "串謀"], "en": "Everybody seems to be in on it."}, {"zh": ["假如", "人人", "都", "串謀"], "en": "If everybody Is in on it..."}, {"zh": ["串謀", "殺", "人"], "en": "Conspiracy to commit murder."}, {"zh": ["魚類", "和", "磷", "蝦", "數量", "急遽", "減少", " ", "像", "這樣", "的", "景象", "可能", "不久", "之", "後", " ", "就會", "成為", "歷史"], "en": "Fish and krill stocks are declining so rapidly that spectacles like this may soon be part of history."}, {"zh": ["過程", "中", "，", "其", "放射", "能量", "急遽", "增加"], "en": "In the process, the fragment's potential yield is increasing exponentially."}, {"zh": ["維", "克特", "...", " ", "銀行", "想", "祝賀", "你", "...", " ", "以", "自大", "蕭條", "時期", "以來", " ", "最", "急遽", "的", "價格", "下跌"], "en": "Well, Victor... the bank would like to congratulate you... on the fastest freefall since the Depression."}, {"zh": ["我", "感覺", "自己", "在", "和", "Ward", "博士", "神交"], "en": "I feel like I'm channeling doc ward."}, {"zh": ["因此", "我", "必須", "去", "完成", " ", "神交", "給我", "的", "使命"], "en": "And that is why I must do the task... that God has given me."}, {"zh": ["你", "和", "華生", "只是", "神交", "嗎", "？"], "en": "You and John Watson, just platonic?"}, {"zh": ["你", "由", "我們", "神經科", "負責", " ", "當時", "是", "用", "強制", "手段", "把", "你", "帶", "來", "的"], "en": "You were admitted to our neurosurgical unit, you were seizing violently."}, {"zh": ["我", "可以", "幫", "你", "找", "神經科", "的", "醫生", " ", "柯漢", "醫生", "同事"], "en": "Go see Dr. Cohen first thing in the morning. He's a neurologist in my building."}, {"zh": ["召集", "國際", "眼科", "和", "神經科", "專家", " ", "舉行", "大型", "研討會"], "en": "Let's organize a massive international medical conference... of ophthalmologists and neurologists."}, {"zh": ["и", "癸", "", "", "痺", "", "泊"], "en": "I gave you that... wink."}, {"zh": ["и", "琌", "", "炳", "", "ぃ", "痺泊", "", "", ""], "en": "I'm the deadliest woman in the world."}, {"zh": ["", "", "炳", "", "ぃ", "痺泊", " ", "璶", "琌", "", "", "т", "", "硂", "", "", "穦", "炳", "", "и", ""], "en": "You don't understand who these people are. If they find me here, they will kill all of us."}, {"zh": ["這國家", "當初", "是", "奠基", "在", "偉大", "的", "理想", "和", "原則", "之上", "."], "en": "This country was founded on great ideals and principles."}, {"zh": ["我們", "在", "此", "宣布", " ", "宇宙", "星河", "球場", "正式", "奠基"], "en": "We are here to announce the opening of Universal Astro Ball."}, {"zh": ["從", "奠基", "日算起", "的", "話", " ", "要", "追溯到", "男爵", "的", "時代", "了", "。"], "en": "Foundations date back to the time of the barons."}, {"zh": ["我們", "是", "用", "你", "的", "還是", "我", "的", "煙槍"], "en": "Shall we use your gear, or mine?"}, {"zh": ["但", "你", "們", "和", "煙槍", "之間", "還有", "幾個", "問題"], "en": ". ..but you may have a couple of problems with the pipe."}, {"zh": ["努力", "讓", "亡者", "留在", "我們", "身邊"], "en": "Trying to keep the fallen with us."}, {"zh": ["亡者", "從", "不", "說", "話"], "en": "The dead don't talk."}, {"zh": ["從", "你", "結婚", "開始", "你", "拿", "你", "那些", "藍籌股", "幹什麼", "了", "？"], "en": "It is. So, those blue chips you own, what have they done since you got married?"}, {"zh": ["喬丹", " ", "藍籌股", "你", "能", "拿到", "多少"], "en": "Jordan, what do you get on that blue chip stock?"}, {"zh": ["我", "不", "懂", "怎麼", "個", "玩法", "，", "我", "有", "一些", "藍籌股"], "en": "I don't know about playing. I do own some blue chips."}, {"zh": ["我", "發明", "的", "雲霄", "飛車", "更", "嚇人"], "en": "I got a roller coaster that'll stop your heart."}, {"zh": ["像", "坐在", "只會", "往", "上", "飆升", "的", "雲霄", "飛車"], "en": "I'm on a roller coaster that only goes up, my friend."}, {"zh": ["雲霄", "飛車", "很", "好玩", "啊"], "en": "Roller coasters are fun."}, {"zh": ["告訴", "我", "午夜", "編年史"], "en": "Tell me about the dead Legates."}, {"zh": ["不多", "說", "了", ",", "讓", "我", "介紹", "我們", "的", "新", "編年史", "女孩"], "en": "- You're looking at your new client. - What?"}, {"zh": ["在", "這些", "編年史", "中", " ", "只", "提到", "你", "和", "費爾南", "多"], "en": "These chronicles only talk about you and Fernando."}, {"zh": ["你", "不是", "住", "在", "公寓", "園區", "那邊", "嗎"], "en": "I thought you were at the apartment."}, {"zh": ["園區", "的", "事業", "看", "起來", "需要", "加快", "腳步", "阿"], "en": "This... park business seems to be picking up speed."}, {"zh": ["我", "從", "來", "就", "不是", "個會", "輕敵", "的", "人"], "en": "I didn't realize I was known for trifling with criminals."}, {"zh": ["之前", "他們", "就是", "因為", "輕敵"], "en": "Whoever gets that Isle, will win this fight."}, {"zh": ["永遠", "不要", "輕敵"], "en": "Never underestimate your opponent,"}, {"zh": ["光子", "乳液", "的", "功能", "是", "養分", "與", "導體"], "en": "The photon milk acts as both a nutrient supply and conductor."}, {"zh": ["我嘗試", "要", "超載", "導體"], "en": "I'm trying to overload the conductors."}, {"zh": ["乘以", "導體", "速度"], "en": "Times velocity of conductor."}, {"zh": ["這是", "我", "的", "訂婚", "喜帖"], "en": "It's an invitation to an engagement party."}, {"zh": ["我會", "寄", "喜帖"], "en": "I'll send you the invitation"}, {"zh": ["那", "你", "有", "寄", "結婚", "喜帖", "給爸", "吧", "？"], "en": "Are you inviting him to the wedding?"}, {"zh": ["將會", "流出", "各色", "各樣", "的", "血"], "en": "Going to be all colors of blood spilled."}, {"zh": ["各色", "舞者"], "en": "The Motley Folk."}, {"zh": ["只有", "一個", "披著", "斑斑", "駁駁", " ", "打滿", "各色", "補丁", "的", "披風", "的", "影子", " ", "帶著", "孩子", "們", "從", "他們", "家", "到", "森林", "里", "去"], "en": "O... only a figure hidden by a pied cloak of multicolor patches, leading the children from their homes and into the forest."}, {"zh": ["我懷", "唸", "在", "球場", "吶喊", "助威", "；"], "en": "- I miss screaming at fooball games."}, {"zh": ["共同", "青睞", "的", "冠軍爭", "奪者", "助威"], "en": "Yes, to revive color."}, {"zh": ["在", "民間", "傳說", "中", "狼獾", "是", " ", "人", "跟", "靈界", "的", "連", "繫", " ", "而且", "是", "狼", "跟", "熊", "的", "混血", "兒"], "en": "In local folklore, the wolverine is a link to the spirit world and a cross between a bear and a wolf."}, {"zh": ["馬", "上", "開始", "了", "...", " ", "莫裡斯", ".", " ", "布朗", "大學", " ", "狼獾", "遊行樂隊"], "en": "Here they come... the Morris Brown College Marching Wolverine Band."}, {"zh": ["你", "試過", "所有", "交點"], "en": "Have you tried every intersection?"}, {"zh": ["你", "得", "交點", "新", "朋友", "了", " ", "皮爾斯"], "en": "You need to get new friends, Pierce."}, {"zh": ["那", "它", "的", "交點", "應該", "在", "..."], "en": "Then its mate would be..."}, {"zh": ["白", "衣服", "的", "人", "是", "白戎"], "en": "Those in white are the White Indians"}, {"zh": ["你", "知道", "什么", "是", "第戎", "長", "炮", "嗎"], "en": "Do you know what a Dijon culverin is?"}, {"zh": ["這樣", "你", "就", "有", "機會", "見", "我", "戎裝", "騎馬", "了"], "en": "So you'll have a chance to see me in all my pomp."}, {"zh": ["颳", "風", "時", "在", "空", "氣", "中", "會", "產", "生", "很多", "負離子", " ", "讓", "人", "心情愉快"], "en": "Wind moves electrons in the air to other atoms, which is what makes you feel good."}, {"zh": ["清邁", "負離子", "光彩", "奪目速", "豐胸"], "en": "Instant breast enlargement by ionic re-texturizing system and IPL"}, {"zh": ["因此", "寶寶來", "到", "這個", "世界", "...", " ", "不帶", "有", "任何", "一種負", "能量", "或", "負離子"], "en": "So that the baby isn't brought into the world with any kind of negative energy or ions."}, {"zh": ["布蘭多", "有", "植物所", "稀缺", "的", "成分"], "en": "Brawndo's got what plants crave."}, {"zh": ["但是", "布蘭多", "有", "植物", "有", "稀缺", "的", "成分", " ", "它", "含有", "電解質"], "en": "But Brawndo's got what plants crave. It's got electrolytes."}, {"zh": ["食物", "在", "沙漠", "中", "非常", "稀缺", " ", "即便", "是", "在", "夜晚", " ", "動物們", "也", "無權", "挑剔", "自己", "的", "飲食"], "en": "Food can be so scarce in the desert that, even at night, animals can't afford to be choosy about what they eat."}, {"zh": ["誰", "在", "這個", "點發", "信息", "來", " ", "真是", "瘋", "了"], "en": "Who sends messages at this hour ? ! They're crazy !"}, {"zh": ["嘿", "，", "這就", "有", "點發", "傻", "了"], "en": "Hey, it gets crazy, you know?"}, {"zh": ["凌晨", "1", "點發", "表演", "講", " ", "沒有", "多少", "人會", "收看", "的"], "en": "A speech at one in the morning, we lose major viewership."}, {"zh": ["我", "這兒", "已經", "都", "是", "華夫", "了"], "en": "I got waffles flying all over the place here."}, {"zh": ["華夫", "吧", "也", "很棒"], "en": "Waffle bar's awesome too."}, {"zh": ["-", " ", "我", "剛給", "你", "做", "的", "華夫", "怎麼", "辦"], "en": "What about the waffle I just made you?"}, {"zh": ["可以", "結", "集成", "書"], "en": "Might even make a nice book."}, {"zh": ["是", "你", "的", "電子", "集成", "驅動器", "的", "接口"], "en": "Your hard drive was fried, but it works now."}, {"zh": ["我", "是", "芯片", "集成"], "en": "Mine is silicon."}, {"zh": ["我", "很", "明白", " ", "因為", "我", " ", "你", "一直", "壓抑", "隱忍", "著", "對", "我媽", "的", "怨恨", " ", "日", "後", "你", "也", "會", "繼續", "這麼", "做"], "en": "I know that you've be suppressing the hatred that you feel for my mom because of me and I also know that you'll continue to do so from now on."}, {"zh": ["今天", " ", "我", "隱忍", "不", "表露"], "en": "Today I keep up the pretence."}, {"zh": ["身上", "的", "衣服", "是", "從", "博物", "館", "弄", "來", "的", "維", "多利", "亞時代", "仿冒品"], "en": "It's Dr.essed in a shoddy Victorian outfit from a museum."}, {"zh": ["那", "是", "仿冒品"], "en": "It is a fake."}, {"zh": ["那", "不是", "仿冒品"], "en": "It's not a fake."}, {"zh": ["那", "玩意", "會", "傳送", "電波", " ", "刺激", "你", "的", "尺骨"], "en": "That thing will emit such a jolt that it will literally tickle your funny bone."}, {"zh": ["我", "知道", "你", "几年", "前", "左", "尺骨", "曾", "骨折", "過", " ", "而且", "骨接", "的", "不好"], "en": "I know that you fractured your left ulna a couple of years ago and it was set poorly."}, {"zh": ["中部", "橈", "骨", "移位", "並", "粉碎性", "骨折", " ", "而且", "尺骨", "骨折"], "en": "Looks like comminuted, displaced - mid-shaft radius and ulna fractures."}, {"zh": ["泡妞", "達人", "的", "經驗"], "en": "Are you listening, Bobby?"}, {"zh": ["你", "是", "舞蹈", "達人", " ", "太棒了"], "en": "You're dancing machine. That was pretty good!"}, {"zh": ["像", "抗震", "救災", "的", "英雄", "學習", " ", "像", "抗震", "救災", "的", "戰友", "致敬"], "en": "Learn from the heroes of the earthquake rescue."}, {"zh": ["她", "就是", "洛陽", "花魁"], "en": "It's the Courtesan of Luoyang"}, {"zh": ["無意間", "讀到", "了", "他們", "的", "唇語", " ", "推斷", "他們", "是", "來", "擄", "花魁", "的"], "en": "I read their lips and deduced they were kidnapping the courtesan"}, {"zh": ["我會", "掛住", "你", "！"], "en": "I'm gonna miss you, monkey."}, {"zh": ["等", "你", "打敗", "袁紹", "之", "後"], "en": "What about after Yuan Shao is defeated?"}, {"zh": ["袁紹", "要", "打過", "來", "了"], "en": "Yuan Shao is about to invade"}, {"zh": ["我們", "怎麼", "對付", "袁紹"], "en": "How to handle the Yuan Shao situation"}, {"zh": ["他", "聽", "起來", "像", "雜耍", "諧星"], "en": "He sounds like a wad-will comic."}, {"zh": ["歡迎", "諧星", "克里斯", "洛克", "登場"], "en": "Chris Rock, everybody."}, {"zh": ["你", "是", "職業", "諧星", "嗎", "？"], "en": "You're a professional comedian or something?"}, {"zh": ["這", "好像", "是", "個", "搖擺州", "派", "對"], "en": "I smell a swing state party."}, {"zh": ["尤其", "受關", "注", "的", "是", "典型", "的", "搖擺州"], "en": "Particular attention is being paid to typical battleground states,"}, {"zh": ["這份", "九點", "的", "投票率", "是", "我們", "票", "倉", "的", "還是", "搖擺州", "的"], "en": "This is 9:00 a.m. turnout in our base precincts or swing?"}, {"zh": ["但", "他", "很", "是", "高興", " ", "大家", "都", "在", "為", "他", "歡呼雀躍"], "en": "But was thrilled that people cheered for him."}, {"zh": ["我承認", "我", "以前", "從", "沒見過", "你", " ", "那么", "歡呼雀躍"], "en": "I confess that I have never seen you so delightfully vulnerable before."}, {"zh": ["你", "未來", "的", "婆婆", "肯定", "歡呼雀躍", " ", "黛朵"], "en": "Well, that will render your future mother-in-law ecstatic, Dido."}, {"zh": ["老", "闆", "與", "我們", "很", "投契"], "en": "The boss had a good rapport with us."}, {"zh": ["你們", "看", "起來", "很", "投契"], "en": "You guys are looking good together."}, {"zh": ["如果", "你", "覺得", "不", "投契", "，", "可以", "隨時", "離開"], "en": "If you don't find it click, you may leave any time"}, {"zh": ["我", "的", "意思", "是", "退出", "足壇", "。"], "en": "I mean quitting football."}, {"zh": ["由", "於", "退出", "足壇", "，"], "en": "Since quitting football,"}, {"zh": ["我", "知道", "我", "看", "著", "很", "滲人"], "en": "I know I've behaved terribly."}, {"zh": ["火車", "向", "著", "韶山", "跑"], "en": "Train heading for Shaoshan!"}, {"zh": ["黎明前", "的", "一段", "恍惚", " ", "我見", "到", "了", "日", "後", "的", "你", "韶華", "已逝", " ", "日", "後", "的", "我", "發禿眼", "垂"], "en": "I saw before dawn the aged you from the future and the aged me from the future"}, {"zh": ["她", "的", "膝", "盂", "都", "磨破", "了"], "en": "She has her kneecaps worn bare."}, {"zh": ["來", "，", "我", "有", "全新", "的", "痰盂", "..."], "en": "Here, I got a brand-new spittoon..."}, {"zh": ["我", "這連盂", "蘭盆節", "和", "過年", "都", "不", "休息"], "en": "This job has no holidays."}, {"zh": ["我", "請", "你", "們", "到", "最好", "的", "水窪", "喝", "兩杯"], "en": "I'll show you my favorite watering holes."}, {"zh": ["我", "發現", "是", "跟", "你", "在", "一起", " ", "而", "我", "蹉跎", "了", "多少", "時光"], "en": "I realize that with you, my life is passing me by."}, {"zh": ["稛", "孬", "硐", "衄", "斕", "扂", "ㄛ", "睡", "斛", "嗣", "跎"], "en": "We're alone here. There's no need for formalities"}, {"zh": ["一事", "無成", "，", "蹉跎", "歲", "月"], "en": "You won't get anywhere"}, {"zh": ["我", "已", "掙脫", "地球", "的", "桎梏", "觸摸", "到", "上帝", "的", "臉"], "en": "Slipped the surly bonds of Earth to touch the face of God."}, {"zh": ["他", "經常", "打斷", "我", "的", "話", " ", "-", "他", "總", "是", "桎梏", "..."], "en": "I'll be talking... and he'll never let me finish a sentence."}, {"zh": ["恐懼將", "我們", "桎梏", "於", "蛙", "井"], "en": "Afraid, we stayed confined in the well"}, {"zh": ["就是", "這本", "\"", "化學", "與", "物理", "手冊", "\"", " ", "我", "拿", "來查", "鍆", "的", "反應", "速率", " ", "並", "..."], "en": "This is the very copy of The Handbook of Chemistry and Physics in which I looked up the reaction rates of mendelevium and..."}, {"zh": ["我要", "天天", "拿", "倆", "眼賊", "著", "你", " ", "你", "媽還", "不得", "拿", "一錐子", "滿", "大街", "攮", "我", "去"], "en": "If I stared at you, your mother would've chased me around with a shank."}, {"zh": ["於", "是", "，", "我", "放下", "槍", "，", "就", "坐在", "那", "...", " ", "我們", "隔", "著", "那", "條溪", "，", "彼此", "坐著", "對", "朢"], "en": "So, I put my gun down and just sat there... and we sat there across the creek from each other just looking."}]