{"single": ["單", "單身", "獨", "單一", "獨身"], "essence": ["精神", "性", "精", "素", "本質"], "family": ["家", "家人", "家庭", "家族", "人家"], "ibisbill": ["䴉嘴鷸"], "they": ["他們", "它們", "她們", "傳說", "夫"], "tens": ["什", "十", "拾", "石", "w"], "into": ["成為", "變成", "追", "進入", "加入"], "want": ["要", "想", "需要", "願意", "需"], "stick": ["棒", "貼", "棍子", "插入", "棍"], "right": ["吧", "對", "不錯", "然", "正"], "enemies": ["敵人", "仇", "敵", "寇", "敵方"], "certain": ["肯定", "確定", "某些", "必然", "篤定"], "families": ["家", "家人", "家庭", "家族", "人家"], "without outside help": ["一手"], "sun": ["日", "太陽", "白日", "陽", "曝"], "think": ["想", "覺得", "認為", "當", "心想"], "pool": ["澤", "水池", "池塘", "撞球", "桌球"], "noise": ["聲", "響", "噪音", "嘩", "音"], "leaving": ["走", "別", "離開", "離", "走開"], "nest": ["窩", "巢穴", "巢", "淵藪", "營巢"], "enter": ["進", "進入", "輸", "入", "鑽"], "previous defeat": ["一箭之仇"], "mandarin": ["官話", "普通話", "鴛鴦", "橘", "貪官"], "address": ["地址", "講話", "住址", "致辭", "尋址"], "remark": ["備註", "評註", "名言", "反話", "一言"], "bargaining": ["還價", "講價", "侃價", "砍價", "討價還價"], "it's a deal": ["一言為定"], "repeat errors": ["一錯再錯"], "butyl glycol": ["丁二醇"], "polo": ["波羅", "馬球", "水球", "水球場", "馬可波羅"], "gansu": ["張掖地區", "甘肅柳鶯", "天水地區", "定西地區", "平涼地區"], "length": ["長", "上下", "截", "篇幅", "梴"], "repeated": ["累", "層", "累累", "殗", "磊落"], "under": ["下面", "之下", "下邊", "在下", "被捕"], "shop": ["店", "館", "商店", "鋪", "鋪子"], "star": ["明星", "星", "恆星", "琁", "主演"], "busik": ["金富軾", "三國史記"], "nets": ["網", "網", "淨", "淨", "實付"], "chloride": ["氯化物", "鹽酸鹽", "聚氯乙烯", "光氣", "升汞"], "ecological": ["群落", "生態足迹", "生物群", "三江生態旅遊區"], "miura": ["三浦", "三浦梅園", "價原"], "punch": ["動手", "拳打", "猛擊", "揰", "賓治"], "triple point": ["三相點"], "trifid": ["三葉星雲"], "kangxi": ["車", "肉", "火", "身", "片"], "qiannan": ["平塘", "平塘縣", "惠水", "惠水縣", "獨山"], "buyei": ["布依", "紫云苗族布依族自治縣", "紫雲", "鎮寧布依族苗族自治縣", "鎮寧縣"], "sanmen": ["浙江三門縣", "三門", "三門縣"], "context menu": ["上下文菜單"], "favor": ["惠", "恩", "德", "厚", "人情"], "tract": ["氣管", "呼吸道", "尿道", "氣道", "尿生殖管道"], "codomain": ["上域"], "spin": ["旋轉", "打轉", "績", "紡", "紡紗"], "ashore": ["岸上", "登陸", "上岸", "登岸", "抵岸"], "fangchenggang": ["防城港", "防城港市", "上思", "上思縣", "東興"], "rising tendency": ["上揚趨勢"], "imperial sword": ["上方寶劍", "尚方劍", "尚方寶劍"], "shangli": ["上栗", "上栗縣"], "fatten": ["催肥", "上膘", "蹲膘", "催膘"], "appeals": ["祈求", "祈求", "上訴", "上訴", "求助"], "enemy": ["敵人", "仇", "敵", "寇", "敵方"], "exit": ["離去", "出口", "彈出", "退場", "下場門"], "kitchen": ["廚房", "廚", "灶", "庖", "庖廚"], "genitalia": ["陰", "陰部", "私處", "那話兒", "下身"], "notice": ["通知", "提示", "海報", "帖", "物色"], "alcoholic": ["酒精性", "酒", "白乾兒", "烈酒", "私釀"], "jawbone": ["下頷骨"], "bhutan": ["不丹", "麗星噪鶥", "廷布", "辛布", "茶馬古道"], "unclean": ["不乾不淨", "黑齷"], "germs": ["病菌", "菌", "細菌", "萌芽", "微菌"], "unafraid": ["不畏", "不含糊", "臉大", "昂然", "長風破浪"], "differing": ["左", "差", "相差", "不一", "歧見"], "mishap": ["意外", "差錯", "不測", "閃失", "差池"], "sharp": ["快", "利", "尖", "犀利", "激"], "doubt": ["懷疑", "疑問", "疑惑", "疑慮", "置疑"], "calmly": ["消停", "坦承", "不慌不忙", "發熱", "泰然處之"], "crook": ["臂彎", "不擇手段"], "sense": ["感覺", "感到", "感受", "道理", "意義"], "now and then": ["有時", "不時", "間或"], "details": ["細部", "細部", "選派", "選派", "細節"], "not presentable": ["拿出手", "不登大雅之堂", "拿不出手"], "brazen": ["大膽", "老臉", "不知羞恥", "厚臉皮", "悍然"], "heisenberg's uncertainty principle": ["不確定性原理"], "calculate": ["打", "打算", "算", "計算", "計"], "indecent": ["猥褻", "不雅", "淫猥", "非禮", "猥褻性暴露"], "hillock": ["包包", "丘", "土丘", "土崗", "坵"], "polypropylene": ["聚丙烯", "丙綸"], "together with": ["和", "與", "並", "連同", "偕同"], "pigeon": ["鴿子", "鴿", "鵓鴿", "信鴿", "飛鴿"], "noon": ["中午", "正午", "亭午", "日中", "晌午"], "srrc": ["中國無線電頻譜管理和監測"], "central processing unit": ["中央處理機"], "books": ["書籍", "圖書", "芸帙", "芸籤", "芸編"], "tender": ["溫柔", "溫", "嫩", "致以", "夭"], "intermediate egret": ["中白鷺"], "infix": ["中綴"], "lute": ["封泥", "泥封", "琉特琴", "魯特琴", "筑"], "figure": ["算", "數字", "數", "人士", "形象"], "one's own judgment": ["主心骨"], "hawks": ["主戰派", "強硬派", "老鷹", "老鷹", "鷹"], "subject-predicate": ["主謂句", "主謂結構"], "jummah": ["主麻"], "chronic": ["慢性", "老毛病", "疚", "慢性病", "久病"], "obedient": ["聽話", "順從", "服服帖帖", "乖順", "叒"], "oh my lord": ["乖乖"], "train": ["訓練", "火車", "練", "列車", "造就"], "acetyl": ["乙酰", "乙酸基", "乙酸根"], "mining": ["採礦", "挖礦", "採礦業", "雷", "礦"], "oxen": ["牛", "犉", "黃牛", "牛頭", "麝牛"], "yemen": ["葉門", "也門", "阿丹", "沙那", "薩那"], "latex": ["乳膠", "膠乳", "乳膠漆"], "tidy": ["整齊", "整潔", "井井", "嶄齊", "順溜"], "hoarse": ["沙", "啞", "沙啞", "嗄", "乾澀"], "desiccant": ["乾燥劑"], "sketch": ["素描", "草稿", "段子", "勾勒", "剪影"], "defecation": ["大小便", "二便"], "calculated": ["打", "打算", "算", "計算", "計"], "valve": ["瓣", "門", "閥門", "活塞", "閥"], "erhlin": ["二林", "二林鎮"], "dioxide": ["二氧化物", "二氧化氮", "二氧化硅", "二氧化鈦", "二氧化鈾"], "offense": ["犯罪", "進攻", "罪行", "罪過", "佚"], "shift": ["搬", "轉移", "嫁", "轉變", "委"], "internet site": ["互聯網站"], "xiamen": ["廈門大學", "廈門市", "杏林", "南普陀寺", "篔簹湖"], "gamut": ["色域", "俱全", "五味俱全"], "ironmonger's": ["五金店"], "yadong": ["亞東", "亞東縣"], "asiaweek": ["亞洲周刊"], "descent": ["非裔", "亞裔", "日裔", "種系", "嫡系"], "azores islands": ["亞速爾群島"], "excited": ["刺激", "激動", "激發", "激", "聳"], "trader": ["商販", "商戶", "交易員", "業者", "行商"], "empire": ["帝國", "俄羅斯帝國", "大清帝國", "大英帝國", "奧斯曼帝國"], "heinz": ["亨氏"], "reflected": ["照", "反射", "反映", "體現", "映"], "sandals": ["涼鞋", "拖鞋", "屝", "屨", "人字拖鞋"], "forces": ["逼", "逼", "力量", "力量", "部隊"], "gives": ["與", "與", "送", "送", "給"], "plans": ["安排", "打算", "打算", "計劃", "計劃"], "brouhaha": ["人聲鼎沸"], "everyone comments disapprovingly": ["人言嘖嘖"], "malicious and duplicitous": ["人面獸心", "佛口蛇心"], "tithe": ["仂"], "accepting": ["曠達", "甘於", "接受", "受", "答應"], "ethereal": ["幽雅", "仙氣"], "jingtai": ["景泰", "景泰縣", "代宗", "朱祁鈺"], "collect": ["羅", "藏", "收", "撿", "集"], "ensure strictly obedience": ["令行禁止"], "accidents": ["意外", "事故", "差錯", "意外事故", "岔子"], "ephraim": ["以法蓮"], "mulao": ["仫佬", "仫佬族", "姆佬", "姆佬族", "羅城仫佬族自治縣"], "period in office": ["任內"], "rencheng": ["任城", "任城區"], "a heavy burden": ["任重"], "upright and outspoken": ["伉", "剛直"], "ilyich": ["伊里奇", "列寧", "柴科夫斯基"], "squad": ["班", "班長", "儀隊", "防暴警察", "勁旅"], "lie prostrate": ["伏地", "伏惟", "伏臥", "俯伏", "匍"], "enjoy leisure": ["休閒"], "bethlehem": ["伯利恆"], "reckon": ["估計", "數數", "算計", "打量", "推算"], "to suppose": ["估計"], "our": ["我們", "阿拉", "伲", "我國", "我方"], "seemingly familiar": ["似曾相識"], "alighieri": ["神曲", "但丁"], "welfare": ["福利", "福祉", "低保", "公益", "福利院"], "octave": ["八度", "低八度", "高八度", "補足音程"], "marks": ["號", "號", "痕跡", "痕跡", "紋"], "floyd": ["弗洛伊德", "佛洛伊德"], "writings or works": ["作"], "adequate": ["當", "充分", "充足", "妥", "夠用"], "beasts": ["獸", "野獸", "禽獸", "狗玩兒的", "走獸"], "2007-2011": ["佩洛西"], "ribbon lap machine": ["併捲機"], "erupt simultaneously": ["併發"], "merger": ["併購", "寶鋼", "寶武鋼鐵"], "harass": ["騷擾", "擾亂", "使困擾", "唣", "搔擾"], "sent": ["去", "送", "派", "使", "差"], "traces": ["痕", "蛛絲馬跡", "行跡", "跡證", "靷"], "sample": ["樣本", "品味", "品", "樣品", "標本"], "promote sales": ["促銷"], "layman": ["老外", "外行", "素人", "門外漢", "俗家"], "ensure safety": ["保安"], "defend one's country": ["保衛祖國", "衛國"], "wrap": ["包", "打包", "裝", "裹", "帕"], "knight-errant": ["俠", "遊俠", "俠客", "武俠", "俠士"], "credit derivative": ["信貸衍生產品"], "homing": ["尋的", "家", "家裡", "家園", "故鄉"], "buddhahood": ["修成正果"], "increase": ["長", "增加", "提高", "增長", "加強"], "marker": ["記號筆", "奇異筆", "馬克筆", "標柱", "標磚"], "bad debt": ["倒賬", "呆帳", "呆賬", "壞賬"], "arts": ["藝術", "功夫", "藝", "美術", "技藝"], "to draw on": ["借鏡"], "demure": ["假正經"], "undue trouble": ["偏勞"], "partial differential": ["偏微分"], "diverge": ["叉", "偏離", "分支", "岔", "發散"], "port of call": ["停靠港", "停靠站"], "pause": ["頓", "暫停", "消停", "停頓", "打頓"], "incline towards": ["側", "歸於"], "pilfer": ["偷", "偷竊", "偷雞摸狗", "胠篋", "偷吃"], "seinfeld": ["傑瑞·宋飛"], "standing proud": ["傲立"], "efferent neuron": ["傳出神經"], "preacher": ["傳道者"], "grieve": ["傷心", "悼念", "哀痛", "傷心蒿目", "怞"], "grieved": ["傷心", "悼念", "哀痛", "傷心蒿目", "怞"], "cunt": ["屄", "淫穴", "傻屄", "雞掰", "撕逼"], "dominance": ["優勢", "統治權", "壟斷"], "unocal": ["優尼科"], "haowen": ["元好問"], "hanqing": ["關漢卿", "元曲四大家", "雜劇四大家"], "inflatable": ["皮筏", "充氣船", "渾脫"], "fiendish": ["兇惡", "凶惡", "窮凶極惡"], "first of all": ["先不先"], "person with foresight": ["先覺"], "hualien": ["花蓮市", "花蓮縣", "壽豐", "壽豐鄉", "富里"], "speed of light": ["光速"], "cleveland": ["克利夫蘭"], "karamay": ["克拉瑪依", "克拉瑪依市", "克拉瑪依區", "烏爾禾", "烏爾禾區"], "queen": ["后", "女王", "王后", "娘娘", "王太后"], "crimean peninsula": ["克里木半島"], "childhood": ["童年", "兒時", "幼年", "幼時", "沖齡"], "hound": ["走狗", "獵犬", "短腿獵犬", "逼死", "兔死狗烹"], "use in medicine": ["入藥"], "fascinated": ["迷住", "著迷", "入迷", "醉心", "神往"], "enter a pass": ["入關"], "enter hospital": ["入院"], "psychological drama": ["內心戲"], "chamberlain": ["張伯倫", "內臣"], "2005-2013": ["本篤·十六世", "內賈德", "艾哈邁迪內賈德"], "lactone": ["內酯"], "all year long": ["全年"], "whole of america": ["全美"], "national broadcasting company": ["美國全國廣播公司"], "rival": ["敵", "對手", "匹敵", "對敵者", "打對台"], "a few words": ["兩句"], "two unrelated matters": ["兩回事"], "each other's sunshine": ["兩情相悅"], "two-pronged": ["兩手策略"], "stabbing": ["戳", "刺", "捅", "刺傷", "劇痛"], "kinmen": ["金門縣", "金沙", "烈嶼", "烈嶼鄉", "烏坵"], "shoki": ["八岐大蛇"], "most probably": ["八成"], "exams": ["測試", "考試", "題", "期末考", "考卷"], "fructus anisi stellati": ["八角茴香"], "public servant": ["公僕"], "business class": ["公務艙"], "axiom": ["公理"], "sixth month": ["六月"], "supernumerary": ["冗長", "增生"], "mull": ["琢磨", "醞釀", "冥思苦索", "咂摸", "咬嚼"], "chilling": ["耍廢", "冷森森", "冰", "陰風", "風寒"], "chaoyang": ["朝陽", "朝陽縣", "朝陽區", "雙塔", "建平"], "keirin": ["凱林賽"], "glint": ["閃耀", "凶光", "閃射"], "offer for sale": ["出賣", "出售"], "a way out": ["出路", "退路"], "diffused": ["擴散", "彌漫", "刊印", "分散的策略", "散光"], "machining": ["切削", "機器", "機", "車", "機械"], "vice-president": ["副總統", "副院長", "曾慶紅", "拜登", "切尼"], "2001-2008": ["穆沙拉夫", "切尼"], "slide examination": ["切片檢查"], "affidavit": ["切結書", "宣誓供詞證明", "宣誓書"], "suicide": ["自盡", "自殺式", "短見", "自殺", "遺書"], "please don't": ["甮", "甭", "切莫", "覅"], "concerning oneself": ["切身"], "diffuse": ["擴散", "彌漫", "刊印", "散光", "瀰漫星雲"], "chain of islands": ["列島"], "binwang": ["駱賓王", "初唐四傑"], "planer": ["刨工", "刨床"], "liberman": ["利伯曼"], "talon": ["利爪"], "advent": ["到來", "耶穌降臨節", "降臨節"], "finished": ["得", "盡", "畢", "掛", "散會"], "depending": ["看", "靠", "指", "據", "寄"], "excite": ["刺激", "激動", "激發", "激", "聳"], "prickly amaranth": ["刺莧"], "impair": ["損害", "削弱", "減損", "毀損", "礙胃口"], "proceed towards": ["前往"], "one moment ": ["前腳"], "front section": ["前部"], "lever": ["扳手", "桿", "槓桿", "重臂", "撬"], "shuck": ["剝"], "highway robbery": ["剪徑"], "snip": ["剪斷"], "create and practice": ["創練"], "shipei": ["劉師培"], "xiaobo": ["王小波", "奚嘯伯", "四大鬚生", "劉曉波"], "sword-play": ["劍法", "太極劍"], "unexpected winning move": ["劍走偏鋒", "劍走蜻蛉"], "gatling": ["加特林", "加特林機槍"], "additive": ["助劑", "外加劑", "添加劑", "添加物", "相加性的"], "reagent": ["試劑", "助劑", "活性劑", "試液"], "liven": ["助興", "炒氣氛", "炒熱氣氛"], "firearm": ["槍", "槍械", "火器", "噴子", "槍砲"], "courage": ["勇氣", "膽", "膽量", "膽子", "筋骨"], "movable": ["活動", "浮", "可動", "動產", "活字"], "moving point": ["動點"], "army orderly": ["勤務兵", "勤務員"], "thicken": ["增稠", "變厚", "勾芡"], "rented": ["出租", "雇", "租", "租金", "撕裂"], "charter a ship": ["租船", "包船"], "wrapping cloth": ["包袱", "包袱皮兒"], "corona": ["科羅納", "科羅娜", "日冕", "北冕座", "南冕座"], "polar": ["極地", "白熊", "北極熊", "寒帶", "極座標"], "lienchiang": ["北竿", "東引", "莒光", "南竿", "連江"], "decameron": ["薄伽丘", "十日談"], "manifold": ["多樣", "千真萬確", "多種多樣", "流形", "萬般"], "thousand-league": ["千里搭長棚，沒有不散的宴席"], "simiao": ["千金方", "千金要方", "孫思邈"], "kilobase": ["千鹼基對"], "antihypotensive": ["升壓劑"], "weekend spouse": ["半糖夫妻"], "nanking": ["金陵大學", "南京大屠殺事件", "約翰·拉貝"], "south slope": ["南坡"], "namling": ["南木林", "南木林縣"], "nanxi": ["南溪", "南溪縣"], "nanpiao": ["南票", "南票區", "錦西", "錦西縣"], "tubo": ["吐蕃", "吐蕃王朝", "松贊干布", "南詔國"], "borges": ["博爾赫斯"], "xlr": ["卡儂"], "sarcoma": ["肉瘤", "卡波西氏肉瘤"], "karzai": ["卡爾紮伊"], "2004-2014": ["卡爾紮伊", "蘇西洛", "巴羅佐"], "karnataka": ["卡納塔克邦", "班加羅爾"], "bizet": ["比才", "採珠人", "卡門", "梅里美", "鬥牛士之歌"], "indians": ["印第安", "印度人", "印第安人", "印度教", "小春"], "instant message": ["即時通訊"], "follicle": ["卵泡", "毛小囊", "濾泡", "葖", "蓇"], "loop": ["圈", "循環", "環", "回路", "環路"], "remove harness": ["卸套"], "authentic taste": ["原味"], "place of origin": ["原地", "老家", "產地", "原產地", "發源地"], "original location": ["原址"], "monera": ["原核生物界"], "original source": ["原產地"], "previous place": ["原處"], "but expectedly": ["反倒"], "avocet": ["反嘴鷸"], "accuser": ["反坐"], "response time": ["反應時", "反應時間", "響應時間"], "cross-examine": ["盤問", "反詰問", "盤詰", "盤駁"], "accept surrender": ["受降"], "conceited": ["驕傲", "自負", "恣睢", "矜貴", "自恃"], "ejaculate": ["射精", "顏射", "口射", "口爆"], "well-wishing": ["口彩"], "ventriloquism": ["口技", "腹語", "腹語術"], "then and now": ["古今"], "guye": ["古冶", "古冶區"], "in olden days": ["古時候", "古昔", "往初", "往古", "往歲"], "hoot": ["叫囂", "啼", "鳴笛", "叱", "鳴叫"], "wake-up call": ["叫醒服務"], "pitiable": ["可念", "可憐見", "悲悽"], "taidong": ["台東"], "taihsi": ["台西", "台西鄉", "臺西", "臺西鄉"], "all-powerful": ["叱咤風雲", "錢能通神", "安德海"], "judges": ["法官", "法官", "斷", "斷", "判斷"], "grapes": ["葡萄", "提子", "吃不到葡萄說葡萄酸", "說葡萄酸", "酸葡萄"], "dialogue": ["對話", "對白", "對口詞", "臺詞", "相聲"], "rubber": ["膠", "橡膠", "橡皮", "橡皮擦", "膠帶"], "cocktail": ["雞尾酒", "調酒", "合成物", "燃燒瓶", "夜招待酒會"], "weinan": ["渭南地區", "渭南", "渭南市", "白水", "合陽"], "relics": ["殘餘", "遺風", "文物", "聖跡", "遺址"], "meets": ["會", "會", "見", "見", "遇到"], "tufan": ["贊普", "吐蕃"], "lily": ["百合", "百合花", "蘭", "木蘭", "安祖花"], "monarchical power": ["君權"], "mumble": ["喃喃", "咕噥", "支支吾吾", "嘰嘰咕咕", "囁嚅"], "yelp": ["吠叫"], "angkor": ["吳哥窟"], "francis": ["弗蘭西斯", "法蘭西斯", "吳鎮宇", "韋德", "弗蘭西斯·培根"], "sucker mouth": ["吸口"], "a leech": ["吸血者"], "kiss": ["吻", "親", "接吻", "親吻", "親親"], "howl": ["嚎", "吼", "吼叫", "嚎叫", "狂吠"], "midweek": ["周中"], "expel": ["開除", "轟", "逐出", "驅", "驅逐"], "cherish": ["抱", "珍惜", "懷抱", "心懷", "稀罕"], "whir": ["呼呼聲"], "fixer": ["和事佬"], "defying": ["抗", "抗拒", "不畏", "拗", "傲"], "peace negotiations": ["和平談判"], "aggrieved": ["窩心", "哀怨", "委委屈屈", "憤憤不平", "校鬧"], "ramayana": ["羅摩衍那", "哈奴曼"], "harper": ["哈珀", "斯蒂芬·哈珀"], "armageddon": ["哈米吉多頓"], "somalia": ["索馬里", "索馬裡", "索馬利亞", "摩加迪休", "摩加迪沙"], "sighs": ["唉", "唉", "嘆氣", "嘆氣", "嘅"], "xiu": ["歐陽修", "新五代史", "新唐書", "唐宋八大家"], "commodity grain": ["商品糧"], "chamber of commerce": ["商會"], "trade and commerce": ["商貿"], "qidong": ["祁東", "祁東縣", "啟東", "啟東市", "啟海話"], "hops": ["啤酒花", "忽布", "蛇麻", "酒花", "跳"], "pow": ["啪"], "laryngopharynx": ["喉咽"], "agents": ["探員", "代理人", "中介", "主體", "仲介"], "single-celled algae": ["單胞藻"], "following year": ["嗣歲", "翌年"], "he he": ["嘿嘿"], "hissing sound": ["噓聲", "噝噝聲"], "antics": ["噱頭", "揶", "貧限想"], "grave consequence": ["嚴重後果"], "rats": ["老鼠", "老鼠", "鼠", "鼠", "耗子"], "monal-partridge": ["四川雉鶉", "雉鶉"], "quads": ["四條"], "a panacea": ["四海皆准", "放之四海而皆准"], "four cleanups movement": ["四清"], "retrace": ["回描", "折回"], "rollback": ["回滾"], "dots": ["點", "點", "點子", "點子", "圓點"], "country's": ["國土", "境外", "過境"], "snu": ["國立首爾大學", "首爾國立大學"], "mist rolling upwards": ["圛"], "landmark": ["地標", "界標", "埄"], "chinese waistcoat": ["坎肩"], "tambora": ["坦博拉"], "euskadi": ["埃塔"], "essen": ["埃森"], "marbles": ["彈珠", "玻璃球", "大理石", "大理石", "大理岩"], "chengxi": ["城西區"], "rapid transit system": ["城鐵"], "puli": ["埔里", "埔里鎮"], "slavic": ["斯拉夫", "斯拉夫語", "基輔羅斯"], "tenge kazakhstan currency": ["堅戈"], "pallet": ["托盤", "棧板", "貨盤", "托盤車", "堆高車"], "stod": ["堆龍德慶", "堆龍德慶縣", "瑪多", "瑪多縣", "雜多"], "dutiable": ["報稅"], "elevated": ["超拔", "高架", "嶭", "軒昂", "高揚"], "gloom": ["幽暗", "塊壘"], "maurice": ["塔列朗"], "increased": ["長", "增加", "提高", "增長", "加強"], "open up land": ["拓荒", "墾荒", "開地", "開荒"], "fresco": ["壁畫", "露天"], "pressure gauge": ["壓力計"], "layered": ["成層", "層", "疊", "層次", "一層"], "maternal grandfather": ["老爺", "外公", "外祖父", "姥爺", "外爺"], "external diameter": ["外徑"], "wooded": ["多樹木"], "betto": ["多那太羅"], "night departure": ["夜行"], "fourth-year": ["大四"], "dayuan": ["大園", "大園鄉", "虞應龍"], "dayong": ["大庸", "張家界"], "4100-2600": ["大汶口文化"], "nirvana sutra": ["大般涅槃經"], "a rough diamond": ["大醇小疵"], "damson": ["大馬士革李"], "rhubarb": ["大黃"], "devanagari": ["天城文"], "tiandeng": ["天等", "天等縣"], "taishi": ["太石村"], "place in between": ["夾"], "oleander": ["夾竹桃"], "preposterous bullshit": ["奇文共賞"], "obtain slyly": ["套"], "polite remarks": ["套數"], "awards": ["標", "標", "獎賞", "獎賞", "授予"], "retail outlet": ["經銷商", "奧特萊斯", "銷售點"], "fenchihu": ["奮起湖"], "slave servant": ["奴婢", "家奴", "蠻子"], "slave-owning society": ["奴隸社會"], "slave-owning": ["奴隸社會"], "pretty boy": ["小白臉", "奶油小生"], "pins": ["別", "別", "密碼", "密碼", "釘"], "rugao": ["如皋", "如皋市"], "unduly humble": ["妄自菲薄"], "monster-like": ["妖氣"], "dolls": ["娃娃", "玩偶", "洋娃娃", "娃", "人形"], "illicit partner": ["姘夫"], "seeking": ["找", "求", "尋找", "謀", "邀"], "bewitch": ["迷魂", "蠱", "媚惑", "迷魂陣"], "nenjiang": ["嫩江", "嫩江地區", "嫩江縣"], "serene": ["平靜", "安詳", "安祥", "幽", "嫻雅"], "tender yellow": ["嬌黃"], "buggy": ["馬車", "嬰兒手推車", "手推車", "月球車"], "bc-": ["子貢", "道家"], "stem compound": ["字根合體字"], "alphabetical": ["字母順序"], "lonely soul": ["孤魂", "形單影隻"], "diploma": ["文憑", "學位證書", "野雞大學"], "illegitimate son": ["孽子"], "protect the country": ["守土"], "remain constant": ["守恆"], "guard's van": ["守車"], "anqiu": ["安丘", "安丘市"], "go to sleep": ["安息", "就寢"], "anxin": ["安新", "安新縣"], "angus": ["安格斯牛", "安格斯"], "set up camp": ["安營紮寨"], "anxiang": ["安鄉", "安鄉縣"], "bureaucratic language": ["官話"], "dingtao": ["定陶", "定陶縣"], "yifeng": ["宜豐", "宜豐縣"], "talk with propriety": ["客氣話"], "passenger train": ["客車", "載客車"], "commercial brochure": ["宣傳冊"], "interior design": ["室內設計"], "family matters": ["家事"], "perennial root": ["宿根"], "closely connected": ["密接"], "esoteric buddhism": ["密教"], "crowded together": ["密集"], "rich country": ["富國"], "hump": ["富貴包", "駝"], "finish a trial": ["審結"], "annul": ["寬免", "銷"], "baowu": ["寶鋼", "寶武鋼鐵"], "liangfu": ["封禪"], "let sb down": ["對不住", "虧負"], "beginner": ["小學生", "菜鳥"], "popular song": ["小曲"], "short paragraph": ["小段子"], "yellow-crested cockatoo": ["小葵花鳳頭鸚鵡"], "hawker": ["小販", "行商"], "achieving": ["了", "做到", "實現", "成就", "達到"], "chignon": ["小鬟"], "early youth": ["少年"], "pretty girl": ["美眉", "靚女", "靚妹", "少艾"], "jianshi": ["尖石", "尖石鄉", "建始", "建始縣"], "pinnacle": ["巔峰", "極致", "尖頂", "臻化境", "尖閣列島"], "nicosia": ["尼古西亞", "尼科西亞"], "nyima": ["文部", "文部鄉", "尼瑪", "尼瑪縣"], "centered": ["中", "心", "中心", "中央", "正中"], "pike position": ["屈體"], "chinese hawthorn": ["山楂"], "supraspinatus": ["岡上肌"], "wife's father father-in-law": ["岳父"], "1103-1142": ["岳飛"], "emeishan": ["峨眉山", "峨嵋山市", "峨眉山市"], "gyuha": ["崔圭夏"], "laoshan": ["嶗山", "嶗山區", "老山自行車館"], "gongs": ["銅鑼", "銅鑼", "鑼", "鑼", "廝鑼"], "mdzo": ["左貢", "左貢縣"], "great majority": ["差不多的"], "manuel": ["巴羅佐"], "qazaq": ["巴里坤", "巴里坤哈薩克自治縣", "巴里坤縣", "木壘哈薩克自治縣", "木壘縣"], "pakistani comrades": ["巴鐵"], "university of paris": ["巴黎大學"], "muhammad": ["穆聖", "納吉布", "布托", "紮馬剌丁"], "brucella": ["布魯氏菌病", "布氏菌苗"], "army division": ["師"], "p'yong'an": ["平安南道", "平安北道"], "pingfang": ["平房", "平房區"], "quadratic root": ["平方平均數"], "terrace": ["臺", "看台", "平臺", "樓臺", "陔"], "geometric series": ["幾何級數", "等比級數"], "prefectural seat": ["府城"], "glamor": ["魅力", "艷色", "爭妍鬥艷", "庫爾尼科娃"], "front court": ["庭除"], "charlatan": ["庸醫", "江湖醫生", "蒙古大夫", "風水先生"], "broadcasting room": ["廣播室"], "ranging": ["範圍", "射程", "方圓", "幅度", "靶場"], "retard": ["腦殘", "減緩", "延緩", "拖慢", "減低速度"], "a trial run": ["試車", "引而不發"], "grasped": ["把", "操", "掌握", "把握", "握"], "under sb's control": ["彀中"], "sing and play": ["彈唱"], "warp": ["縱", "經", "扭曲", "彎曲", "淤灌"], "time to come": ["往後"], "postoperative examination": ["後診"], "an up-and-coming youngster": ["後起之秀"], "trainee worker": ["徒工"], "enjoy success": ["得誌"], "obey an order": ["聽命", "從命"], "a movie actor": ["從影"], "negligible": ["渺小", "微不足道", "微末", "涓埃", "涓埃之力"], "tehran": ["德黑蘭"], "itching": ["癢", "發癢", "瘙癢", "痒", "瘙"], "bradycardia": ["心跳過緩"], "swallow one's anger": ["忍氣吞聲"], "allegro": ["快板"], "blush": ["臉紅", "通紅", "紅臉", "發紅", "忸"], "irascible": ["暴躁", "急躁", "急噪", "氣粗", "髝髞"], "love aperture": ["情竇"], "vicious appearance": ["惡相"], "provoke incite": ["惹起"], "intend": ["準備", "打算", "有意", "意圖", "有心"], "edison": ["愛迪生", "陳冠希"], "feel sentiments": ["感懷"], "tsar": ["愷撒"], "habitual": ["慣用", "慣性", "慣犯", "慣偷", "慣竊"], "colloquial usage": ["慣用語"], "receivable": ["應收", "應收賬款"], "ripen": ["成熟", "秖"], "an army banner": ["戰旗"], "joking": ["玩話", "諧談", "玩笑", "鬧", "笑話"], "manually adroit": ["手巧"], "rolled": ["滾", "捲", "卷", "幅", "轉悠"], "viral": ["病毒性", "病毒感染", "病毒式營銷", "病毒性營銷", "病毒性肝炎"], "gimlet": ["手鑽", "螺絲鑽"], "cheaply": ["賤賣", "打口"], "mannered": ["扭扭捏捏", "扭捏"], "grantee": ["承讓人"], "skilled worker": ["技工"], "batsman": ["擊球員", "投殺"], "arcade basketball machine": ["投籃機"], "antigen": ["抗原", "素原促進", "抗原決定簇"], "elevate": ["超拔", "抬舉"], "smooth out": ["舒展", "抹平"], "levy a tax": ["抽稅"], "randomly select": ["抽號"], "lashkar": ["赫爾曼德", "拉什卡爾加"], "bolivia": ["玻利維亞", "蘇克雷", "拉巴斯", "拉帕斯"], "dawdling": ["拖磨", "頇", "顢", "泡", "挨"], "get students": ["招生"], "2021-": ["拜登", "賀錦麗"], "ryan": ["賴安", "拯救大兵瑞恩"], "bend back": ["挫"], "straighten up": ["挺"], "yarn": ["紗線", "毛線", "絲線", "紗", "棉線"], "sweep a grave": ["掃墓"], "award a prize": ["發獎", "授獎"], "devalued": ["掉價", "貶低", "毛"], "locket": ["掛墜盒"], "coupling links": ["掛鉤"], "service a plane": ["接機"], "vaccinated": ["接種"], "exalt": ["揚清激濁", "激濁揚清"], "heart-wrenching": ["揪心揪肺"], "harming": ["傷害", "惡", "害", "危害", "損害"], "waddling": ["跩", "搖搖擺擺"], "what the hell": ["搞毛"], "thorough search": ["摸排"], "abandon or discard": ["撂"], "catfight": ["撕逼"], "impact printer": ["撞擊式印表機", "撞擊式打印機"], "withdraw from": ["撤離", "淡出"], "blatant": ["露骨", "撲面", "撲面而來"], "arrogate power": ["擅權"], "military drill": ["操課"], "eraser": ["擦子", "橡皮擦", "橡皮", "板擦", "板擦兒"], "street vending": ["擺賣"], "surveillance camera": ["攝像頭"], "change profession": ["改行", "轉行"], "radioactive material": ["放射性材料", "放射物"], "former haunts": ["故地", "舊地"], "school administration office": ["教務室"], "vatican": ["教廷", "梵帝岡", "梵諦岡", "羅馬教廷", "梵蒂岡"], "scatter money": ["散錢"], "raise the alarm": ["敲響"], "worthy match": ["敵手"], "c4h7cl2po4": ["敵敵畏"], "dataset": ["數據組"], "several million": ["數百萬"], "wen wei po": ["文彙報"], "reedling": ["文鬚雀"], "mahjong layout": ["方城"], "abuser": ["施虐者"], "myeo": ["旀"], "flagpole": ["杠", "旗杆"], "falcons": ["鷹", "鷹", "獵鷹", "獵鷹", "隼"], "ntt": ["日本電報電話公司"], "adolescence": ["青春期", "早年", "早歲", "青年期"], "rise in rank": ["昇"], "*": ["星號"], "erotic picture": ["春宮"], "jinjiang": ["晉江地區", "晉江", "晉江市", "錦江", "錦江區"], "santana": ["桑塔納", "普桑"], "prodi": ["普羅迪"], "common rosefinch": ["普通朱雀"], "lattice": ["格子", "網格", "柵格", "格網", "點陣"], "endowed": ["稟", "賦", "智珠在握", "鍾靈毓秀"], "infallible": ["自以為是", "智者千慮，必有一失"], "airsick": ["暈機"], "warm current": ["暖流"], "violent method": ["暴力法"], "scorch": ["燒焦", "燒灼", "朓", "烤炙", "焦炙"], "in the sun": ["曬太陽"], "bibliotheca": ["書庫"], "jinghua": ["曹靖華", "李汝珍", "鏡花緣"], "paternal great-grandmother": ["老奶奶", "曾祖母"], "most distant": ["最遠"], "amidst": ["雲裡霧裡", "月下花前"], "sell-by date": ["有效期"], "attained": ["達", "達到", "高達", "達致", "馴"], "telescopic sight": ["望遠瞄準鏡"], "look skyward": ["朝天"], "zimei": ["木子美"], "tso": ["木格措"], "ganymede": ["木衛三"], "future tense": ["未來式"], "inessential detail": ["末"], "one's role": ["本分"], "native person": ["本地人"], "rtsa": ["札達", "札達縣", "申扎", "申扎縣"], "teul": ["朰"], "hongdeng": ["朱紅燈"], "railing": ["欄", "欄杆", "闌", "鐵欄", "闌檻"], "cunninghamia lanceolata": ["杉"], "linfu": ["李林甫"], "dewey": ["杜威"], "dushanbe": ["杜尚別"], "east asian games": ["東亞運動會"], "dongtai": ["東台", "東台市"], "eastern europe": ["東歐"], "eastern orthodox church": ["東正教"], "flagstaff": ["枓"], "juicer": ["果汁機", "榨汁機"], "chess-like game": ["棋", "枰"], "tarred": ["焦油", "柏油", "柏油路", "柏油馬路", "煤焦油"], "hovel": ["蓬居", "柴門小戶", "篳門閨竇", "蓽門圭竇"], "fargesii": ["栲"], "nuclear nations": ["核國家"], "arsenal": ["軍火庫", "武庫", "核武庫", "阿森納"], "tonal": ["聲調語言", "格律"], "guey": ["桂綸鎂"], "rose myrtle": ["桃金娘"], "mehlis": ["梅氏腺"], "terraced": ["梯形", "臺", "看台", "平臺", "樓臺"], "tnt": ["梯恩梯", "梯恩梯當量", "黃色炸藥"], "corncob": ["棒子"], "rufous-breasted accentor": ["棕胸岩鷚"], "rufous-bellied": ["棕腹仙鶲", "棕腹啄木鳥", "棕腹隼鵰"], "geezer": ["老拙", "棺材瓤子"], "fagus sylvatica": ["椑"], "coconut water": ["椰汁", "椰子汁"], "coconut grove": ["椰林"], "yuci": ["榆次", "榆次區"], "weedy": ["薉", "榛蕪"], "giddily": ["樂呵呵"], "maoqian": ["樂府詩集", "郭茂倩"], "tesco": ["樂購", "特易購"], "fuzzy logic": ["模糊邏輯"], "hengduan": ["橫段山脈", "橫斷山脈"], "die by violence": ["橫死"], "official denunciation": ["檄文", "檄書"], "examine a ballot": ["檢票"], "type of oak": ["櫪"], "cherry mouth": ["櫻桃小嘴"], "subprime mortgage crisis": ["次級房屋信貸危機", "次貸危機"], "pledging": ["保證", "發誓", "誓", "質", "誓言"], "merrily spend": ["歡度"], "farewell party": ["歡送會"], "regular education": ["正規教育"], "historic cost": ["歷史成本"], "rote": ["滿堂灌", "死背", "死記", "死記硬背"], "diehard followers": ["死黨"], "differing attitude": ["殊姿"], "fungicide": ["殺真菌劑"], "mother and child": ["母子"], "mildew": ["毛", "霉病", "白粉病", "霉蠹"], "devalue": ["貶低", "毛"], "folk customs": ["民間習俗"], "calm and composed": ["氣定神閒"], "hopcalite canister": ["氧化罐"], "hydrofluorocarbon": ["氫氟烴"], "hydraulic engineer": ["水利家"], "water disaster": ["水患"], "macaroni": ["通心粉", "水管麵", "空心麵", "通心麵"], "calamus": ["水菖蒲", "菖蒲", "蒲"], "spinach": ["菠", "菠菜", "炒菠菜", "莧", "莧菜"], "jiangjin": ["江津", "江津區"], "kiangsi": ["江西", "江西省"], "wolfson wulfsohn etc": ["沃爾芬森"], "lacking in class": ["沒品"], "settled matter": ["沒說的"], "sardine": ["沙丁魚", "鰮"], "shawan": ["沙灣", "沙灣區", "沙灣縣"], "chinese red pine": ["油松"], "french polynesia": ["法屬波利尼西亞"], "fascism": ["法西斯主義"], "mason": ["泥瓦匠", "泥工", "泥水匠"], "tagore": ["泰戈爾"], "thames": ["泰晤士河", "泰晤士"], "washing powder": ["洗衣粉"], "lakers": ["洛杉磯湖人", "湖人", "科比·布萊恩特"], "tunnel entrance": ["洞口"], "float and drift": ["浮動"], "fuliang": ["浮梁", "浮梁縣"], "wuhai": ["烏海市", "烏海", "海南"], "haishu": ["海曙", "海曙區"], "heinrich": ["海涅", "赫茲"], "gelderland": ["海爾德蘭"], "hairui": ["海瑞", "海瑞鄉"], "tellina iridescens": ["海瓜子"], "coastal erosion": ["海蝕"], "alumen": ["涅石", "羽涅"], "ablation": ["消蝕"], "slow business season": ["淡季"], "hybrid": ["雜種", "混合", "混血", "混種", "混合體"], "qing troops": ["清兵"], "to be spoiled": ["減色"], "cushioning shoe": ["減震鞋"], "yubei": ["渝北", "渝北區"], "ferry crossing point": ["渡頭"], "weicheng": ["渭城", "渭城區", "濰城", "濰城區"], "transformations": ["轉變", "蛻變", "轉型", "幻化", "變換"], "surjective map": ["滿射"], "manchurian-chinese": ["滿漢"], "a sumptuous banquet": ["滿漢全席"], "brow": ["皺眉", "眉梢", "滿頭大汗", "眉心輪", "眉間輪"], "a leak": ["漏洩"], "gradual forward progress": ["演進"], "hamburg": ["漢堡"], "hanyang": ["漢陽", "漢陽區"], "rinse one's mouth": ["漱口"], "decelerando": ["漸慢"], "unimpeachable conduct": ["潔操"], "lucheng": ["潞城", "潞城市", "鹿城", "鹿城區"], "chaochou": ["潮州", "潮州鎮"], "disperse water": ["潵"], "australian open": ["澳網"], "jiyang": ["濟陽", "濟陽縣"], "small pratincole": ["灰燕鴴"], "emei shan liocichla": ["灰胸藪鶥"], "do the cooking": ["炒菜"], "billowing smoke": ["烏煙瘴氣"], "rice au gratin": ["焗飯"], "scented": ["氣味", "臭跡", "馥", "花茶", "香片"], "unspecified period": ["無期"], "moyamoya disease": ["煙霧症"], "stand all alone": ["煢煢孑立"], "charcoal briquette": ["煤球"], "stilb": ["熙提"], "fusion weapon": ["熱核武器"], "brambling": ["燕雀"], "brigands": ["山賊", "路霸", "狗賊", "馬子", "營盤"], "creeper": ["蔓", "蔓生", "蔓生植物", "蔓草", "藟"], "teacup": ["茶杯", "茶碗", "蓋碗", "爭長論短"], "do sb proud": ["爭面子"], "dentin": ["牙本質"], "bird of prey": ["鵰", "猛禽", "雕", "鷙"], "long time off": ["猴年馬月"], "adansonia": ["猴麵包樹"], "tortilla chips": ["玉米片"], "2003-2015": ["王家瑞"], "class monitor": ["班長"], "present value": ["現值"], "swiss roll": ["瑞士捲"], "lovely color": ["瑞色"], "maxine": ["瑪克辛", "美心"], "epoxy resin": ["環氧樹脂"], "cyclic hydrocarbon": ["環烴"], "licorice": ["苷", "甘草"], "lamented": ["哀", "哭訴", "弔", "感嘆", "哀嘆"], "biological parents": ["生父母"], "biofuel": ["生物燃料"], "total output value": ["生產總值"], "calcium oxide cao": ["生石灰"], "chinese edible frog": ["田雞"], "yojana": ["由旬"], "gentian": ["甲紫", "龍膽", "秦艽", "龍膽紫"], "sto": ["申通"], "exchange student": ["留學生"], "detain a guest": ["留客"], "on the alert": ["警戒", "警惕", "留心眼兒", "警悟"], "resemble closely": ["畢肖"], "painting world": ["畫壇"], "atelier": ["畫室"], "dissident view": ["異說"], "skew": ["異面直線"], "very moment": ["當兒"], "a doubtful case": ["疑案"], "terminally ill": ["病危"], "to downsize": ["瘦身"], "employ talent": ["登庸人才"], "ta da": ["登愣"], "noddy": ["白頂玄鷗"], "baihequan": ["白鶴拳"], "treasure chest": ["百寶箱", "藏寳箱"], "all the grains": ["百穀"], "stories abound": ["盛傳"], "widely circulated": ["盛傳"], "spiral staircase": ["盤梯"], "rune": ["盧恩字母", "符文"], "touch-type": ["盲打"], "lasting until": ["直至"], "speak bluntly": ["直言不諱"], "guard each other": ["相保"], "worry-free": ["省心"], "gaze intently": ["眈"], "non-falsetto": ["真聲最高音"], "venomous glance": ["眼毒"], "blindfold": ["眼罩", "障眼"], "melanoma": ["黑瘤", "黑素瘤", "眼色素層黑色素瘤"], "muse": ["繆斯", "瞑想"], "short-tailed shearwater": ["短尾鸌"], "temporary job": ["短工", "零工"], "basset": ["短腿獵犬"], "short garment": ["短衣"], "toiling masses": ["短衣幫"], "short pants": ["短褲"], "graphene": ["石墨烯"], "pomegranate arils": ["石榴子"], "shiding": ["石碇", "石碇鄉"], "dianthus genus": ["石竹屬"], "shitai": ["石臺", "石臺縣"], "advantech": ["研華"], "break the rule": ["破格"], "arsine": ["砷化氫", "胂"], "fishes": ["魚類", "魚", "魚", "釣魚", "釣魚"], "largest-size": ["磅刷"], "chatter away incessantly": ["磨豆腐"], "ore stratum": ["礦層"], "social grouping": ["社群"], "social movement": ["社運"], "for generations": ["祖祖輩輩"], "welfare services": ["福利事業"], "fukien": ["福建", "福建省"], "scientific management": ["科學管理"], "coptic": ["科普特語"], "reaping": ["艾", "穫", "收割", "秋收", "收穫"], "tax system": ["稅制"], "under automatic control": ["程控"], "an intrusion": ["竄犯"], "4th-18th": ["立春"], "stereoisomerism": ["立體異構"], "end face": ["端面"], "trimeresurus stejnegeri": ["竹葉青蛇"], "a fence": ["籬"], "mickey": ["迷藥", "米老鼠", "米奇老鼠", "米奇"], "minoan": ["米諾安"], "elite troops": ["精兵"], "spiritual leader": ["精神領袖"], "updike": ["約翰·厄普代克"], "kombucha": ["紅茶菌"], "rufous-capped": ["紅頭穗鶥"], "goldfinch": ["紅額金翅雀"], "button loop": ["紐襻"], "ticker": ["紙帶", "股票代號", "跑馬燈"], "have always had": ["素有"], "soria": ["索里亞"], "mauve": ["紫紅色"], "run through": ["貫穿", "細數"], "examine carefully": ["細看"], "indelicate": ["絁"], "structuralism": ["結構主義"], "unexpected tricky move": ["絕招"], "dandelion": ["蒲公英", "絮球"], "scripture hall": ["經堂"], "economically backward": ["經濟落後"], "beryl": ["綠寶石"], "close securely": ["緊閉"], "county level": ["縣級"], "indent": ["縮排", "縮格", "頂格"], "striated bulbul": ["縱紋綠鵯"], "general armaments department": ["總裝備部"], "to plague sb": ["纏身"], "amnion": ["羊膜"], "braggart": ["羊質虎皮"], "meituan-dianping": ["美團點評"], "lynch": ["美林集團"], "manicure and-or pedicure": ["美甲"], "melamine loanword": ["美耐皿"], "beautified": ["美", "美容", "增色", "美顏", "美顏"], "righteous and courageous": ["義勇"], "earmuff": ["耳套"], "upright and outstanding": ["耿介"], "assemble together": ["聚合"], "polymerization": ["聚合作用"], "nyalam": ["聶拉木", "聶拉木縣"], "voluptuous": ["肉感"], "femoral": ["股動脈"], "extract water": ["脫水"], "coelacanth": ["腔棘魚"], "girth": ["腰圍", "韅"], "popliteal fossa": ["膕"], "roll of film": ["膠卷", "菲林", "膠捲"], "colloid": ["膠狀", "膠粒", "膠質", "膠體"], "kneecaps": ["膝蓋骨", "膝蓋骨", "髕骨", "髕骨", "臏刑"], "store front": ["臨街房", "鋪面"], "automatic clutch": ["自動離合"], "enjoy oneself quietly": ["自得其樂"], "comfort oneself": ["自我安慰"], "minding": ["心", "精神", "介意", "腦子", "在意"], "most respected": ["至尊"], "reach the pinnacle": ["臻化境"], "weight-lifting": ["舉重"], "tongue root": ["舌根"], "ship's ladder": ["船梯"], "fastened": ["繫", "固定", "扣", "攬", "扣上"], "satin textile": ["色丁"], "trp": ["色氨酸"], "semu": ["色目"], "colocasia": ["芋"], "semen euryales": ["雞頭米"], "wreathed hornbill": ["花冠皺盔犀鳥"], "figured": ["算", "數字", "數", "人士", "形象"], "anther": ["花藥"], "young years": ["芳華"], "rutaceae": ["芸香科"], "mdzod": ["若爾蓋", "若爾蓋縣"], "aniline c6h5nh2": ["苯胺"], "league of legends": ["英雄聯盟"], "small side table": ["茶几"], "lacewing": ["蜻蛉", "草蜻蛉"], "lipu": ["荔浦", "荔浦縣"], "mojave": ["莫哈韋沙漠"], "pinkafeld": ["萍卡菲爾特"], "ten-thousand": ["萬維天羅地網"], "fulva": ["萱草"], "curtain drops": ["落幕"], "cinereous tit": ["蒼背山雀"], "mongolian-born": ["蕭乾"], "samaranch": ["薩馬蘭奇"], "coriaria": ["藍膚木"], "wicker suitcase": ["藤篋"], "scaly thrush": ["虎斑地鶇"], "find oneself at": ["處在"], "imaginary number": ["虛數"], "northern barbarian": ["虜"], "ascaris": ["蛔", "蛔蟲", "蛔蟲病", "雚菌"], "odonata": ["蜻蛉目", "蜻蜓目"], "large turtles": ["蠵"], "silkworm eggs": ["蠶種", "蠶子"], "silkworm's": ["蠶眠"], "sericulturist": ["蠶農"], "blood poisoning": ["血中毒"], "blood and tears": ["血淚"], "hematin": ["血色素"], "about to act": ["行將"], "batter": ["衝擊", "衝打", "連擊"], "hengdong": ["衡東", "衡東縣"], "hat and clothes": ["衣冠"], "duchenne": ["裘馨氏肌肉萎縮症"], "fill a tooth": ["補牙"], "double-entry": ["複式"], "jerdon's baza": ["褐冠鵑隼"], "shikra": ["褐耳鷹"], "hemless skirt": ["襆"], "creases": ["襞", "皺", "皺", "褶皺", "褶皺"], "xicheng": ["西城區"], "transport under guard": ["解"], "unpack": ["解包"], "tactile": ["觸覺", "質感", "觸感", "觸毛", "觸診"], "trackpad": ["觸摸板"], "recalls": ["追", "追", "想起", "想起", "記憶"], "feelers": ["觸鬚", "鬚子", "鬚", "觸角", "厚薄規"], "antennae": ["觸鬚", "天線", "觸角", "微波天線", "雷達天線"], "bickering": ["計較", "拌嘴", "鬥嘴", "抬槓", "鬥口齒"], "ct computed tomography": ["計算機斷層"], "computational complexity": ["計算複雜性"], "make a promise": ["許下"], "diagnose": ["診斷", "診治"], "test marketing": ["試銷"], "lebron": ["詹姆斯"], "promote sex": ["誨淫"], "smelled": ["味道", "臭", "氣", "聞", "味"], "tell stories": ["說話"], "adjust upward": ["調升"], "ask for guidance": ["請教"], "humming sound": ["謍"], "aged care worker": ["護老者"], "sometimes called hieroglyph": ["象形", "象形字"], "worm-like invertebrate": ["豸"], "ravenous beast": ["豺"], "bellamy": ["貝拉米"], "currency exchange": ["貨幣兌換"], "guinan": ["貴南", "貴南縣"], "kapital": ["資本論"], "engage in prostitution": ["賣春"], "barefoot lawyer": ["赤腳律師"], "terra": ["赤陶"], "hezhen": ["赫哲語", "赫哲族"], "electric generator": ["起電機"], "stumbling along": ["跌跌爬爬"], "a prayer mat": ["跪毯"], "lunan": ["路南彞族自治縣", "路南區"], "diving platform": ["跳臺"], "do ensemble dancing": ["跳集體舞"], "lurch": ["蹣跚"], "manner of dancing": ["躚"], "make way for": ["躲讓"], "motor show": ["車展"], "trans-siberian": ["車里雅賓斯克"], "military nuclear power": ["軍事核大國"], "4-horse": ["軜"], "caster": ["輪腳"], "transfer character": ["轉注", "轉注字"], "forty-eighth": ["辛亥"], "fascinate": ["迷住"], "general motors": ["通用汽車公司"], "generally referred": ["通稱"], "wildcard": ["通配符"], "walk aimlessly": ["逯"], "operating method": ["運行方式"], "tolerably well": ["過得", "過得去"], "allergen": ["過敏原"], "dalton": ["道爾頓"], "taotai": ["道臺"], "delays": ["拖", "拖", "推", "推", "挨"], "remote affinity": ["遠緣"], "delivery address": ["配送地址"], "flaky pastry": ["酥"], "disgraceful show": ["醜劇"], "gimcheon": ["金泉"], "jinhu": ["金湖", "金湖縣"], "a golden couple": ["金童玉女"], "financial system": ["金融系統"], "conifer": ["針葉樹"], "large woodshrike": ["鉤嘴林鶪"], "silver standard": ["銀本位制"], "maidenhair": ["銀杏"], "yinhai": ["銀海", "銀海區"], "galaxias": ["銀魚"], "inscribed motto": ["銘"], "bedcover": ["鋪墊"], "sound recording": ["錄音"], "incorrect character": ["錯字"], "cool or chill": ["鎮"], "radium": ["鐳"], "tekken": ["鐵拳"], "agony": ["長痛不如短痛"], "supernumeraries": ["閑冗", "冗長", "增生"], "military command": ["閫寄"], "liminal": ["閾限"], "anti-virus": ["防毒軟件"], "aqsu": ["阿克蘇", "阿克蘇地區", "阿克蘇市"], "agnus": ["阿格尼迪"], "useless thing": ["阿物兒"], "amebiasis": ["阿米巴病"], "resina": ["阿魏"], "2016-2020": ["陳建仁"], "skier": ["陳美"], "terence": ["陶哲軒"], "revel": ["陶醉"], "1125-1210": ["陸遊"], "yanggao": ["陽高", "陽高縣"], "random interval": ["隨機時間"], "yardang": ["雅丹地貌"], "chengdu's main airport": ["雙流"], "young talent": ["雛鳳"], "nestling pigeon": ["雛鴿"], "grocer": ["雜貨商"], "homeplace": ["離鄉背井"], "urmia": ["雷扎耶湖"], "electronegativity": ["電負性"], "flashes": ["閃", "閃", "閃光", "閃光", "煥發"], "sinian": ["震旦紀"], "freezing weather": ["霜天"], "chinese green date": ["青棗"], "non-nuclear country": ["非核國家"], "stop whining": ["靠北"], "fuju": ["韓復榘"], "chives": ["細香蔥", "蝦夷蔥", "韭菜花", "韭菜"], "music television mtv": ["音樂電視"], "fulin": ["順治帝"], "commendation speech": ["頌詞"], "first start": ["領頭"], "dandruff": ["頭皮屑"], "youngster's talent": ["頭角"], "carotid": ["頸動脈"], "elbegdorj": ["額勒貝格·道爾吉"], "changeable situation": ["風雲變幻"], "darts": ["飛鏢", "鏢", "鏢", "飛鏢", "飛鏢"], "one's remaining years": ["餘年"], "chief financial officer": ["首席財務官"], "red nut sedge": ["香附"], "marrakech": ["馬拉喀什"], "marathi": ["馬拉地", "馬拉地語"], "magdeburg": ["馬格德堡"], "pearl oyster": ["馬氏珍珠貝"], "a barge": ["駁"], "validate": ["驗證"], "epiphyseal plate": ["骺軟骨板"], "tinea corporis": ["體癬"], "chinese fulvetta": ["高山雀鶥"], "takahashi": ["高橋", "高梁", "高橋留美子", "高梁市"], "haute couture": ["高檔服裝"], "senior post": ["高級職務"], "gaoyang": ["高陽", "高陽縣"], "gaoqing": ["高青", "高青縣"], "not consolidated": ["鬆散"], "100-170": ["魏伯陽"], "weidu": ["魏都", "魏都區"], "rubik's cube": ["魯畢克方塊"], "nomads": ["遊牧", "鮮卑族"], "gills of fish": ["鰓"], "fengshan": ["鳳山", "鳳山市", "鳳山縣"], "accipiter nisus": ["鷂"], "lukang": ["鹿港", "鹿港鎮"], "linlo": ["麟洛", "麟洛鄉"], "macmillan": ["麥克米蘭"], "malipo": ["麻栗坡", "麻栗坡縣"], "mazhang": ["麻章", "麻章區"], "yellow-green": ["黃綠"], "yellow-vented warbler": ["黃胸柳鶯"], "darter": ["黑腹蛇鵜"], "simultaneous fired cannonade": ["齊放"]}