{"word姐": [{"en": "my big sister (Internet slang version of 我的姐[wo3 de5 jie3])", "pinyin": "w o r d jie3"}], "㐖毒": [{"en": "India (archaic)", "pinyin": "Xie2 du2"}], "岸": [{"en": "variant of 岸[an4]", "pinyin": "an4"}, {"en": "bank, shore, beach, coast, CL:個|个[ge4]", "pinyin": "an4"}], "一一": [{"en": "one by one, one after another", "pinyin": "yi1 yi1"}], "一一映射": [{"en": "bijective map (i.e. map between sets in math. that is one-to-one and onto), one-to-one correspondence", "pinyin": "yi1 yi1 ying4 she4"}], "一拍即合": [{"en": "lit. to be together from the first beat (idiom), to hit it off, to click together, to chime in easily", "pinyin": "yi1 pai1 ji2 he2"}], "一望而知": [{"en": "to be evident at a glance (idiom)", "pinyin": "yi1 wang4 er2 zhi1"}], "一气": [{"en": "at one go, at a stretch, for a period of time, forming a gang", "pinyin": "yi1 qi4"}], "一身两役": [{"en": "one person taking on two tasks simultaneously", "pinyin": "yi1 shen1 liang3 yi4"}], "三等分": [{"en": "trisection (math.), trisecting an angle", "pinyin": "san1 deng3 fen1"}], "三贞九烈": [{"en": "(of a widow) faithful to the death to her husband's memory", "pinyin": "san1 zhen1 jiu3 lie4"}], "上弦": [{"en": "to wind, to tighten, crescent moon, first quarter or waxing moon", "pinyin": "shang4 xian2"}], "上林县": [{"en": "Shanglin county in Nanning 南寧|南宁[Nan2 ning2], Guangxi", "pinyin": "Shang4 lin2 xian4"}], "上海合作组织": [{"en": "Shanghai Cooperation Organisation (SCO)", "pinyin": "Shang4 hai3 He2 zuo4 Zu3 zhi1"}], "上确界": [{"en": "supremum (math.), least upper bound", "pinyin": "shang4 que4 jie4"}], "下划线": [{"en": "underscore _, underline", "pinyin": "xia4 hua4 xian4"}], "下发": [{"en": "to issue (a memorandum etc) to lower levels, to distribute (e.g. disaster relief to victims)", "pinyin": "xia4 fa1"}], "下关区": [{"en": "Xiaguan district of Nanjing City 南京市 in Jiangsu 江蘇|江苏", "pinyin": "Xia4 guan1 qu1"}], "不事张扬": [{"en": "quietly, without ostentation", "pinyin": "bu4 shi4 zhang1 yang2"}], "不分上下": [{"en": "not to know one's place", "pinyin": "bu4 fen1 shang4 xia4"}], "不可数": [{"en": "uncountable", "pinyin": "bu4 ke3 shu3"}], "不在状态": [{"en": "to be out of form, not to be oneself", "pinyin": "bu4 zai4 zhuang4 tai4"}], "不治而愈": [{"en": "to recover spontaneously (from an illness), to get better without medical treatment", "pinyin": "bu4 zhi4 er2 yu4"}], "不理不睬": [{"en": "to completely ignore (idiom), to pay no attention to, not to be in the least concerned about", "pinyin": "bu4 li3 bu4 cai3"}], "中介所": [{"en": "agency", "pinyin": "zhong1 jie4 suo3"}], "中国人": [{"en": "Chinese person", "pinyin": "Zhong1 guo2 ren2"}], "中国国际航空公司": [{"en": "Air China Ltd.", "pinyin": "Zhong1 guo2 Guo2 ji4 Hang2 kong1 Gong1 si1"}], "中国感恩节": [{"en": "Chinese Thanksgiving, another name for 蛋炒飯節|蛋炒饭节[Dan4 chao3 fan4 jie2]", "pinyin": "Zhong1 guo2 Gan3 en1 jie2"}], "中国电信": [{"en": "China Telecom (Chinese company providing mobile phone service)", "pinyin": "Zhong1 guo2 Dian4 xin4"}], "中性笔": [{"en": "rollerball pen", "pinyin": "zhong1 xing4 bi3"}], "中级": [{"en": "middle level (in a hierarchy)", "pinyin": "zhong1 ji2"}], "主料": [{"en": "main ingredients (in a cooking recipe)", "pinyin": "zhu3 liao4"}], "主法向量": [{"en": "principal normal vector (to a space curve)", "pinyin": "zhu3 fa3 xiang4 liang4"}], "九卿": [{"en": "the Nine Ministers (in imperial China)", "pinyin": "jiu3 qing1"}], "干嚎": [{"en": "to cry out loud without tears", "pinyin": "gan1 hao2"}], "干煸土豆丝": [{"en": "dry-fried potato slices (Chinese dish)", "pinyin": "gan1 bian1 tu3 dou4 si1"}], "干瞪眼": [{"en": "to watch helplessly", "pinyin": "gan1 deng4 yan3"}], "干酪素": [{"en": "casein", "pinyin": "gan1 lao4 su4"}], "二次元": [{"en": "two-dimensional, the fictional worlds of anime, comics and games", "pinyin": "er4 ci4 yuan2"}], "二进制编码": [{"en": "binary code, binary encoding", "pinyin": "er4 jin4 zhi4 bian1 ma3"}], "互异": [{"en": "differing from one another, mutually different", "pinyin": "hu4 yi4"}], "五常": [{"en": "Wuchang county level city in Harbin 哈爾濱|哈尔滨[Ha1 er3 bin1], Heilongjiang, the Permanent Five (the five permanent members of the United Nations Security Council: China, France, Russia, the UK, and the USA)", "pinyin": "Wu3 chang2"}, {"en": "five constant virtues of Confucianism, namely: benevolence 仁, righteousness 義|义, propriety 禮|礼, wisdom 智 and fidelity 信, five cardinal relationships of Confucianism (between ruler and subject, father and son, husband and wife, brothers, friends), five phases of Chinese philosophy: water 水, fire 火, wood 木, metal 金, earth 土", "pinyin": "wu3 chang2"}], "五胡十六国": [{"en": "Sixteen Kingdoms of Five non-Han people (ruling most of China 304-439)", "pinyin": "Wu3 hu2 Shi2 liu4 guo2"}], "交易者": [{"en": "dealer", "pinyin": "jiao1 yi4 zhe3"}], "京东": [{"en": "Jingdong, Chinese e-commerce company", "pinyin": "Jing1 dong1"}], "亮锃锃": [{"en": "polished to a shine, shiny, glistening", "pinyin": "liang4 zeng4 zeng4"}], "人民战争": [{"en": "people's war (Maoist military strategy)", "pinyin": "ren2 min2 zhan4 zheng1"}], "人头税": [{"en": "poll tax", "pinyin": "ren2 tou2 shui4"}], "人体解剖学": [{"en": "human anatomy", "pinyin": "ren2 ti3 jie3 pou1 xue2"}], "代购": [{"en": "to buy (on behalf of sb)", "pinyin": "dai4 gou4"}], "伊斯帕尼奥拉": [{"en": "Hispaniola (Caribbean island including Haiti and the Dominican Republic)", "pinyin": "Yi1 si1 pa4 ni2 ao4 la1"}], "伯仲叔季": [{"en": "eldest, second, third and youngest of brothers, order of seniority among brothers", "pinyin": "bo2 zhong4 shu1 ji4"}], "住宅楼": [{"en": "residential building, CL:幢[zhuang4],座[zuo4],棟|栋[dong4]", "pinyin": "zhu4 zhai2 lou2"}], "佛语": [{"en": "Buddhist term", "pinyin": "fo2 yu3"}], "佰": [{"en": "hundred (banker's anti-fraud numeral)", "pinyin": "bai3"}], "侏儒仓鼠": [{"en": "dwarf hamster", "pinyin": "zhu1 ru2 cang1 shu3"}], "供花": [{"en": "flower offering", "pinyin": "gong4 hua1"}], "依依不舍": [{"en": "reluctant to part (idiom); broken-hearted at having to leave", "pinyin": "yi1 yi1 bu4 she3"}], "俄狄浦斯期": [{"en": "oedipal phase (psychology)", "pinyin": "e2 di2 pu3 si1 qi1"}], "保山地区": [{"en": "Baoshan prefecture in Yunnan", "pinyin": "Bao3 shan1 di4 qu1"}], "保鲜期": [{"en": "shelf life, freshness date", "pinyin": "bao3 xian1 qi1"}], "信宿": [{"en": "(ancient) to lodge for two nights", "pinyin": "xin4 su4"}], "修造厂": [{"en": "repair workshop (for machinery, vehicles etc)", "pinyin": "xiu1 zao4 chang3"}], "个把": [{"en": "one or two, a couple of", "pinyin": "ge4 ba3"}], "倒胃口": [{"en": "to spoil one's appetite, fig. to get fed up with sth", "pinyin": "dao3 wei4 kou3"}], "借故": [{"en": "to find an excuse", "pinyin": "jie4 gu4"}], "借重": [{"en": "to rely on sb for support", "pinyin": "jie4 zhong4"}], "假仙": [{"en": "(Tw) to pretend, to put on a false front, (Taiwanese, Tai-lo pr. [ké-sian])", "pinyin": "jia3 xian1"}], "偏态": [{"en": "skewness (math)", "pinyin": "pian1 tai4"}], "做派": [{"en": "way of doing sth, behavior, to act in an affected manner, mannerism, gestures in opera", "pinyin": "zuo4 pai4"}], "偷工": [{"en": "to skimp on the job, to avoid work", "pinyin": "tou1 gong1"}], "伪书": [{"en": "forged book, book of dubious authenticity, misattributed book, Apocrypha", "pinyin": "wei3 shu1"}], "傜": [{"en": "Yao tribe", "pinyin": "yao2"}], "传动器": [{"en": "drive (engine)", "pinyin": "chuan2 dong4 qi4"}], "传票": [{"en": "summons, subpoena, voucher", "pinyin": "chuan2 piao4"}], "伤怀": [{"en": "grieved, full of sorrow", "pinyin": "shang1 huai2"}], "价码": [{"en": "price tag", "pinyin": "jia4 ma3"}], "偿命": [{"en": "to pay with one's life", "pinyin": "chang2 ming4"}], "优胜": [{"en": "winning, superior", "pinyin": "you1 sheng4"}], "光量": [{"en": "quantity of light, luminosity", "pinyin": "guang1 liang4"}], "儿媳妇儿": [{"en": "erhua variant of 兒媳婦|儿媳妇[er2 xi2 fu5]", "pinyin": "er2 xi2 fu5 r5"}], "入球": [{"en": "to score a goal, goal", "pinyin": "ru4 qiu2"}], "内卷": [{"en": "(embryology) to involute, involution, (neologism c. 2017) (of a society) to become more and more of a rat race, to become increasingly competitive (due to limited resources)", "pinyin": "nei4 juan3"}], "内唇": [{"en": "epipharynx (entomology), inner part of the lip", "pinyin": "nei4 chun2"}], "全局语境": [{"en": "global context", "pinyin": "quan2 ju2 yu3 jing4"}], "全州市": [{"en": "Jeonju city, capital of North Jeolla Province, in west South Korea", "pinyin": "Quan2 zhou1 shi4"}], "八步": [{"en": "Babu district of Hezhou city 賀州市|贺州市[He4 zhou1 shi4], Guangxi", "pinyin": "Ba1 bu4"}], "八珍汤": [{"en": "eight-treasure decoction, tonic formula used in Chinese medicine", "pinyin": "ba1 zhen1 tang1"}], "公主抱": [{"en": "to carry sb the way grooms carry brides across the threshold", "pinyin": "gong1 zhu3 bao4"}], "公伤事故": [{"en": "industrial accident, work-related injury", "pinyin": "gong1 shang1 shi4 gu4"}], "公开讨论会": [{"en": "open forum", "pinyin": "gong1 kai1 tao3 lun4 hui4"}], "具体而微": [{"en": "miniature, scaled-down, forming a microcosm", "pinyin": "ju4 ti3 er2 wei1"}], "冤头": [{"en": "enemy, foe", "pinyin": "yuan1 tou2"}], "冰河时代": [{"en": "ice age", "pinyin": "bing1 he2 shi2 dai4"}], "冰镐": [{"en": "ice pick", "pinyin": "bing1 gao3"}], "凛遵": [{"en": "to strictly abide by", "pinyin": "lin3 zun1"}], "分社": [{"en": "subdivision or branch of an organization, news bureau", "pinyin": "fen1 she4"}], "切入": [{"en": "to cut into, to incise, to penetrate deeply into (a topic, area etc), cut (offensive moves in basketball)", "pinyin": "qie1 ru4"}], "切特豪斯学校": [{"en": "Charterhouse public school (UK)", "pinyin": "Qie1 te4 hao2 si1 xue2 xiao4"}], "切结书": [{"en": "affidavit, written pledge", "pinyin": "qie4 jie2 shu1"}], "初心": [{"en": "(one's) original intention, aspiration etc, (Buddhism) \"beginner's mind\" (i.e. having an attitude of openness when studying a subject just as a beginner in that subject would)", "pinyin": "chu1 xin1"}], "别树一帜": [{"en": "lit. to fly one's banner on a solitary tree (idiom); fig. to act as a loner, to stand out, to develop one's own school, to have attitude of one's own", "pinyin": "bie2 shu4 yi1 zhi4"}], "利他能": [{"en": "Ritalin (brand name), methylphenidate (stimulant drug used to treat ADHD), also written 利他林[Li4 ta1 lin2]", "pinyin": "Li4 ta1 neng2"}], "到案": [{"en": "to make an appearance in court", "pinyin": "dao4 an4"}], "制造业": [{"en": "manufacturing industry", "pinyin": "zhi4 zao4 ye4"}], "刻日": [{"en": "variant of 克日[ke4 ri4]", "pinyin": "ke4 ri4"}], "剃发留辫": [{"en": "to shave the head but keep the queue", "pinyin": "ti4 fa4 liu2 bian4"}], "剖腹产手术": [{"en": "Cesarean section operation", "pinyin": "pou1 fu4 chan3 shou3 shu4"}], "刬": [{"en": "variant of 鏟|铲[chan3]", "pinyin": "chan3"}], "剥削阶级": [{"en": "exploiting class (in Marxist theory)", "pinyin": "bo1 xue1 jie1 ji2"}], "剪刀差": [{"en": "prices scissor (caught between low income and high prices)", "pinyin": "jian3 dao1 cha1"}], "副秘书长": [{"en": "vice-secretary", "pinyin": "fu4 mi4 shu1 zhang3"}], "刘表": [{"en": "Liu Biao (142-208), warlord", "pinyin": "Liu2 Biao3"}], "劐": [{"en": "(coll.) to slit with a knife, (variant of 耠[huo1]) hoe, to loosen soil with a hoe", "pinyin": "huo1"}, {"en": "(literary) variant of 穫|获[huo4]", "pinyin": "huo4"}], "加拉帕戈斯群岛": [{"en": "Galapagos Islands", "pinyin": "Jia1 la1 pa4 ge1 si1 Qun2 dao3"}], "加沃特": [{"en": "gavotte, French dance popular in 18th century (loanword)", "pinyin": "jia1 wo4 te4"}], "加餐": [{"en": "to have an extra meal, snack", "pinyin": "jia1 can1"}], "动L": [{"en": "flowing, flexible, lively (Internet slang)", "pinyin": "dong4 L"}], "勘界": [{"en": "boundary survey", "pinyin": "kan1 jie4"}], "勤俭耐劳": [{"en": "diligent and able to endure hardship (idiom)", "pinyin": "qin2 jian3 nai4 lao2"}], "化学信息素": [{"en": "semiochemical", "pinyin": "hua4 xue2 xin4 xi1 su4"}], "北山": [{"en": "northern mountain, refers to Mt Mang 邙山 at Luoyang in Henan", "pinyin": "Bei3 shan1"}], "北达科他": [{"en": "North Dakota, US state", "pinyin": "Bei3 Da2 ke1 ta1"}], "汇兑": [{"en": "remittance, funds paid to a bank account", "pinyin": "hui4 dui4"}], "千里搭长棚，没有不散的宴席": [{"en": "even if you build a thousand-league awning for it, every banquet must come to an end (idiom)", "pinyin": "qian1 li3 da1 chang2 peng2 , mei2 you3 bu4 san4 de5 yan4 xi2"}], "千里送鹅毛，礼轻情意重": [{"en": "goose feather sent from afar, a trifling present with a weighty thought behind it (idiom); It's not the gift that counts, but the thought behind it.", "pinyin": "qian1 li3 song4 e2 mao2 , li3 qing1 qing2 yi4 zhong4"}], "南天门": [{"en": "The Southern Heavenly Gates, a name for a mountain pass gate in several places", "pinyin": "Nan2 tian1 men2"}], "南沙": [{"en": "Nansha Islands or Spratly Islands, Nansha District of Guangzhou City 廣州市|广州市[Guang3 zhou1 Shi4], Guangdong", "pinyin": "Nan2 sha1"}], "南郭": [{"en": "surname Nanguo", "pinyin": "Nan2 guo1"}], "単": [{"en": "Japanese variant of 單|单", "pinyin": "dan1"}], "博学": [{"en": "learned, erudite", "pinyin": "bo2 xue2"}], "博弈论": [{"en": "game theory", "pinyin": "bo2 yi4 lun4"}], "卡内基": [{"en": "Carnegie (name), Andrew Carnegie (1835-1919), Scots American steel millionaire and philanthropist", "pinyin": "Ka3 nei4 ji1"}], "卡乐星": [{"en": "Carl's Jr. (fast-food restaurant chain)", "pinyin": "Ka3 le4 xing1"}], "卡特彼勒公司": [{"en": "Caterpillar Inc.", "pinyin": "Ka3 te4 bi3 le4 gong1 si1"}], "印子": [{"en": "trace, impression (e.g. footprint), abbr. of 印子錢|印子钱[yin4 zi5 qian2], usury", "pinyin": "yin4 zi5"}], "卷绕": [{"en": "to wind, to coil, to spool, to loop around, winding", "pinyin": "juan3 rao4"}], "原形毕露": [{"en": "original identity fully revealed (idiom); fig. to unmask and expose the whole truth", "pinyin": "yuan2 xing2 bi4 lu4"}], "厌酷球孢子菌": [{"en": "Coccidioides immitis", "pinyin": "yan4 ku4 qiu2 bao1 zi3 jun1"}], "厼": [{"en": "one of the characters used in kwukyel (phonetic \"keum\"), an ancient Korean writing system", "pinyin": "xx5"}], "反科学": [{"en": "anti-science, anti-scientific", "pinyin": "fan3 ke1 xue2"}], "反贪污": [{"en": "anticorruption", "pinyin": "fan3 tan1 wu1"}], "叔子": [{"en": "brother-in-law, husband's younger brother", "pinyin": "shu1 zi5"}], "取样数量": [{"en": "sample size (statistics)", "pinyin": "qu3 yang4 shu4 liang4"}], "受洗命名": [{"en": "to be christened", "pinyin": "shou4 xi3 ming4 ming2"}], "受益匪浅": [{"en": "to benefit (from)", "pinyin": "shou4 yi4 fei3 qian3"}], "叫阵": [{"en": "to challenge an opponent to a fight", "pinyin": "jiao4 zhen4"}], "召集人": [{"en": "convener", "pinyin": "zhao4 ji2 ren2"}], "可读音性": [{"en": "pronounceability", "pinyin": "ke3 du2 yin1 xing4"}], "可贵": [{"en": "to be treasured, praiseworthy", "pinyin": "ke3 gui4"}], "各界": [{"en": "all walks of life, all social circles", "pinyin": "ge4 jie4"}], "合成器": [{"en": "synthesizer", "pinyin": "he2 cheng2 qi4"}], "合成纤维": [{"en": "synthetic fiber", "pinyin": "he2 cheng2 xian1 wei2"}], "合成语音": [{"en": "assembled phonology", "pinyin": "he2 cheng2 yu3 yin1"}], "合眼": [{"en": "to close one's eyes, to get to sleep", "pinyin": "he2 yan3"}], "吉迪恩": [{"en": "Gideon (name, from Judges 6:11-ffoll.), also written 基甸", "pinyin": "Ji2 di2 en1"}], "同分异构": [{"en": "isomerism (chemistry)", "pinyin": "tong2 fen1 yi4 gou4"}], "同道者": [{"en": "fellow-traveler, like-minded person", "pinyin": "tong2 dao4 zhe3"}], "名义上": [{"en": "nominally", "pinyin": "ming2 yi4 shang4"}], "向壁虚构": [{"en": "facing a wall, an imaginary construction (idiom); baseless fabrication", "pinyin": "xiang4 bi4 xu1 gou4"}], "向性": [{"en": "tropism", "pinyin": "xiang4 xing4"}], "向量图形": [{"en": "vector graphics (computer)", "pinyin": "xiang4 liang4 tu2 xing2"}], "吡叻": [{"en": "Perak (state of Malaysia)", "pinyin": "Bi3 le4"}], "含糊其词": [{"en": "to equivocate, to talk evasively (idiom)", "pinyin": "han2 hu2 qi2 ci2"}], "吸毒成瘾": [{"en": "drug addiction", "pinyin": "xi1 du2 cheng2 yin3"}], "吸门": [{"en": "epiglottis", "pinyin": "xi1 men2"}], "呼伦湖": [{"en": "Hulun Lake of Inner Mongolia", "pinyin": "Hu1 lun2 Hu2"}], "呼噜": [{"en": "(onom.) wheezing", "pinyin": "hu1 lu1"}, {"en": "(onom.) snoring, Taiwan pr. [hu1 lu1]", "pinyin": "hu1 lu5"}], "咄": [{"en": "(old)(interjection expressing disapproval, commiseration etc) tut!, Taiwan pr. [duo4]", "pinyin": "duo1"}], "咬伤": [{"en": "bite (e.g. snake bite, mosquito bite)", "pinyin": "yao3 shang1"}], "哈珀": [{"en": "Harper (name), see also 斯蒂芬·哈珀[Si1 di4 fen1 · Ha1 po4]", "pinyin": "Ha1 po4"}], "哨": [{"en": "a whistle, sentry", "pinyin": "shao4"}], "哲蚌寺": [{"en": "Drepung monastery, Lhasa, Tibet", "pinyin": "Zhe2 bang4 si4"}], "哺乳期": [{"en": "breastfeeding period, lactation period, suckling period", "pinyin": "bu3 ru3 qi1"}], "唐中宗": [{"en": "Emperor Zhongzong of Tang, reign name of fourth Tang emperor Li Zhe 李哲[Li3 Zhe2] (656-710), reigned 705-710", "pinyin": "Tang2 Zhong1 zong1"}], "唯识宗": [{"en": "Yogachara school of Buddhism (\"consciousness only\" school of Buddhism)", "pinyin": "Wei2 shi2 zong1"}], "哑鼓": [{"en": "drum practice pad (music), a practice drum (music)", "pinyin": "ya3 gu3"}], "喀麦隆": [{"en": "Cameroon", "pinyin": "Ka1 mai4 long2"}], "喝采": [{"en": "to acclaim, to cheer", "pinyin": "he4 cai3"}], "丧亡": [{"en": "to die", "pinyin": "sang4 wang2"}], "丧尽天良": [{"en": "devoid of conscience (idiom); utterly heartless", "pinyin": "sang4 jin4 tian1 liang2"}], "喰": [{"en": "old variant of 餐[can1]", "pinyin": "can1"}], "慨": [{"en": "old variant of 慨[kai3], to sigh (with emotion)", "pinyin": "kai3"}, {"en": "indignant, generous, to sigh (with emotion)", "pinyin": "kai3"}], "哗儿哗儿": [{"en": "(dialect) sound used to call cats", "pinyin": "hua2 r5 hua2 r5"}], "嗳气腐臭": [{"en": "putrid belching (medical term)", "pinyin": "ai4 qi4 fu3 chou4"}], "困厄": [{"en": "in deep water, difficult situation", "pinyin": "kun4 e4"}], "固化": [{"en": "to solidify, solidification (chemistry)", "pinyin": "gu4 hua4"}], "国务院港澳事务办公室": [{"en": "Hong Kong and Macao Affairs Office of the State Council", "pinyin": "Guo2 wu4 yuan4 Gang3 Ao4 Shi4 wu4 Ban4 gong1 shi4"}], "国土资源部": [{"en": "Ministry of Land and Resources (MLR), formed in 1998", "pinyin": "Guo2 tu3 Zi1 yuan2 bu4"}], "国家安全局": [{"en": "National Security Bureau (NSB) (Tw), National Security Agency (NSA) (USA)", "pinyin": "Guo2 jia1 An1 quan2 ju2"}], "国小": [{"en": "elementary school (Tw), abbr. for 國民小學|国民小学[guo2 min2 xiao3 xue2]", "pinyin": "guo2 xiao3"}], "国际法庭": [{"en": "International Court of Justice in The Hague", "pinyin": "Guo2 ji4 Fa3 ting2"}], "围堰": [{"en": "a cofferdam", "pinyin": "wei2 yan4"}], "圆腹鲱": [{"en": "round herring", "pinyin": "yuan2 fu4 fei1"}], "团体冠军": [{"en": "group championship", "pinyin": "tuan2 ti3 guan4 jun1"}], "土著人": [{"en": "indigenous person, aboriginal", "pinyin": "tu3 zhu4 ren2"}], "地下通道": [{"en": "underpass, subway, tunnel", "pinyin": "di4 xia4 tong1 dao4"}], "地层学": [{"en": "stratigraphy (geology)", "pinyin": "di4 ceng2 xue2"}], "地拉那": [{"en": "Tirana, capital of Albania", "pinyin": "Di4 la1 na4"}], "地瓜": [{"en": "sweet potato (Ipomoea batatas), yam (family Dioscoreaceae)", "pinyin": "di4 gua1"}], "址": [{"en": "location, site, foundation of a building", "pinyin": "zhi3"}, {"en": "foundation of a building (variant of 址[zhi3]), islet (variant of 沚[zhi3])", "pinyin": "zhi3"}], "坐降落伞": [{"en": "to do a parachute jump", "pinyin": "zuo4 jiang4 luo4 san3"}], "垤": [{"en": "anthill, mound", "pinyin": "die2"}], "埋天怨地": [{"en": "lit. to blame the heavens and reproach the earth, fig. to rave and rant", "pinyin": "man2 tian1 yuan4 di4"}], "埤头": [{"en": "Pitou Township in Changhua County 彰化縣|彰化县[Zhang1 hua4 Xian4], Taiwan", "pinyin": "Pi2 tou2"}], "执政党": [{"en": "ruling party, the party in power", "pinyin": "zhi2 zheng4 dang3"}], "执教": [{"en": "to teach, to be a teacher, to train, to coach", "pinyin": "zhi2 jiao4"}], "基建": [{"en": "capital construction (project), infrastructure", "pinyin": "ji1 jian4"}], "堈": [{"en": "earthen jug, crock, cistern", "pinyin": "gang1"}], "场区": [{"en": "(sports) section of a court or playing field, (computer chip manufacture) field area", "pinyin": "chang3 qu1"}], "塔吉克": [{"en": "Tajik ethnic group, Tajikistan, former Soviet republic adjoining Xinjiang and Afghanistan", "pinyin": "Ta3 ji2 ke4"}], "塬": [{"en": "plateau, esp. Loess Plateau of northwest China 黃土高原|黄土高原[Huang2 tu3 Gao1 yuan2]", "pinyin": "yuan2"}], "增防": [{"en": "to reinforce defenses", "pinyin": "zeng1 fang2"}], "墨纸": [{"en": "blotting paper", "pinyin": "mo4 zhi3"}], "夕照": [{"en": "glow of the setting sun", "pinyin": "xi1 zhao4"}], "外商": [{"en": "foreign businessman", "pinyin": "wai4 shang1"}], "外场": [{"en": "outside world, society", "pinyin": "wai4 chang2"}, {"en": "outer area (of a place that has an inner area), dining area of a restaurant (as opposed to the kitchen), outfield (baseball etc), area outside a venue (e.g. exterior of a stadium), field (maintenance, testing etc), (Chinese opera) the area in front of the table on the stage", "pinyin": "wai4 chang3"}], "多腺染色体": [{"en": "polytene chromosome", "pinyin": "duo1 xian4 ran3 se4 ti3"}], "多党": [{"en": "multiparty", "pinyin": "duo1 dang3"}], "大公国": [{"en": "grand duchy", "pinyin": "da4 gong1 guo2"}], "大排档": [{"en": "food stall, open-air restaurant", "pinyin": "da4 pai2 dang4"}], "大柴旦镇": [{"en": "Da Qaidam town in Haixi Mongol and Tibetan autonomous prefecture 海西蒙古族藏族自治州[Hai3 xi1 Meng3 gu3 zu2 Zang4 zu2 zi4 zhi4 zhou1], Qinghai", "pinyin": "Da4 chai2 dan4 zhen4"}], "大港区": [{"en": "Dagang former district of Tianjin, now part of Binhai subprovincial district 濱海新區|滨海新区[Bin1 hai3 xin1 qu1]", "pinyin": "Da4 gang3 qu1"}], "大尽": [{"en": "lunar month of 30 days, same as 大建[da4 jian4]", "pinyin": "da4 jin4"}], "大余": [{"en": "Dayu county in Ganzhou 贛州|赣州[Gan4 zhou1], Jiangxi", "pinyin": "Da4 yu2"}], "大鸿胪": [{"en": "Grand Herald in imperial China, one of the Nine Ministers 九卿[jiu3 qing1]", "pinyin": "da4 hong2 lu2"}], "天公地道": [{"en": "absolutely fair and reasonable (idiom); equitable", "pinyin": "tian1 gong1 di4 dao4"}], "天体演化学": [{"en": "cosmogony", "pinyin": "tian1 ti3 yan3 hua4 xue2"}], "天龙人": [{"en": "(slang) (Tw) person from Taipei 臺北|台北[Tai2 bei3]", "pinyin": "Tian1 long2 ren2"}], "太婆": [{"en": "great-grandmother", "pinyin": "tai4 po2"}], "失当": [{"en": "inappropriate, improper", "pinyin": "shi1 dang4"}], "夹板": [{"en": "splint, clamp, vise (as torture instrument)", "pinyin": "jia1 ban3"}], "女工": [{"en": "working woman, variant of 女紅|女红[nu:3 gong1]", "pinyin": "nu:3 gong1"}], "奶精": [{"en": "non-dairy creamer", "pinyin": "nai3 jing1"}], "好自为之": [{"en": "to do one's best, to shape up, to behave, to fend for oneself, you're on your own", "pinyin": "hao3 zi4 wei2 zhi1"}], "妙语如珠": [{"en": "sparkling with wit (idiom)", "pinyin": "miao4 yu3 ru2 zhu1"}], "姘头": [{"en": "lover, mistress", "pinyin": "pin1 tou5"}], "奸杀": [{"en": "to rape and murder", "pinyin": "jian1 sha1"}], "威望": [{"en": "prestige", "pinyin": "wei1 wang4"}], "威玛": [{"en": "Weimar (German city)", "pinyin": "Wei1 ma3"}], "娜娜": [{"en": "Nana (name), Nana (1880 novel by Émile Zola), Nana (Japanese manga series)", "pinyin": "Na4 na4"}], "婚外": [{"en": "extramarital", "pinyin": "hun1 wai4"}], "媒体接口连接器": [{"en": "medium interface connector", "pinyin": "mei2 ti3 jie1 kou3 lian2 jie1 qi4"}], "嫄": [{"en": "name of an empress", "pinyin": "yuan2"}], "孝道": [{"en": "filial piety (Confucian virtue), to be a good son or daughter", "pinyin": "xiao4 dao5"}], "孟良崮": [{"en": "Mt Mengliang in Mengyin county 蒙陰縣|蒙阴县[Meng2 yin1 xian4], Linyi 臨沂|临沂[Lin2 yi2], Shandong", "pinyin": "Meng4 liang2 gu4"}], "孤高": [{"en": "arrogant", "pinyin": "gu1 gao1"}], "孙毓棠": [{"en": "Sun Yutang (1911-1985), historian and poet, studied in Tokyo, Oxford and Harvard", "pinyin": "Sun1 Yu4 tang2"}], "宅男": [{"en": "a guy who stays at home all the time, typically spending a lot of time playing online games (derived from Japanese \"otaku\")", "pinyin": "zhai2 nan2"}], "守一而终": [{"en": "to be faithful to one's mate all one's life", "pinyin": "shou3 yi1 er2 zhong1"}], "守成": [{"en": "to preserve the accomplishments of previous generations, to carry on the good work of one's predecessors", "pinyin": "shou3 cheng2"}], "完型填空": [{"en": "cloze (pedagogy)", "pinyin": "wan2 xing2 tian2 kong4"}], "定出": [{"en": "to determine, to fix upon, to set (a target, a price etc)", "pinyin": "ding4 chu1"}], "客家": [{"en": "Hakka ethnic group, a subgroup of the Han that in the 13th century migrated from northern China to the south", "pinyin": "Ke4 jia1"}], "害兽": [{"en": "vermin, harmful animal", "pinyin": "hai4 shou4"}], "宿营地": [{"en": "camp, campsite", "pinyin": "su4 ying2 di4"}], "寄销": [{"en": "to dispatch, consigned (goods)", "pinyin": "ji4 xiao1"}], "宁冈县": [{"en": "former Ninggang county in Jiangxi, now within Jinggangshan county level city 井岡山市|井冈山市[Jing3 gang1 shan1 shi4] in Ji'an 吉安, Jiangxi", "pinyin": "Ning2 gang1 xian4"}], "写意": [{"en": "to suggest (rather than depict in detail), freehand style of Chinese painting, characterized by bold strokes rather than accurate details", "pinyin": "xie3 yi4"}, {"en": "comfortable, enjoyable, relaxed", "pinyin": "xie4 yi4"}], "宽假": [{"en": "to pardon, to excuse", "pinyin": "kuan1 jia3"}], "宽贷": [{"en": "to pardon, to excuse", "pinyin": "kuan1 dai4"}], "寰": [{"en": "large domain, extensive region", "pinyin": "huan2"}], "宝殿": [{"en": "king's palace, throne hall", "pinyin": "bao3 dian4"}], "宝兴鹛雀": [{"en": "(bird species of China) rufous-tailed babbler (Moupinia poecilotis)", "pinyin": "Bao3 xing4 mei2 que4"}], "专利局": [{"en": "patent office", "pinyin": "zhuan1 li4 ju2"}], "专征": [{"en": "to go on a personal punitive expedition", "pinyin": "zhuan1 zheng1"}], "专管": [{"en": "to be in charge of something specific", "pinyin": "zhuan1 guan3"}], "专卖店": [{"en": "specialty store", "pinyin": "zhuan1 mai4 dian4"}], "尊从": [{"en": "to obey, to observe, to follow", "pinyin": "zun1 cong2"}], "小妹": [{"en": "little sister, girl, (Tw) young female employee working in a low-level role dealing with the public (assistant, waitress, attendant etc)", "pinyin": "xiao3 mei4"}], "小写字母": [{"en": "lowercase (letters)", "pinyin": "xiao3 xie3 zi4 mu3"}], "小白鼠": [{"en": "white mouse, lab mouse, lab rat, (fig.) human guinea pig", "pinyin": "xiao3 bai2 shu3"}], "小蝗莺": [{"en": "(bird species of China) Pallas's grasshopper warbler (Locustella certhiola)", "pinyin": "xiao3 huang2 ying1"}], "小麦胚芽": [{"en": "wheat germ", "pinyin": "xiao3 mai4 pei1 ya2"}], "尖尾滨鹬": [{"en": "(bird species of China) sharp-tailed sandpiper (Calidris acuminata)", "pinyin": "jian1 wei3 bin1 yu4"}], "尖锐湿疣": [{"en": "genital wart, condyloma acuminatum", "pinyin": "jian1 rui4 shi1 you2"}], "尤卡坦半岛": [{"en": "Yucatan Peninsula (Mexico)", "pinyin": "You2 ka3 tan3 Ban4 dao3"}], "尼布楚条约": [{"en": "Treaty of Nerchinsk (1689) between Qing China and Russia", "pinyin": "Ni2 bu4 chu3 Tiao2 yue1"}], "尼雅河": [{"en": "Niya River in south Xinjiang", "pinyin": "Ni2 ya3 He2"}], "尿炕": [{"en": "bed-wetting", "pinyin": "niao4 kang4"}], "尿生殖管道": [{"en": "urinogenital tract", "pinyin": "niao4 sheng1 zhi2 guan3 dao4"}], "局促一隅": [{"en": "to be cramped in a corner (idiom)", "pinyin": "ju2 cu4 yi1 yu2"}], "局地": [{"en": "local, locally", "pinyin": "ju2 di4"}], "居心": [{"en": "to harbor (evil) intentions, to be bent on, a tranquil heart or mind", "pinyin": "ju1 xin1"}], "展期": [{"en": "to extend the period, to reschedule (a debt)", "pinyin": "zhan3 qi1"}], "层出不穷": [{"en": "more and more emerge, innumerable succession, breeding like flies (idiom)", "pinyin": "ceng2 chu1 bu4 qiong2"}], "层层": [{"en": "layer upon layer", "pinyin": "ceng2 ceng2"}], "属世": [{"en": "of this world", "pinyin": "shu3 shi4"}], "山核桃": [{"en": "hickory", "pinyin": "shan1 he2 tao5"}], "山涧": [{"en": "mountain stream", "pinyin": "shan1 jian4"}], "崴子": [{"en": "bend (in a river, road etc) (used in place names)", "pinyin": "wai3 zi5"}], "巤": [{"en": "old variant of 鬣[lie4]", "pinyin": "lie4"}], "工尺谱": [{"en": "traditional Chinese musical notation using Chinese characters to represent musical notes", "pinyin": "gong1 che3 pu3"}], "工期": [{"en": "time allocated for a project, completion date", "pinyin": "gong1 qi1"}], "工艺品": [{"en": "handicraft article, handiwork, CL:個|个[ge4]", "pinyin": "gong1 yi4 pin3"}], "巴三览四": [{"en": "to talk about this and that (idiom); to ramble incoherently", "pinyin": "ba1 san1 lan3 si4"}], "巴吞鲁日": [{"en": "Baton Rouge, capital of Louisiana", "pinyin": "Ba1 tun1 Lu3 ri4"}], "巴掌": [{"en": "palm of the hand, classifier: slap", "pinyin": "ba1 zhang5"}], "市场调查": [{"en": "market research", "pinyin": "shi4 chang3 diao4 cha2"}], "帑藏": [{"en": "state treasury, also written 帑臧[tang3 zang1]", "pinyin": "tang3 zang4"}], "师资": [{"en": "qualified teacher", "pinyin": "shi1 zi1"}], "幈": [{"en": "variant of 屏[ping2]", "pinyin": "ping2"}], "平安里": [{"en": "Ping'an Li (street name in Beijing)", "pinyin": "Ping2 an1 li3"}], "平房区": [{"en": "Pingfang district of Harbin 哈爾濱|哈尔滨[Ha1 er3 bin1] in Heilongjiang", "pinyin": "Ping2 fang2 qu1"}], "平方反比律": [{"en": "inverse square law (physics)", "pinyin": "ping2 fang1 fan3 bi3 lu:4"}], "年终": [{"en": "end of the year", "pinyin": "nian2 zhong1"}], "干将": [{"en": "capable person", "pinyin": "gan4 jiang4"}], "几希": [{"en": "not much, very little (e.g. difference)", "pinyin": "ji1 xi1"}], "度外": [{"en": "outside the sphere of one's consideration", "pinyin": "du4 wai4"}], "庬": [{"en": "huge", "pinyin": "pang2"}], "康定县": [{"en": "Dartsendo, Dardo or Kangding county (Tibetan: dar mdo rdzong) in Garze Tibetan autonomous prefecture 甘孜藏族自治州[Gan1 zi1 Zang4 zu2 zi4 zhi4 zhou1], Sichuan (formerly in Kham province of Tibet)", "pinyin": "Kang1 ding4 xian4"}], "建基": [{"en": "to lay foundations", "pinyin": "jian4 ji1"}], "弐": [{"en": "Japanese variant of 貳|贰[er4]", "pinyin": "er4"}], "引号": [{"en": "quotation mark (punct.)", "pinyin": "yin3 hao4"}], "弗洛里斯岛": [{"en": "Flores, Indonesia, also written 弗洛勒斯島|弗洛勒斯岛[Fu2 luo4 lei1 si1 dao3]", "pinyin": "Fu2 luo4 li3 si1 dao3"}], "强迫性": [{"en": "compulsive, obsessive", "pinyin": "qiang3 po4 xing4"}], "弹痕累累": [{"en": "bullet-riddled", "pinyin": "dan4 hen2 lei3 lei3"}], "弹簧门": [{"en": "swing door", "pinyin": "tan2 huang2 men2"}], "彩画": [{"en": "color painting", "pinyin": "cai3 hua4"}], "彴": [{"en": "bridge", "pinyin": "zhuo2"}], "往复锯": [{"en": "reciprocating saw", "pinyin": "wang3 fu4 ju4"}], "往脸上抹黑": [{"en": "to bring shame to, to smear, to disgrace", "pinyin": "wang3 lian3 shang4 mo3 hei1"}], "待字": [{"en": "(literary) (of a young lady) to be awaiting betrothal", "pinyin": "dai4 zi4"}], "后勤学": [{"en": "military logistics", "pinyin": "hou4 qin2 xue2"}], "后继有人": [{"en": "to have qualified successors to carry on one's undertaking", "pinyin": "hou4 ji4 you3 ren2"}], "后轮": [{"en": "rear wheel", "pinyin": "hou4 lun2"}], "微溶": [{"en": "slightly soluble", "pinyin": "wei1 rong2"}], "征信社": [{"en": "(Tw) private investigator, credit bureau", "pinyin": "zheng1 xin4 she4"}], "德安": [{"en": "De'an county in Jiujiang 九江, Jiangxi", "pinyin": "De2 an1"}], "德法年鉴": [{"en": "Deutsch-Französische Jahrbücher (published once in 1844 by Karl Marx and bourgeois radical Arnold Ruge)", "pinyin": "De2 Fa3 Nian2 jian4"}], "彻头彻尾": [{"en": "lit. from head to tail (idiom); thoroughgoing, through and through, out and out, from top to bottom", "pinyin": "che4 tou2 che4 wei3"}], "忙音": [{"en": "busy signal (telephony)", "pinyin": "mang2 yin1"}], "性向": [{"en": "aptitude, disposition, inclination", "pinyin": "xing4 xiang4"}], "怪罪": [{"en": "to blame", "pinyin": "guai4 zui4"}], "怵惧": [{"en": "fear, dread, panic", "pinyin": "chu4 ju4"}], "恒春半岛": [{"en": "Hengchun Peninsula in Pingtung County 屏東縣|屏东县[Ping2 dong1 Xian4], the southernmost point of Taiwan", "pinyin": "Heng2 chun1 Ban4 dao3"}], "恍然醒悟": [{"en": "a sudden realization, to realize sth in a flash", "pinyin": "huang3 ran2 xing3 wu4"}], "悦色": [{"en": "happy, contented", "pinyin": "yue4 se4"}], "悍妇": [{"en": "violent woman, shrew", "pinyin": "han4 fu4"}], "悠": [{"en": "long or drawn out, remote in time or space, leisurely, to swing, pensive, worried", "pinyin": "you1"}], "悠然神往": [{"en": "thoughts wandering far away", "pinyin": "you1 ran2 shen2 wang3"}], "悲怆": [{"en": "sorrow, tragic", "pinyin": "bei1 chuang4"}], "闷葫芦": [{"en": "lit. closed gourd, fig. enigma, complete mystery, taciturn person", "pinyin": "men4 hu2 lu5"}], "惠斯特": [{"en": "whist (loanword)", "pinyin": "hui4 si1 te4"}], "恶疾": [{"en": "unpleasant ailment, foul disease", "pinyin": "e4 ji2"}], "恶言伤人": [{"en": "to insult, to direct bad language at sb, to slag off", "pinyin": "e4 yan2 shang1 ren2"}], "恶魔城": [{"en": "Castlevania (video game series)", "pinyin": "E4 mo2 Cheng2"}], "惹毛": [{"en": "(coll.) to irritate, to annoy, to piss sb off", "pinyin": "re3 mao2"}], "爱德": [{"en": "Aide (brand)", "pinyin": "Ai4 de2"}], "愣劲儿": [{"en": "dash, pep, vigor", "pinyin": "leng4 jin4 r5"}], "愣神儿": [{"en": "to stare blankly, to be in a daze", "pinyin": "leng4 shen2 r5"}], "慢性疾病": [{"en": "chronic illness, disease that takes effect slowly", "pinyin": "man4 xing4 ji2 bing4"}], "愤愤": [{"en": "extremely angry", "pinyin": "fen4 fen4"}], "怼": [{"en": "(Internet slang) to attack verbally, to publicly criticize, to call out", "pinyin": "dui3"}, {"en": "dislike, hate", "pinyin": "dui4"}], "成华区": [{"en": "Chenghua district of Chengdu city 成都市[Cheng2 du1 shi4], Sichuan", "pinyin": "Cheng2 hua2 qu1"}], "所幸": [{"en": "fortunately (formal writing)", "pinyin": "suo3 xing4"}], "扁嘴海雀": [{"en": "(bird species of China) ancient murrelet (Synthliboramphus antiquus)", "pinyin": "bian3 zui3 hai3 que4"}], "扁坯": [{"en": "slab", "pinyin": "bian3 pi1"}], "扎鲁特": [{"en": "Jarud banner or Jarud khoshuu in Tongliao 通遼|通辽[Tong1 liao2], Inner Mongolia", "pinyin": "Za1 lu3 te4"}], "打钱": [{"en": "to collect money from sb, to give money to sb", "pinyin": "da3 qian2"}], "批量": [{"en": "batch, lot", "pinyin": "pi1 liang4"}], "承籍": [{"en": "to inherit a rank (from a predecessor)", "pinyin": "cheng2 ji2"}], "抄近儿": [{"en": "erhua variant of 抄近[chao1 jin4]", "pinyin": "chao1 jin4 r5"}], "抓紧学习": [{"en": "to concentrate on studying hard", "pinyin": "zhua1 jin3 xue2 xi2"}], "抔": [{"en": "take up in both hands", "pinyin": "pou2"}], "投保人": [{"en": "policy holder, insured person", "pinyin": "tou2 bao3 ren2"}], "投机者": [{"en": "speculator", "pinyin": "tou2 ji1 zhe3"}], "抗旱": [{"en": "drought-resistant, to weather a drought", "pinyin": "kang4 han4"}], "抗母": [{"en": "(loanword) com (as in \"dot-com\")", "pinyin": "kang4 mu3"}], "抱愧": [{"en": "feel ashamed", "pinyin": "bao4 kui4"}], "拉力": [{"en": "pulling force, (fig.) allure, (materials testing) tensile strength, (loanword) rally", "pinyin": "la1 li4"}], "拉皮条": [{"en": "to procure, to act as pimp", "pinyin": "la1 pi2 tiao2"}], "拌和": [{"en": "to mix and stir, to blend", "pinyin": "ban4 huo4"}], "拘守": [{"en": "to hold tight, to cling to, to adhere, stubborn, to detain sb as prisoner", "pinyin": "ju1 shou3"}], "拚财": [{"en": "to make rash speculations", "pinyin": "pan4 cai2"}], "招聘者": [{"en": "prospective employer, person advertising a job, recruiter", "pinyin": "zhao1 pin4 zhe3"}], "拜金女": [{"en": "materialistic woman, (slang) gold-digger", "pinyin": "bai4 jin1 nu:3"}], "捉获": [{"en": "to capture", "pinyin": "zhuo1 huo4"}], "捋虎须": [{"en": "lit. to stroke the tiger's whiskers, to do sth very daring", "pinyin": "luo1 hu3 xu1"}], "捜": [{"en": "Japanese variant of 搜[sou1]", "pinyin": "sou1"}], "捷克共和国": [{"en": "Czech Republic", "pinyin": "Jie2 ke4 Gong4 he2 guo2"}], "排洪": [{"en": "to drain flood-water", "pinyin": "pai2 hong2"}], "排炮": [{"en": "to fire a salvo, broadside, cannonade", "pinyin": "pai2 pao4"}], "措置": [{"en": "to handle, to arrange", "pinyin": "cuo4 zhi4"}], "拣择": [{"en": "(literary) to select, to choose", "pinyin": "jian3 ze2"}], "揄扬": [{"en": "to praise, to extol, to publicize, to advocate", "pinyin": "yu2 yang2"}], "扬科维奇": [{"en": "Jankovic, Yankovic, Yankovich, Jelena Jankovic (1985-), Serbian tennis player", "pinyin": "Yang2 ke1 wei2 qi2"}], "搬用": [{"en": "to apply mechanically, to copy and use", "pinyin": "ban1 yong4"}], "摩登": [{"en": "modern (loanword), fashionable", "pinyin": "mo2 deng1"}], "拨转": [{"en": "to turn, to turn around, to transfer (funds etc)", "pinyin": "bo1 zhuan3"}], "抚松": [{"en": "Fusong county in Baishan 白山, Jilin", "pinyin": "Fu3 song1"}], "抚养权": [{"en": "custody (of a child etc)", "pinyin": "fu3 yang3 quan2"}], "撬杠": [{"en": "crowbar", "pinyin": "qiao4 gang4"}], "扑热息痛": [{"en": "paracetamol (loanword)", "pinyin": "pu1 re4 xi1 tong4"}], "擅离职守": [{"en": "to abscond, to be absent without leave", "pinyin": "shan4 li2 zhi2 shou3"}], "擘开": [{"en": "to break open", "pinyin": "bo4 kai1"}], "放射性计时": [{"en": "radiometric dating", "pinyin": "fang4 she4 xing4 ji4 shi2"}], "放风": [{"en": "to allow in fresh air, to allow a prisoner out for exercise, to give out information", "pinyin": "fang4 feng1"}], "效忠誓词": [{"en": "pledge of allegiance", "pinyin": "xiao4 zhong1 shi4 ci2"}], "败德": [{"en": "evil conduct", "pinyin": "bai4 de2"}], "散乱": [{"en": "in disorder, messy", "pinyin": "san4 luan4"}], "散粉": [{"en": "loose powder (makeup)", "pinyin": "san3 fen3"}], "文教": [{"en": "culture and education", "pinyin": "wen2 jiao4"}], "文静": [{"en": "(of a person's manner or character) gentle and quiet", "pinyin": "wen2 jing4"}], "斑姬啄木鸟": [{"en": "(bird species of China) speckled piculet (Picumnus innominatus)", "pinyin": "ban1 ji1 zhuo2 mu4 niao3"}], "斗拱": [{"en": "interlocking wooden brackets between the top of a column and crossbeams used in traditional Chinese architecture", "pinyin": "dou3 gong3"}], "斜眼": [{"en": "to look askance, cross or wall-eyed", "pinyin": "xie2 yan3"}], "斜轴": [{"en": "oblique axes (math.)", "pinyin": "xie2 zhou2"}], "斯柯达": [{"en": "Škoda, Czech Republic car manufacturer, a subsidiary of Volkswagen Group", "pinyin": "Si1 ke1 da2"}], "新源": [{"en": "Xinyuan County or Künes nahiyisi in Ili Kazakh Autonomous Prefecture 伊犁哈薩克自治州|伊犁哈萨克自治州[Yi1 li2 Ha1 sa4 ke4 Zi4 zhi4 zhou1], Xinjiang", "pinyin": "Xin1 yuan2"}], "新农合": [{"en": "New Rural Cooperative Medical Scheme, abbr. for 新型農村合作醫療|新型农村合作医疗", "pinyin": "Xin1 Nong2 He2"}], "新乡县": [{"en": "Xinxiang county in Xinxiang 新鄉|新乡[Xin1 xiang1], Henan", "pinyin": "Xin1 xiang1 xian4"}], "方程组": [{"en": "(math.) simultaneous equations, system of equations", "pinyin": "fang1 cheng2 zu3"}], "旋前肌": [{"en": "pronator teres muscle (below the elbow)", "pinyin": "xuan2 qian2 ji1"}], "旋转行李传送带": [{"en": "luggage conveyor belt, carousel", "pinyin": "xuan2 zhuan3 xing2 li5 chuan2 song4 dai4"}], "旗山": [{"en": "Chishan town in Kaohsiung county 高雄縣|高雄县[Gao1 xiong2 xian4], southwest Taiwan", "pinyin": "Qi2 shan1"}], "日光浴浴床": [{"en": "sunbed", "pinyin": "ri4 guang1 yu4 yu4 chuang2"}], "日据时代": [{"en": "the era of Japanese occupation", "pinyin": "Ri4 ju4 shi2 dai4"}], "星罗棋布": [{"en": "scattered about like stars in the sky or chess pieces on a board (idiom); spread all over the place", "pinyin": "xing1 luo2 qi2 bu4"}], "昭平": [{"en": "Zhaoping county in Hezhou 賀州|贺州[He4 zhou1], Guangxi", "pinyin": "Zhao1 ping2"}], "昴宿星团": [{"en": "Pleiades M45", "pinyin": "Mao3 xiu4 xing1 tuan2"}], "时辰未到": [{"en": "the time has not yet come", "pinyin": "shi2 chen5 wei4 dao4"}], "晚期癌症": [{"en": "terminal cancer", "pinyin": "wan3 qi1 ai2 zheng4"}], "普渡大学": [{"en": "Purdue University", "pinyin": "Pu3 du4 Da4 xue2"}], "晕高儿": [{"en": "to feel giddy on heights, vertigo", "pinyin": "yun4 gao1 r5"}], "暖壶": [{"en": "vacuum flask, thermos flask", "pinyin": "nuan3 hu2"}], "暨南大学": [{"en": "Jinan University in Guangdong Province, with 4 campuses in Guangzhou, Shenzhen and Zhuhai", "pinyin": "Ji4 nan2 Da4 xue2"}], "曹锟": [{"en": "Cao Kun (1862-1938), one of the Northern Warlords", "pinyin": "Cao2 Kun1"}], "曾金燕": [{"en": "Zeng Jinyan (1983-), Chinese blogger and human rights activist, wife of dissident activist Hu Jia 胡佳[Hu2 Jia1]", "pinyin": "Zeng1 Jin1 yan4"}], "会诊": [{"en": "consultation (medical), to meet for diagnosis, (by extension) consultation of different specialists", "pinyin": "hui4 zhen3"}], "有两下子": [{"en": "to have real skill, to know one's stuff", "pinyin": "you3 liang3 xia4 zi5"}], "有滋有味": [{"en": "flavorsome, (fig.) delightful, full of interest", "pinyin": "you3 zi1 you3 wei4"}], "服输": [{"en": "to concede, to admit defeat, to admit sth is wrong after insisting it is right", "pinyin": "fu2 shu1"}], "杜撰": [{"en": "to fabricate, to make sth up, invented", "pinyin": "du4 zhuan4"}], "杜门": [{"en": "to close the door (lit. and fig.)", "pinyin": "du4 men2"}], "束手就毙": [{"en": "hands tied and expecting the worst", "pinyin": "shu4 shou3 jiu4 bi4"}], "东南亚联盟": [{"en": "ASEAN (Association of Southeast Asian Nations), same as 東南亞國家聯盟|东南亚国家联盟[Dong1 nan2 ya4 Guo2 jia1 Lian2 meng2]", "pinyin": "Dong1 nan2 ya4 Lian2 meng2"}], "林岭雀": [{"en": "(bird species of China) plain mountain finch (Leucosticte nemoricola)", "pinyin": "lin2 ling3 que4"}], "枝丫": [{"en": "variant of 枝椏|枝桠[zhi1 ya1]", "pinyin": "zhi1 ya1"}], "架子车": [{"en": "two-wheeled handcart", "pinyin": "jia4 zi5 che1"}], "栗鳽": [{"en": "(bird species of China) Japanese night heron (Gorsachius goisagi)", "pinyin": "li4 yan2"}], "校样": [{"en": "proofs (printing)", "pinyin": "jiao4 yang4"}], "格林纳达": [{"en": "Grenada", "pinyin": "Ge2 lin2 na4 da2"}], "梳芙厘": [{"en": "soufflé (loanword)", "pinyin": "shu1 fu2 li2"}], "棉毛": [{"en": "knitted cotton", "pinyin": "mian2 mao2"}], "棕绳": [{"en": "rope of palm fiber, coir (coconut fiber)", "pinyin": "zong1 sheng2"}], "枨": [{"en": "door post", "pinyin": "cheng2"}], "森林脑炎": [{"en": "forest encephalitis", "pinyin": "sen1 lin2 nao3 yan2"}], "植物人": [{"en": "person in a vegetative state, human vegetable", "pinyin": "zhi2 wu4 ren2"}], "椸": [{"en": "clothes-horse", "pinyin": "yi2"}], "杨贵妃": [{"en": "Yang Guifei (719-756), famous Tang beauty, consort of Emperor Xuanzhong 唐玄宗[Tang2 Xuan2 zong1]", "pinyin": "Yang2 Gui4 fei1"}], "楚辞": [{"en": "Chu Ci, the Songs of Chu (ancient book of poems, collected during Han but esp. from country of Chu c. 500 BC)", "pinyin": "Chu3 ci2"}], "极端主义": [{"en": "extremism", "pinyin": "ji2 duan1 zhu3 yi4"}], "树丛": [{"en": "thicket, undergrowth", "pinyin": "shu4 cong2"}], "树苗": [{"en": "sapling", "pinyin": "shu4 miao2"}], "横三竖四": [{"en": "in disorder, in a tremendous mess", "pinyin": "heng2 san1 shu4 si4"}], "横滨市": [{"en": "Yokohama, major port city in Kanagawa prefecture 神奈川縣|神奈川县[Shen2 nai4 chuan1 xian4], Japan", "pinyin": "Heng2 bin1 shi4"}], "检毒盒": [{"en": "detection kit", "pinyin": "jian3 du2 he2"}], "栌": [{"en": "capital (of column), smoke tree", "pinyin": "lu2"}], "权位": [{"en": "power and position (politics)", "pinyin": "quan2 wei4"}], "欬": [{"en": "to cough", "pinyin": "kai4"}], "歌罗西书": [{"en": "Epistle of St Paul to the Colossians", "pinyin": "Ge1 luo2 xi1 shu1"}], "欧当归": [{"en": "(botany) lovage, Levisticum officinale", "pinyin": "Ou1 dang1 gui1"}], "欧罗巴洲": [{"en": "Europe, abbr. to 歐洲|欧洲[Ou1 zhou1]", "pinyin": "Ou1 luo2 ba1 Zhou1"}], "欢欣雀跃": [{"en": "elated, overjoyed", "pinyin": "huan1 xin1 que4 yue4"}], "正对": [{"en": "directly facing", "pinyin": "zheng4 dui4"}], "正教": [{"en": "lit. true religion, orthodox religion, orthodox Christianity, Islam (in the writing of Chinese or Hui theologians)", "pinyin": "zheng4 jiao4"}], "步调": [{"en": "gait, marching order, step, pace", "pinyin": "bu4 diao4"}], "步辇": [{"en": "(literary) palanquin, sedan chair, to ride in a palanquin", "pinyin": "bu4 nian3"}], "武则天": [{"en": "Wu Zetian (624-705), Tang empress, reigned 690-705", "pinyin": "Wu3 Ze2 tian1"}], "武汉大学": [{"en": "Wuhan University", "pinyin": "Wu3 han4 Da4 xue2"}], "历史唯物主义": [{"en": "historical materialism (Marx's theory of history)", "pinyin": "li4 shi3 wei2 wu4 zhu3 yi4"}], "归根到底": [{"en": "after all, in the final analysis, ultimately", "pinyin": "gui1 gen1 dao4 di3"}], "归顺": [{"en": "to surrender and pay allegiance to", "pinyin": "gui1 shun4"}], "残杀者": [{"en": "killer, butcher, slaughterer", "pinyin": "can2 sha1 zhe3"}], "段氏": [{"en": "a branch of the Xianbei 鮮卑|鲜卑 nomadic people", "pinyin": "Duan4 shi4"}], "杀螺剂": [{"en": "snail poison", "pinyin": "sha1 luo2 ji4"}], "杀猪宰羊": [{"en": "to kill the pigs and slaughter the sheep (idiom)", "pinyin": "sha1 zhu1 zai3 yang2"}], "毛重": [{"en": "gross weight", "pinyin": "mao2 zhong4"}], "毫不迟疑": [{"en": "without the slightest hesitation", "pinyin": "hao2 bu4 chi2 yi2"}], "毴": [{"en": "old variant of 屄[bi1]", "pinyin": "bi1"}], "民生凋敝": [{"en": "the people's livelihood is reduced to destitution (idiom); a time of famine and impoverishment", "pinyin": "min2 sheng1 diao1 bi4"}], "民变峰起": [{"en": "seething discontent (idiom); widespread popular grievances", "pinyin": "min2 bian4 feng1 qi3"}], "气数": [{"en": "fate, destiny, one's lot", "pinyin": "qi4 shu5"}], "气缸": [{"en": "cylinder (engine)", "pinyin": "qi4 gang1"}], "氰酸": [{"en": "cyanic acid HCN", "pinyin": "qing2 suan1"}], "水到渠成": [{"en": "lit. where water flows, a canal is formed (idiom), fig. when conditions are right, success will follow naturally", "pinyin": "shui3 dao4 qu2 cheng2"}], "水准仪": [{"en": "level (device to determine horizontal), spirit level, surveyor's level", "pinyin": "shui3 zhun3 yi2"}], "水产养殖": [{"en": "aquaculture", "pinyin": "shui3 chan3 yang3 zhi2"}], "水质": [{"en": "water quality", "pinyin": "shui3 zhi4"}], "永新": [{"en": "Yongxin county in Ji'an 吉安, Jiangxi", "pinyin": "Yong3 xin1"}], "求同存异": [{"en": "to seek common ground, putting differences aside (idiom)", "pinyin": "qiu2 tong2 cun2 yi4"}], "汗斑": [{"en": "common name for 花斑癬|花斑癣[hua1 ban1 xuan3], tinea versicolor", "pinyin": "han4 ban1"}], "江浙": [{"en": "abbr. for Jiangsu 江蘇|江苏[Jiang1 su1] and Zhejiang 浙江[Zhe4 jiang1]", "pinyin": "Jiang1 Zhe4"}], "江边": [{"en": "river bank", "pinyin": "jiang1 bian1"}], "汽车技工": [{"en": "auto mechanic", "pinyin": "qi4 che1 ji4 gong1"}], "没天理": [{"en": "(old) unprincipled, incorrect, (modern) unnatural, against reason, incredible", "pinyin": "mei2 tian1 li3"}], "没经验": [{"en": "inexperienced", "pinyin": "mei2 jing1 yan4"}], "河北日报": [{"en": "Hebei Daily, www.hebeidaily.com.cn", "pinyin": "He2 bei3 Ri4 bao4"}], "沼": [{"en": "pond, pool", "pinyin": "zhao3"}], "况味": [{"en": "circumstances, atmosphere, mood", "pinyin": "kuang4 wei4"}], "泥菩萨过江，自身难保": [{"en": "like a clay Bodhisattva fording a river, can't guarantee his own safety, unable to save oneself, let alone others", "pinyin": "ni2 pu2 sa4 guo4 jiang1 , zi4 shen1 nan2 bao3"}], "洛扎县": [{"en": "Lhozhag county, Tibetan: Lho brag rdzong, in Lhokha prefecture 山南地區|山南地区[Shan1 nan2 di4 qu1], Tibet", "pinyin": "Luo4 zha1 xian4"}], "洛桑": [{"en": "Lausanne (city in Switzerland)", "pinyin": "Luo4 sang1"}], "活性剂": [{"en": "reagent (chemistry)", "pinyin": "huo2 xing4 ji4"}], "活脱": [{"en": "remarkably alike", "pinyin": "huo2 tuo1"}], "流布": [{"en": "to spread, to circulate, to disseminate", "pinyin": "liu2 bu4"}, {"en": "to spread, to circulate, to disseminate", "pinyin": "liu2 bu4"}], "浙江": [{"en": "Zhejiang province (Chekiang) in east China, abbr. 浙, capital Hangzhou 杭州", "pinyin": "Zhe4 jiang1"}], "浣纱": [{"en": "to wash silk", "pinyin": "huan4 sha1"}], "浪潮": [{"en": "wave, tides", "pinyin": "lang4 chao2"}], "浪费者": [{"en": "waster, wastrel, squanderer", "pinyin": "lang4 fei4 zhe3"}], "浴盐": [{"en": "bath salts", "pinyin": "yu4 yan2"}], "海洋学": [{"en": "oceanography", "pinyin": "hai3 yang2 xue2"}], "海港区": [{"en": "harbor district, Haigang district of Qinhuangdao city 秦皇島市|秦皇岛市[Qin2 huang2 dao3 shi4], Hebei", "pinyin": "Hai3 gang3 qu1"}], "涕泪交流": [{"en": "tears and mucus flowing profusely (idiom); weeping tragically", "pinyin": "ti4 lei4 jiao1 liu2"}], "液面": [{"en": "surface (of a body of liquid)", "pinyin": "ye4 mian4"}], "淆杂": [{"en": "to mix up, to muddle", "pinyin": "xiao2 za2"}], "深广": [{"en": "deep and wide, vast, profound (influence etc)", "pinyin": "shen1 guang3"}], "添乱": [{"en": "(coll.) to cause trouble for sb, to inconvenience", "pinyin": "tian1 luan4"}], "添堵": [{"en": "to make people feel even more stressed or annoyed (coll.), to make traffic congestion even worse", "pinyin": "tian1 du3"}], "清嗓": [{"en": "to clear one's throat, to hawk", "pinyin": "qing1 sang3"}], "清新县": [{"en": "Qingxin county in Qingyuan 清遠|清远[Qing1 yuan3], Guangdong", "pinyin": "Qing1 xin1 xian4"}], "清涧": [{"en": "Qingjian County in Yulin 榆林[Yu2 lin2], Shaanxi", "pinyin": "Qing1 jian4"}], "港股": [{"en": "Hong Kong shares", "pinyin": "Gang3 gu3"}], "湌": [{"en": "variant of 餐[can1]", "pinyin": "can1"}], "准备好了": [{"en": "to be ready", "pinyin": "zhun3 bei4 hao3 le5"}], "准决赛": [{"en": "semifinal", "pinyin": "zhun3 jue2 sai4"}], "温切斯特": [{"en": "Winchester (town in south England, capital of former kingdom of Wessex)", "pinyin": "Wen1 qie1 si1 te4"}], "温室气体": [{"en": "greenhouse gas", "pinyin": "wen1 shi4 qi4 ti3"}], "温驯": [{"en": "docile, meek, harmless, moderate and obedient, tame", "pinyin": "wen1 xun4"}], "渗坑": [{"en": "sewage pit", "pinyin": "shen4 keng1"}], "滴溜溜": [{"en": "whirling, spinning around and around, round and plump (e.g. of fruit)", "pinyin": "di1 liu1 liu1"}], "渔钩儿": [{"en": "variant of 魚鉤兒|鱼钩儿[yu2 gou1 r5]", "pinyin": "yu2 gou1 r5"}], "漏电": [{"en": "to leak electricity, (fig.) (coll.) to unintentionally arouse romantic interest (by being solicitous etc), cf. 放電|放电[fang4 dian4]", "pinyin": "lou4 dian4"}], "潜舰": [{"en": "a submarine", "pinyin": "qian2 jian4"}], "潸": [{"en": "tearfully", "pinyin": "shan1"}], "滥套子": [{"en": "platitude, pointless talk", "pinyin": "lan4 tao4 zi5"}], "濒于": [{"en": "near to, approaching (collapse)", "pinyin": "bin1 yu2"}], "火龙": [{"en": "fiery dragon", "pinyin": "huo3 long2"}], "炤": [{"en": "surname Zhao", "pinyin": "Zhao4"}], "乌丘": [{"en": "Wuchiu township in Kinmen County 金門縣|金门县[Jin1 men2 xian4] (Kinmen or Quemoy islands), Taiwan", "pinyin": "Wu1 qiu1"}], "烘笼": [{"en": "bamboo drying frame", "pinyin": "hong1 long2"}], "焈": [{"en": "old variant of 熙[xi1]", "pinyin": "xi1"}], "焦化": [{"en": "to distill", "pinyin": "jiao1 hua4"}], "煞尾": [{"en": "to finish off, to wind up", "pinyin": "sha1 wei3"}], "烦杂": [{"en": "many and disorderly, muddled", "pinyin": "fan2 za2"}], "熔炼": [{"en": "to smelt", "pinyin": "rong2 lian4"}], "热昏": [{"en": "to be overcome by the heat", "pinyin": "re4 hun1"}], "热河": [{"en": "Rehe, Qing dynasty province abolished in 1955 and divided among Hebei, Liaoning and Inner Mongolia, refers to the Qing imperial resort at Chengde, see also 避暑山莊|避暑山庄[bi4 shu3 shan1 zhuang1] (history)", "pinyin": "Re4 he2"}], "烧烤酱": [{"en": "barbecue sauce", "pinyin": "shao1 kao3 jiang4"}], "燕尾服": [{"en": "swallow-tailed coat, tails", "pinyin": "yan4 wei3 fu2"}], "爪哇岛": [{"en": "Java (island of Indonesia)", "pinyin": "Zhao3 wa1 Dao3"}], "爽朗": [{"en": "clear and bright (of weather), straightforward, candid, open", "pinyin": "shuang3 lang3"}], "牢实": [{"en": "solid, strong, firm, secure", "pinyin": "lao2 shi5"}], "物力": [{"en": "physical resources (as opposed to labor resources)", "pinyin": "wu4 li4"}], "牸马": [{"en": "mare", "pinyin": "zi4 ma3"}], "狂傲": [{"en": "domineering, haughty", "pinyin": "kuang2 ao4"}], "狗吃屎": [{"en": "to fall flat on one's face (vulgar)", "pinyin": "gou3 chi1 shi3"}], "猛丁": [{"en": "suddenly", "pinyin": "meng3 ding1"}], "猛劲儿": [{"en": "to dash, to put on a spurt, to redouble efforts", "pinyin": "meng3 jin4 r5"}], "猛扑": [{"en": "to charge, to pounce on, to swoop down on", "pinyin": "meng3 pu1"}], "猜谜": [{"en": "to answer a riddle, to guess (i.e. form an opinion without much evidence)", "pinyin": "cai1 mi2"}], "奖状": [{"en": "prize certificate, certificate of merit", "pinyin": "jiang3 zhuang4"}], "獠": [{"en": "fierce, hunt, name of a tribe", "pinyin": "liao2"}], "玉皇大帝": [{"en": "Jade Emperor", "pinyin": "Yu4 huang2 Da4 di4"}], "王顾左右而言他": [{"en": "the king looked left and right and then talked of other things, to digress from the topic of discussion (idiom)", "pinyin": "wang2 gu4 zuo3 you4 er2 yan2 ta1"}], "玩失踪": [{"en": "to hide oneself (as a joke)", "pinyin": "wan2 shi1 zong1"}], "玫瑰战争": [{"en": "The Wars of the Roses (1455-1485)", "pinyin": "Mei2 gui1 Zhan4 zheng1"}], "玲玲": [{"en": "(onom.) tinkling (e.g. of jewels)", "pinyin": "ling2 ling2"}], "理顺": [{"en": "to straighten out, to sort out, to organize", "pinyin": "li3 shun4"}], "琨": [{"en": "(jade)", "pinyin": "kun1"}], "瑞士军刀": [{"en": "Swiss Army knife", "pinyin": "Rui4 shi4 jun1 dao1"}], "环极涡旋": [{"en": "circumpolar vortex", "pinyin": "huan2 ji2 wo1 xuan2"}], "环香": [{"en": "incense coil", "pinyin": "huan2 xiang1"}], "瓠瓜": [{"en": "bottle gourd", "pinyin": "hu4 gua1"}], "瓰": [{"en": "deciwatt (old), single-character equivalent of 分瓦[fen1 wa3]", "pinyin": "fen1 wa3"}], "生态学家": [{"en": "ecologist", "pinyin": "sheng1 tai4 xue2 jia1"}], "生理假": [{"en": "menstrual leave (Tw)", "pinyin": "sheng1 li3 jia4"}], "田鼠": [{"en": "vole", "pinyin": "tian2 shu3"}], "由衷": [{"en": "heartfelt, sincere, unfeigned", "pinyin": "you2 zhong1"}], "畔": [{"en": "edge, side, boundary, bank (of a river etc), shore", "pinyin": "pan4"}], "略字": [{"en": "abbreviated character, simplified character", "pinyin": "lu:e4 zi4"}], "异源多倍体": [{"en": "allopolyploid (polyploid with chromosomes of different species)", "pinyin": "yi4 yuan2 duo1 bei4 ti3"}], "畸变": [{"en": "distortion, aberration", "pinyin": "ji1 bian4"}], "疏勒县": [{"en": "Shule county in Kashgar prefecture 喀什地區|喀什地区[Ka1 shi2 di4 qu1], west Xinjiang", "pinyin": "Shu1 le4 xian4"}], "疸": [{"en": "see 疙疸[ge1 da5]", "pinyin": "da5"}, {"en": "jaundice", "pinyin": "dan3"}], "疼惜": [{"en": "to cherish, to dote on", "pinyin": "teng2 xi1"}], "病毒科": [{"en": "virus family", "pinyin": "bing4 du2 ke1"}], "痛砭": [{"en": "to strongly criticize", "pinyin": "tong4 bian1"}], "瘜": [{"en": "a polypus", "pinyin": "xi1"}], "发脱口齿": [{"en": "diction, enunciation", "pinyin": "fa1 tuo1 kou3 chi3"}], "白住": [{"en": "to live (somewhere) for free", "pinyin": "bai2 zhu4"}], "白板笔": [{"en": "whiteboard marker, dry-erase marker", "pinyin": "bai2 ban3 bi3"}], "百分比": [{"en": "percentage", "pinyin": "bai3 fen1 bi3"}], "皀": [{"en": "one grain", "pinyin": "bi1"}], "皇姑": [{"en": "Huanggu district of Shenyang city 瀋陽市|沈阳市, Liaoning", "pinyin": "Huang2 gu1"}], "皮面": [{"en": "outer skin, surface, leather cover (of a book), drum skin, leather upper (of a shoe)", "pinyin": "pi2 mian4"}], "目无光泽": [{"en": "to have eyes without luster (idiom)", "pinyin": "mu4 wu2 guang1 ze2"}], "相貌": [{"en": "appearance", "pinyin": "xiang4 mao4"}], "省长": [{"en": "governor of a province", "pinyin": "sheng3 zhang3"}], "眄眄": [{"en": "dull-looking, looking askance", "pinyin": "mian4 mian4"}], "眄睨": [{"en": "to look askance", "pinyin": "mian4 ni4"}], "督察大队": [{"en": "censorship brigade (PRC)", "pinyin": "du1 cha2 da4 dui4"}], "瞎搞": [{"en": "to fool around, to mess with, to do sth without a plan", "pinyin": "xia1 gao3"}], "瞬": [{"en": "to wink", "pinyin": "shun4"}], "短嘴金丝燕": [{"en": "(bird species of China) Himalayan swiftlet (Aerodramus brevirostris)", "pinyin": "duan3 zui3 jin1 si1 yan4"}], "石川": [{"en": "Ishikawa (Japanese surname and place name)", "pinyin": "Shi2 chuan1"}], "石鼓区": [{"en": "Dangu district of Hengyang city 衡陽市|衡阳市[Heng2 yang2 shi4], Hunan", "pinyin": "Dan4 gu3 qu1"}], "研究人员": [{"en": "research worker, research personnel", "pinyin": "yan2 jiu1 ren2 yuan2"}], "研制过程": [{"en": "manufacturing environment", "pinyin": "yan2 zhi4 guo4 cheng2"}], "破题": [{"en": "writing style in which the main subject is approached directly from the outset, opposite of 冒題|冒题[mao4 ti2]", "pinyin": "po4 ti2"}], "硅橡胶": [{"en": "silicone rubber", "pinyin": "gui1 xiang4 jiao1"}], "硬木": [{"en": "hardwood", "pinyin": "ying4 mu4"}], "硬笔": [{"en": "generic term for hard writing instruments such as quill pens, fountain pens, ball pens and pencils, as opposed to writing brushes", "pinyin": "ying4 bi3"}], "磕膝盖": [{"en": "(dialect) knee", "pinyin": "ke1 xi1 gai4"}], "碍口": [{"en": "to shy to speak out, tongue-tied, to hesitate, too embarrassing for words", "pinyin": "ai4 kou3"}], "矿井": [{"en": "a mine, a mine shaft", "pinyin": "kuang4 jing3"}], "社学": [{"en": "Ming or Qing dynasty school", "pinyin": "she4 xue2"}], "祁连山": [{"en": "Qilian Mountains in Qinghai", "pinyin": "Qi2 lian2 Shan1"}], "神经元": [{"en": "neuron", "pinyin": "shen2 jing1 yuan2"}], "神造论": [{"en": "creationism", "pinyin": "shen2 zao4 lun4"}], "福兴乡": [{"en": "Fuxing or Fuhsing Township in Changhua County 彰化縣|彰化县[Zhang1 hua4 Xian4], Taiwan", "pinyin": "Fu2 xing1 Xiang1"}], "禠": [{"en": "felicity, blessing", "pinyin": "si1"}], "秀气": [{"en": "delicate, graceful", "pinyin": "xiu4 qi5"}], "私仇": [{"en": "personal grudge", "pinyin": "si1 chou2"}], "秋审": [{"en": "autumn trial (judicial hearing of capital cases during Ming and Qing)", "pinyin": "qiu1 shen3"}], "秋燥": [{"en": "autumn dryness disease (TCM)", "pinyin": "qiu1 zao4"}], "租船": [{"en": "to charter a ship, to take a vessel on rent", "pinyin": "zu1 chuan2"}], "秦始皇": [{"en": "Qin Shihuang (259-210 BC), the first emperor", "pinyin": "Qin2 Shi3 huang2"}], "秦州": [{"en": "Qinzhou district of Tianshui city 天水市[Tian1 shui3 shi4], Gansu", "pinyin": "Qin2 zhou1"}], "稀里糊涂": [{"en": "muddleheaded, careless", "pinyin": "xi1 li5 hu2 tu5"}], "稍早时": [{"en": "a little earlier", "pinyin": "shao1 zao3 shi2"}], "种族清洗": [{"en": "\"ethnic cleansing\", genocide", "pinyin": "zhong3 zu2 qing1 xi3"}], "稽查人员": [{"en": "inspector", "pinyin": "ji1 cha2 ren2 yuan2"}], "空穴来风未必无因": [{"en": "wind does not come from an empty cave without reason, there's no smoke without fire (idiom)", "pinyin": "kong4 xue2 lai2 feng1 wei4 bi4 wu2 yin1"}], "空窗期": [{"en": "window period (time between infection and the appearance of detectable antibodies), period during which sth is lacking (boyfriend or girlfriend, work, revenue, production of a commodity etc), lull, hiatus", "pinyin": "kong1 chuang1 qi1"}], "窈窈": [{"en": "obscure, dusky, far and deep, profound, see also 杳杳[yao3 yao3]", "pinyin": "yao3 yao3"}], "立身处世": [{"en": "the way of one's conduct and interaction in society (idiom)", "pinyin": "li4 shen1 chu3 shi4"}], "童山濯濯": [{"en": "treeless hill, (fig.) bald head", "pinyin": "tong2 shan1 zhuo2 zhuo2"}], "童谣": [{"en": "nursery rhyme", "pinyin": "tong2 yao2"}], "笰": [{"en": "duster", "pinyin": "fu2"}], "箔": [{"en": "plaited matting (of rushes, bamboo etc), silkworm basket, metal foil, foil paper", "pinyin": "bo2"}], "箜篌": [{"en": "konghou (Chinese harp)", "pinyin": "kong1 hou2"}], "节奏布鲁斯": [{"en": "Rhythm and Blues R&B", "pinyin": "jie2 zou4 bu4 lu3 si1"}], "简朴": [{"en": "simple and unadorned, plain", "pinyin": "jian3 pu3"}], "简表": [{"en": "table (displaying data in rows and columns)", "pinyin": "jian3 biao3"}], "吁请": [{"en": "to implore, to entreat", "pinyin": "yu4 qing3"}], "精诚": [{"en": "sincerity, absolute good faith", "pinyin": "jing1 cheng2"}], "粮荒": [{"en": "famine, critical shortage of grain", "pinyin": "liang2 huang1"}], "纪律检查委员会": [{"en": "Central Commission for Discipline Inspection of the CCP", "pinyin": "Ji4 lu:4 Jian3 cha2 Wei3 yuan2 hui4"}], "红塔区": [{"en": "Hongta district of Yuxi city 玉溪市[Yu4 xi1 shi4], Yunnan", "pinyin": "Hong2 ta3 qu1"}], "红妆": [{"en": "splendid gay female clothing", "pinyin": "hong2 zhuang1"}], "红轮": [{"en": "the sun", "pinyin": "hong2 lun2"}], "纳粹德国": [{"en": "Nazi Germany (1933-1945)", "pinyin": "Na4 cui4 De2 guo2"}], "纱支": [{"en": "(textiles) yarn count (unit indicating the fineness of a yarn), (sometimes used loosely to mean thread count)", "pinyin": "sha1 zhi1"}], "纴": [{"en": "to weave, to lay warp for weaving, silk thread for weaving, variant of 紉|纫, to sew, to stitch, thread", "pinyin": "ren4"}], "索带": [{"en": "cable tie, plastic strap", "pinyin": "suo3 dai4"}], "绥阳": [{"en": "Suiyang county in Zunyi 遵義|遵义[Zun1 yi4], Guizhou", "pinyin": "Sui2 yang2"}], "综效": [{"en": "synergy", "pinyin": "zong1 xiao4"}], "线性波": [{"en": "linear wave", "pinyin": "xian4 xing4 bo1"}], "线性系统": [{"en": "linear system", "pinyin": "xian4 xing4 xi4 tong3"}], "缘": [{"en": "cause, reason, karma, fate, predestined affinity, margin, hem, edge, along", "pinyin": "yuan2"}], "缝衣匠": [{"en": "tailor", "pinyin": "feng2 yi1 jiang4"}], "繐": [{"en": "fine and loose cloth, tassel", "pinyin": "sui4"}], "绕弯": [{"en": "to go for a walk around, fig. to speak in a roundabout way", "pinyin": "rao4 wan1"}], "罗圈儿揖": [{"en": "to bow around with hands joined (to people on all sides)", "pinyin": "luo2 quan1 r5 yi1"}], "美国全国广播公司": [{"en": "National Broadcasting Company (NBC)", "pinyin": "Mei3 guo2 Quan2 guo2 Guang3 bo1 Gong1 si1"}], "翠": [{"en": "bluish-green, green jade", "pinyin": "cui4"}], "翘足而待": [{"en": "to expect in a short time (idiom), also pr. [qiao4 zu2 er2 dai4]", "pinyin": "qiao2 zu2 er2 dai4"}], "老小": [{"en": "the old and the young, the youngest member of the family", "pinyin": "lao3 xiao3"}], "耐磨": [{"en": "wear resistant", "pinyin": "nai4 mo2"}], "耳罩": [{"en": "earmuffs", "pinyin": "er3 zhao4"}], "圣安德列斯断层": [{"en": "San Andreas Fault, California", "pinyin": "Sheng4 an1 de2 lie4 si1 Duan4 ceng2"}], "聚变武器": [{"en": "fusion-type weapon", "pinyin": "ju4 bian4 wu3 qi4"}], "聚饮": [{"en": "to meet for social drinking", "pinyin": "ju4 yin3"}], "聪颖": [{"en": "smart, intelligent", "pinyin": "cong1 ying3"}], "声气": [{"en": "voice, tone, information", "pinyin": "sheng1 qi4"}], "股份制公司": [{"en": "joint-stock company", "pinyin": "gu3 fen4 zhi4 gong1 si1"}], "股沟": [{"en": "buttock cleavage, butt crack", "pinyin": "gu3 gou1"}], "股癣": [{"en": "tinea cruris, fungal skin infection of the groin, dermatomycosis, esp. sexually transmitted, jock itch", "pinyin": "gu3 xuan3"}], "胖人": [{"en": "overweight person, fatty", "pinyin": "pang4 ren2"}], "胸有成算": [{"en": "the hero has plans already laid (idiom); to have plans ready in advance, forewarned is forearmed", "pinyin": "xiong1 you3 cheng2 suan4"}], "脱手": [{"en": "(not of regular commerce) to sell or dispose of (goods etc), to get rid of, to unload", "pinyin": "tuo1 shou3"}], "脱氧麻黄碱": [{"en": "methamphetamine", "pinyin": "tuo1 yang3 ma2 huang2 jian3"}], "脱胎成仙": [{"en": "reborn as immortal", "pinyin": "tuo1 tai1 cheng2 xian1"}], "肠易激综合征": [{"en": "irritable bowel syndrome (IBS)", "pinyin": "chang2 yi4 ji1 zong1 he2 zheng1"}], "脸相": [{"en": "complexion, looks, appearance of one's face", "pinyin": "lian3 xiang4"}], "自卸车": [{"en": "dump truck", "pinyin": "zi4 xie4 che1"}], "自强": [{"en": "to strive for self-improvement", "pinyin": "zi4 qiang2"}], "自谦": [{"en": "modest, self-deprecating", "pinyin": "zi4 qian1"}], "自适应": [{"en": "adaptive", "pinyin": "zi4 shi4 ying4"}], "臭子儿": [{"en": "dead bullet (one that does not fire), a bad move (in a game of chess)", "pinyin": "chou4 zi3 r5"}], "旧病": [{"en": "old illness, former affliction", "pinyin": "jiu4 bing4"}], "舐犊情深": [{"en": "lit. the cow licking its calf fondly (idiom), fig. to show deep affection towards one's children", "pinyin": "shi4 du2 qing2 shen1"}], "舒梦兰": [{"en": "Shu Menglan (1759-1835), Qin dynasty writer, poet and editor of Anthology of ci poems tunes 白香詞譜|白香词谱", "pinyin": "Shu1 Meng4 lan2"}], "航厦": [{"en": "air terminal", "pinyin": "hang2 sha4"}], "航标灯": [{"en": "lighted buoy, channel marking light, signal light", "pinyin": "hang2 biao1 deng1"}], "舸": [{"en": "barge", "pinyin": "ge3"}], "船梯": [{"en": "ship's ladder", "pinyin": "chuan2 ti1"}], "色欲": [{"en": "sexual desire, lust", "pinyin": "se4 yu4"}], "花样": [{"en": "pattern, way of doing sth, trick, ruse, fancy-style (as in 花樣滑冰|花样滑冰[hua1 yang4 hua2 bing1] figure skating)", "pinyin": "hua1 yang4"}], "花火": [{"en": "firework", "pinyin": "hua1 huo3"}], "花花绿绿": [{"en": "brightly colored, gaudy", "pinyin": "hua1 hua1 lu:4 lu:4"}], "花鸟": [{"en": "painting of birds and flowers", "pinyin": "hua1 niao3"}], "苟安": [{"en": "see 苟且偷安[gou3 qie3 tou1 an1]", "pinyin": "gou3 an1"}], "苦集灭道": [{"en": "the Four Noble Truths (Budd.), namely: all life is suffering 苦[ku3], the cause of suffering is desire 集[ji2], emancipation comes only by eliminating passions 滅|灭[mie4], the way 道[dao4] to emancipation is the Eight-fold Noble Way 八正道[ba1 zheng4 dao4], also called 四諦|四谛[si4 di4]", "pinyin": "ku3 ji2 mie4 dao4"}], "茀": [{"en": "luxuriant growth", "pinyin": "fu2"}], "茶坊": [{"en": "teahouse", "pinyin": "cha2 fang2"}], "草屋": [{"en": "thatched hut", "pinyin": "cao3 wu1"}], "荆州": [{"en": "Jingzhou prefecture-level city on Changjiang in Hubei", "pinyin": "Jing1 zhou1"}], "荒漠化": [{"en": "desertification", "pinyin": "huang1 mo4 hua4"}], "莆田市": [{"en": "Putian prefecture level city in Fujian", "pinyin": "Pu2 tian2 shi4"}], "莫尔斯电码": [{"en": "Morse code", "pinyin": "Mo4 er3 si1 dian4 ma3"}], "萍乡市": [{"en": "Pingxiang prefecture level city in Jiangxi", "pinyin": "Ping2 xiang1 shi4"}], "着慌": [{"en": "alarmed, panicking", "pinyin": "zhao2 huang1"}], "着笔": [{"en": "to put pen to paper", "pinyin": "zhuo2 bi3"}], "荤": [{"en": "strong-smelling vegetable (garlic etc), non-vegetarian food (meat, fish etc), vulgar, obscene", "pinyin": "hun1"}], "蒐": [{"en": "madder (Rubia cordifolia), to hunt for, to gather, to collect", "pinyin": "sou1"}], "莳萝": [{"en": "dill (herb, Anethum graveolens)", "pinyin": "shi2 luo2"}], "蒙巴顿": [{"en": "Mountbatten (name, Anglicization of German Battenberg), Lord Louis Mountbatten, 1st Earl Mountbatten of Burma (1900-1979), British commander in Southeast Asia during WWII, presided over the partition of India in 1947, murdered by the IRA.", "pinyin": "Meng2 ba1 dun4"}], "蒙文": [{"en": "Mongolian language", "pinyin": "Meng3 wen2"}], "蒙阴县": [{"en": "Mengyin county in Linyi 臨沂|临沂[Lin2 yi2], Shandong", "pinyin": "Meng2 yin1 xian4"}], "芜": [{"en": "overgrown with weeds", "pinyin": "wu2"}], "蓝喉拟啄木鸟": [{"en": "(bird species of China) blue-throated barbet (Megalaima asiatica)", "pinyin": "lan2 hou2 ni3 zhuo2 mu4 niao3"}], "蓝精灵": [{"en": "the Smurfs", "pinyin": "Lan2 jing1 ling2"}, {"en": "Smurf", "pinyin": "lan2 jing1 ling2"}], "药到病除": [{"en": "lit. the disease is cured the moment the medicine is taken (idiom), fig. (of a medical treatment) to give instant results, (of a solution or method) highly effective", "pinyin": "yao4 dao4 bing4 chu2"}], "苏共": [{"en": "Soviet Communist Party, abbr. for 蘇聯共產黨|苏联共产党[Su1 lian2 Gong4 chan3 dang3]", "pinyin": "Su1 Gong4"}], "苏报案": [{"en": "Qing's 1903 suppression of revolutionary calls in newspaper 蘇報|苏报, leading to imprisonment of Zhang Taiyan 章太炎 and Zou Rong 鄒容|邹容", "pinyin": "Su1 bao4 an4"}], "号哭": [{"en": "to bawl, to wail, to cry", "pinyin": "hao2 ku1"}], "蜜穴": [{"en": "(coll.) vagina, pussy", "pinyin": "mi4 xue2"}], "蝌": [{"en": "tadpole", "pinyin": "ke1"}], "行不改姓，坐不改名": [{"en": "see 行不更名，坐不改姓[xing2 bu4 geng1 ming2 , zuo4 bu4 gai3 xing4]", "pinyin": "xing2 bu4 gai3 xing4 , zuo4 bu4 gai3 ming2"}], "行政命令": [{"en": "executive order", "pinyin": "xing2 zheng4 ming4 ling4"}], "行辈": [{"en": "generation and age ranking, seniority", "pinyin": "hang2 bei4"}], "行销": [{"en": "to sell, marketing", "pinyin": "xing2 xiao1"}], "衰迈": [{"en": "aged, decrepit", "pinyin": "shuai1 mai4"}], "袖筒": [{"en": "sleeve", "pinyin": "xiu4 tong3"}], "褐头鹀": [{"en": "(bird species of China) red-headed bunting (Emberiza bruniceps)", "pinyin": "he4 tou2 wu2"}], "西凉": [{"en": "Western Liang of the Sixteen Kingdoms (400-421)", "pinyin": "Xi1 Liang2"}], "西门豹": [{"en": "Ximen Bao (active around 422 BC), statesman and hydraulic engineer of Wei 魏國|魏国[Wei4 guo2]", "pinyin": "Xi1 men2 Bao4"}], "要路": [{"en": "important road, main thoroughfare, fig. key position", "pinyin": "yao4 lu4"}], "要风得风，要雨得雨": [{"en": "to get whatever one wants, to have everything going one's way", "pinyin": "yao4 feng1 de2 feng1 , yao4 yu3 de2 yu3"}], "见色忘义": [{"en": "to forget loyalty when in love, hoes before bros", "pinyin": "jian4 se4 wang4 yi4"}], "见血封喉树": [{"en": "Antiaris toxicaria (botany)", "pinyin": "jian4 xue4 feng1 hou2 shu4"}], "见长": [{"en": "to excel at (typically used after the area of expertise), Example: 以研究見長|以研究见长[yi3 yan2 jiu1 jian4 chang2] to be known for one's research", "pinyin": "jian4 chang2"}], "覤": [{"en": "variant of 虩[xi4]", "pinyin": "xi4"}], "角质层": [{"en": "stratum corneum (outermost layer of the skin)", "pinyin": "jiao3 zhi4 ceng2"}], "言教不如身教": [{"en": "Explaining in words is not as good as teaching by example (idiom). Action speaks louder than words.", "pinyin": "yan2 jiao4 bu4 ru2 shen1 jiao4"}], "评章": [{"en": "to appraise", "pinyin": "ping2 zhang1"}], "词意": [{"en": "meaning of word, sense", "pinyin": "ci2 yi4"}], "诣阙": [{"en": "to go to the palace to see the emperor", "pinyin": "yi4 que1"}], "语音合成": [{"en": "speech synthesis", "pinyin": "yu3 yin1 he2 cheng2"}], "诼": [{"en": "to complain", "pinyin": "zhuo2"}], "讳疾忌医": [{"en": "hiding a sickness for fear of treatment (idiom); fig. concealing a fault to avoid criticism, to keep one's shortcomings secret, to refuse to listen to advice", "pinyin": "hui4 ji2 ji4 yi1"}], "谋虑": [{"en": "to plan and consider, to reflect on one's best strategy", "pinyin": "mou2 lu:4"}], "谱线": [{"en": "spectral line", "pinyin": "pu3 xian4"}], "议论纷错": [{"en": "see 議論紛紛|议论纷纷[yi4 lun4 fen1 fen1]", "pinyin": "yi4 lun4 fen1 cuo4"}], "讘": [{"en": "(old) to talk a lot, to talk nonsense, also pr. [zhe2]", "pinyin": "nie4"}], "豁拳": [{"en": "variant of 划拳[hua2 quan2]", "pinyin": "hua2 quan2"}], "岂敢": [{"en": "how could one dare?, I don't deserve such praise", "pinyin": "qi3 gan3"}], "豺狼当路": [{"en": "ravenous wolves hold the road (idiom); wicked people in power, a vicious tyranny rules the land", "pinyin": "chai2 lang2 dang1 lu4"}], "貂熊": [{"en": "wolverine (Gulo gulo)", "pinyin": "diao1 xiong2"}], "貌相": [{"en": "appearance (esp. superficial), looks, to judge a person by appearances", "pinyin": "mao4 xiang4"}], "贞节": [{"en": "chastity, virginity (of women), moral integrity (of men), loyalty, constancy", "pinyin": "zhen1 jie2"}], "资俸": [{"en": "salary, pay, wages", "pinyin": "zi1 feng4"}], "质": [{"en": "character, nature, quality, plain, to pawn, pledge, hostage, to question, Taiwan pr. [zhi2]", "pinyin": "zhi4"}], "赌资": [{"en": "money to gamble with", "pinyin": "du3 zi1"}], "赤脚医生": [{"en": "barefoot doctor, farmer with paramedical training (PRC)", "pinyin": "chi4 jiao3 yi1 sheng1"}], "起居": [{"en": "everyday life, regular pattern of life", "pinyin": "qi3 ju1"}], "超泛神论": [{"en": "panentheism, theological theory of God as equal to the Universe while transcending it", "pinyin": "chao1 fan4 shen2 lun4"}], "超重氢": [{"en": "tritium, 3H, radioactive isotope of hydrogen having 2 neutrons in its nucleus, so atomic weight 3", "pinyin": "chao1 zhong4 qing1"}], "路由": [{"en": "routing (in computer networks)", "pinyin": "lu4 you2"}], "跳跳糖": [{"en": "Pop Rocks, popping candy", "pinyin": "tiao4 tiao4 tang2"}], "蹬子": [{"en": "pedal", "pinyin": "deng1 zi5"}], "躲得过初一，躲不过十五": [{"en": "lit. you may go undetected during the new moon, but at full moon you'll be found out (idiom), fig. you can't put it off forever, sooner or later you'll have to deal with it", "pinyin": "duo3 de5 guo4 chu1 yi1 , duo3 bu4 guo4 shi2 wu3"}], "躺倒": [{"en": "to lie down", "pinyin": "tang3 dao3"}], "车把": [{"en": "handlebar (bicycle etc), shaft (rickshaw etc)", "pinyin": "che1 ba3"}], "轧棉": [{"en": "to gin cotton (separate seeds from fiber)", "pinyin": "ya4 mian2"}], "辀": [{"en": "(literary) shaft (of a cart), cart", "pinyin": "zhou1"}], "转来转去": [{"en": "to rove around, to run around in circles, to walk back and forth", "pinyin": "zhuan4 lai2 zhuan4 qu4"}], "转危为安": [{"en": "to turn peril into safety (idiom); to avert a danger (esp. political or medical)", "pinyin": "zhuan3 wei1 wei2 an1"}], "辣条": [{"en": "spicy sticks, a snack food similar to beef jerky but made with flour or dried beancurd instead of meat", "pinyin": "la4 tiao2"}], "辞书": [{"en": "dictionary, encyclopedia", "pinyin": "ci2 shu1"}], "迤": [{"en": "winding", "pinyin": "yi2"}, {"en": "extending to", "pinyin": "yi3"}], "迷乱": [{"en": "confusion", "pinyin": "mi2 luan4"}], "逆来顺受": [{"en": "to resign oneself to adversity (idiom); to grin and bear it, to submit meekly to insults, maltreatment, humiliation etc", "pinyin": "ni4 lai2 shun4 shou4"}], "这末": [{"en": "variant of 這麼|这么[zhe4 me5]", "pinyin": "zhe4 me5"}], "造纸": [{"en": "papermaking", "pinyin": "zao4 zhi3"}], "进接": [{"en": "(computing) access (to a network)", "pinyin": "jin4 jie1"}], "进料": [{"en": "to feed (a machine), foreign goods (abbr. of 進口資料|进口资料)", "pinyin": "jin4 liao4"}], "选士": [{"en": "selected outstanding scholars (in former times), cream of the crop", "pinyin": "xuan3 shi4"}], "遗鸥": [{"en": "(bird species of China) relict gull (Ichthyaetus relictus)", "pinyin": "yi2 ou1"}], "还本": [{"en": "to repay capital", "pinyin": "huan2 ben3"}], "都江堰": [{"en": "Dujiangyan in Sichuan, a famous water engineering project and World Heritage Site, Dujiangyan county level city in Chengdu 成都[Cheng2 du1], Sichuan", "pinyin": "Du1 jiang1 yan4"}], "乡长": [{"en": "village chief, mayor (of village or township)", "pinyin": "xiang1 zhang3"}], "鄐": [{"en": "surname Chu", "pinyin": "Chu4"}], "邬": [{"en": "surname Wu, ancient place name", "pinyin": "Wu1"}], "酴": [{"en": "yeast", "pinyin": "tu2"}], "野炊": [{"en": "to cook a meal over a campfire (usu. for a group of people on an outing), cookout", "pinyin": "ye3 chui1"}], "量刑": [{"en": "to assess punishment, to determine the sentence (on a criminal)", "pinyin": "liang4 xing2"}], "金石": [{"en": "metal and stone, fig. hard objects, inscription on metal or bronze", "pinyin": "jin1 shi2"}], "金秀县": [{"en": "Jinxiu Yao autonomous county in Laibin 來賓|来宾[Lai2 bin1], Guangxi", "pinyin": "Jin1 xiu4 xian4"}], "金融区": [{"en": "financial district", "pinyin": "jin1 rong2 qu1"}], "针线箔篱": [{"en": "wicker sewing basket (dialect)", "pinyin": "zhen1 xian4 bo2 li2"}], "销行": [{"en": "to sell, to be on sale, to be sold", "pinyin": "xiao1 xing2"}], "锤骨柄": [{"en": "manubrium of malleus (handle of hammer bone), connecting ossicles 聽小骨|听小骨 to tympanum 鼓膜", "pinyin": "chui2 gu3 bing3"}], "钔": [{"en": "mendelevium (chemistry)", "pinyin": "men2"}], "铁力木": [{"en": "ironwood (Mesua ferrea)", "pinyin": "tie3 li4 mu4"}], "铸": [{"en": "to cast or found metals", "pinyin": "zhu4"}], "鉴黄": [{"en": "to inspect videos and other media for pornographic content", "pinyin": "jian4 huang2"}], "长期以来": [{"en": "for a long time", "pinyin": "chang2 qi1 yi3 lai2"}], "长条": [{"en": "strip", "pinyin": "chang2 tiao2"}], "长清": [{"en": "Changqing district of Jinan city 濟南市|济南市[Ji3 nan2 shi4], Shandong", "pinyin": "Chang2 qing1"}], "门吸": [{"en": "doorstop", "pinyin": "men2 xi1"}], "门牌": [{"en": "door plate, house number", "pinyin": "men2 pai2"}], "开局": [{"en": "opening (chess etc), early stage of game, match, work, activity etc", "pinyin": "kai1 ju2"}], "关栈费": [{"en": "bonding fee", "pinyin": "guan1 zhan4 fei4"}], "关税壁垒": [{"en": "tariff wall", "pinyin": "guan1 shui4 bi4 lei3"}], "阤": [{"en": "bank, hillside", "pinyin": "tuo2"}], "防闲": [{"en": "to guard", "pinyin": "fang2 xian2"}], "阻绝": [{"en": "to block, to obstruct, to clog", "pinyin": "zu3 jue2"}], "阿克伦": [{"en": "Acheron River in Epirus, northwest Greece", "pinyin": "A1 ke4 lun2"}], "阿托品": [{"en": "atropine C17H23NO3, alkaloid drug derived from deadly nightshade (Atropa belladonna)", "pinyin": "a1 tuo1 pin3"}], "阿拉巴马": [{"en": "Alabama, US state", "pinyin": "A1 la1 ba1 ma3"}], "阿兹特克": [{"en": "Aztec", "pinyin": "A1 zi1 te4 ke4"}], "降雨量": [{"en": "precipitation, quantity of rainfall", "pinyin": "jiang4 yu3 liang4"}], "阵势": [{"en": "battle array, disposition of forces, situation, circumstance", "pinyin": "zhen4 shi4"}], "陶冶": [{"en": "lit. to fire pots and smelt metal, fig. to educate", "pinyin": "tao2 ye3"}], "陆河县": [{"en": "Luhe county in Shanwei 汕尾, Guangdong", "pinyin": "Lu4 he2 xian4"}], "隆隆声": [{"en": "rumble (sound of thunder or gunfire)", "pinyin": "long2 long2 sheng1"}], "隈": [{"en": "bay, cove", "pinyin": "wei1"}], "隋朝": [{"en": "Sui dynasty (581-617)", "pinyin": "Sui2 chao2"}], "隔间": [{"en": "compartment, booth, cubicle, partitioned-off area", "pinyin": "ge2 jian1"}], "雁江": [{"en": "Yanjiang district of Ziyang city 資陽市|资阳市[Zi1 yang2 shi4], Sichuan", "pinyin": "Yan4 jiang1"}], "雄激素": [{"en": "male hormone, testosterone", "pinyin": "xiong2 ji1 su4"}], "雌三醇": [{"en": "estriol", "pinyin": "ci2 san1 chun2"}], "难舍难离": [{"en": "loath to part (idiom); emotionally close and unwilling to separate", "pinyin": "nan2 she3 nan2 li2"}], "震情": [{"en": "circumstances of an earthquake", "pinyin": "zhen4 qing2"}], "震觉": [{"en": "perception of tremor", "pinyin": "zhen4 jue2"}], "霸王硬上弓": [{"en": "to force oneself upon sb (idiom), to rape", "pinyin": "ba4 wang2 ying4 shang4 gong1"}], "灵恩派": [{"en": "Charismatic Movement", "pinyin": "Ling2 en1 pai4"}], "灵药": [{"en": "legendary magic potion of immortals, panacea, fig. wonder solution to a problem", "pinyin": "ling2 yao4"}], "靐": [{"en": "thunder", "pinyin": "bing4"}], "青脚滨鹬": [{"en": "(bird species of China) Temminck's stint (Calidris temminckii)", "pinyin": "qing1 jiao3 bin1 yu4"}], "非同凡响": [{"en": "out of the ordinary", "pinyin": "fei1 tong2 fan2 xiang3"}], "非相对论性": [{"en": "non-relativistic (physics)", "pinyin": "fei1 xiang1 dui4 lun4 xing4"}], "面皮": [{"en": "cheek, face, leather covering (for handbags etc)", "pinyin": "mian4 pi2"}, {"en": "dumpling skin, piecrust", "pinyin": "mian4 pi2"}], "革故鼎新": [{"en": "to discard the old and introduce the new (idiom); to innovate", "pinyin": "ge2 gu4 ding3 xin1"}], "鞴": [{"en": "to saddle a horse", "pinyin": "bei4"}], "顺带": [{"en": "(do sth) in passing, incidentally (while doing sth else)", "pinyin": "shun4 dai4"}], "须要": [{"en": "must, have to", "pinyin": "xu1 yao4"}], "顼": [{"en": "grieved, anxious", "pinyin": "xu4"}], "显宦": [{"en": "high official", "pinyin": "xian3 huan4"}], "显祖": [{"en": "ancestors (old)", "pinyin": "xian3 zu3"}], "风暴潮": [{"en": "storm surge", "pinyin": "feng1 bao4 chao2"}], "饄": [{"en": "old variant of 糖[tang2]", "pinyin": "tang2"}], "首层": [{"en": "first floor, ground floor", "pinyin": "shou3 ceng2"}], "首席法官": [{"en": "Chief Justice", "pinyin": "shou3 xi2 fa3 guan1"}], "首轮": [{"en": "first round (of a competition etc)", "pinyin": "shou3 lun2"}], "馨": [{"en": "fragrant", "pinyin": "xin1"}], "马奶酒": [{"en": "kumis, horse milk wine", "pinyin": "ma3 nai3 jiu3"}], "马山县": [{"en": "Mashan county in Nanning 南寧|南宁[Nan2 ning2], Guangxi", "pinyin": "Ma3 shan1 xian4"}], "驰": [{"en": "to run fast, to speed, to gallop, to disseminate, to spread", "pinyin": "chi2"}], "驳复": [{"en": "to refute", "pinyin": "bo2 fu4"}], "腾挪": [{"en": "to move, to shift, to move out of the way, to divert (money etc) to a different purpose", "pinyin": "teng2 nuo2"}], "骚客": [{"en": "(literary) poet, literati", "pinyin": "sao1 ke4"}], "验钞机": [{"en": "a device used to check money and detect counterfeit bills", "pinyin": "yan4 chao1 ji1"}], "骨瘤": [{"en": "osteoma (benign tumor composed of bone-like material)", "pinyin": "gu3 liu2"}], "高山雀鹛": [{"en": "(bird species of China) Chinese fulvetta (Fulvetta striaticollis)", "pinyin": "gao1 shan1 que4 mei2"}], "高州市": [{"en": "Gaozhou county level city in Maoming 茂名, Guangdong", "pinyin": "Gao1 zhou1 shi4"}], "高扬": [{"en": "held high, elevated, uplift, soaring", "pinyin": "gao1 yang2"}], "高桥留美子": [{"en": "Takahashi Rumiko, Japanese manga artist", "pinyin": "Gao1 qiao2 Liu2 mei3 zi3"}], "高雄": [{"en": "Kaohsiung or Gaoxiong city and county in south Taiwan", "pinyin": "Gao1 xiong2"}], "发辫": [{"en": "braid", "pinyin": "fa4 bian4"}], "魁梧": [{"en": "tall and sturdy", "pinyin": "kui2 wu2"}], "鱼子": [{"en": "fish eggs, roe, caviar", "pinyin": "yu2 zi3"}], "鱼群": [{"en": "shoal of fish", "pinyin": "yu2 qun2"}], "凤冈": [{"en": "Fenggang county in Zunyi 遵義|遵义[Zun1 yi4], Guizhou", "pinyin": "Feng4 gang1"}], "凤眼兰": [{"en": "water hyacinth", "pinyin": "feng4 yan3 lan2"}], "鹅毛笔": [{"en": "quill pen", "pinyin": "e2 mao2 bi3"}], "鹅膏蕈素": [{"en": "amanitin", "pinyin": "e2 gao1 xun4 su4"}], "鹘": [{"en": "falcon, migratory bird", "pinyin": "hu2"}], "䴘": [{"en": "see 鷿鷈|䴙䴘[pi4 ti1]", "pinyin": "ti1"}, {"en": "variant of 鷈|䴘[ti1]", "pinyin": "ti1"}], "丽佳娜": [{"en": "Regina (name)", "pinyin": "Li4 jia1 na4"}], "麦德林": [{"en": "Medellín, city in Colombia", "pinyin": "Mai4 de2 lin2"}], "麻痹": [{"en": "paralysis, palsy, numbness, to benumb, (fig.) to lull, negligent, apathetic", "pinyin": "ma2 bi4"}], "麻醉药品": [{"en": "narcotic", "pinyin": "ma2 zui4 yao4 pin3"}], "黄梨": [{"en": "pineapple, pear", "pinyin": "huang2 li2"}], "黄粉虫": [{"en": "mealworm (Tenebrio molitor)", "pinyin": "huang2 fen3 chong2"}], "黄腰太阳鸟": [{"en": "(bird species of China) crimson sunbird (Aethopyga siparaja)", "pinyin": "huang2 yao1 tai4 yang2 niao3"}], "黄雀": [{"en": "(bird species of China) Eurasian siskin (Spinus spinus)", "pinyin": "huang2 que4"}], "黄饼": [{"en": "yellowcake", "pinyin": "huang2 bing3"}], "黑痣": [{"en": "mole", "pinyin": "hei1 zhi4"}], "点染": [{"en": "to touch up (a piece of writing), to add details (to a painting)", "pinyin": "dian3 ran3"}], "黧黑": [{"en": "(literary) dark", "pinyin": "li2 hei1"}], "鼎鼎": [{"en": "great, very important", "pinyin": "ding3 ding3"}], "鼠": [{"en": "rat, mouse, CL:隻|只[zhi1]", "pinyin": "shu3"}], "齿列矫正": [{"en": "orthodontic treatment, orthodontics", "pinyin": "chi3 lie4 jiao3 zheng4"}], "龄": [{"en": "age, length of experience, membership etc", "pinyin": "ling2"}], "龙安寺": [{"en": "Ryōanji, temple in northwest Kyōto 京都, Japan with famous rock garden", "pinyin": "Long2 an1 si4"}], "龙王": [{"en": "Dragon King (mythology)", "pinyin": "Long2 wang2"}]}